Workbook

Sheet METAS 2025
A1: TIPO DE FECHAMETO | B1: CÓD META | C1: FECHAMENTO | D1: COD | E1: INICIO | F1: FIM | G1: PARÂMETRO | H1: PERÍODO FECHAMENTO | I1: META | J1: PERC DE PRÊMIO | K1: PRODUÇÃO MÊS | L1: CRÉDITO | M1: FILIAL | N1: GERENTE | O1: CHAMADO / E-MAIL | P1: DATA-CHAM/E-MAIL | Q1: OBS | R1: STATUS
A2: 1- AUTOMÁTICO | B2: 7917 | C2: 09 - SETEMBRO | D2: 15332 | E2: 45901 | F2: 45930 | G2: PRODUÇÃO GERAL BANCO MASTER | H2: MENSAL | I2: 0.01 | J2: 0.01 | O2: 1744553 | P2: 45874.467 | R2: TRUE
A3: 1- AUTOMÁTICO | B3: 7985 | C3: 09 - SETEMBRO | D3: 8465/ 1363/3728/3729 | E3: 45870 | F3: 45930 | G3: BANCO AMIGOZ/ PRODUTO TODOS E TABELAS TODAS | H3: BIMESTRAL | I3: 500000 | J3: 0.012 | O3: 1747448 | P3: 07/08/2025 18:08:59 | Q3: Ajustar datas | R3: Ajustar
A4: 1- AUTOMÁTICO | B4: 7985 | C4: 09 - SETEMBRO | D4: 8465/ 1363/3728/3729 | E4: 45870 | F4: 45930 | G4: BANCO AMIGOZ/ PRODUTO TODOS E TABELAS TODAS | H4: BIMESTRAL | I4: 1000000 | J4: 0.022 | O4: 1747448 | P4: 07/08/2025 18:08:59 | Q4: Ajustar datas | R4: Ajustar
A5: 2- MANUAL | B5: 8473 | C5: 09 - SETEMBRO | D5: 6218 | E5: 45889 | F5: 45930 | G5: TODA A PRODUÇÃO Obs: para bonificação nao serão considerados tabelas que possuem regras VIP aprovadas. | H5: FINAL DE CAMPANHA | I5: 0.01 | J5: 0.003 | O5: 1757082 | P5: 22/08/2025 14:16:07 | R5: TRUE
A6: 1- AUTOMÁTICO | B6: 8701 | C6: 09 - SETEMBRO | D6: 12156 | E6: 45901 | F6: 45930 | G6: PAN -PRODU??O TOTAL CONVENIO INSS | I6: 1000 | J6: 0.003 | O6: 1761547 | P6: 29/08/2025 09:38:39 | R6: TRUE
A7: 2- MANUAL | B7: 8506 | C7: 09 - SETEMBRO | D7: 17097 | E7: 45901 | F7: 45930 | G7: CONFORME REGRAS FACTA | H7: MENSAL | I7: 0.01 | J7: 0.006 | O7: 1762550 | P7: 01/09/2025 10:37:18 | R7: TRUE
A8: 1- AUTOMÁTICO | B8: 8524 | C8: 09 - SETEMBRO | D8: 16131 | E8: 45901 | F8: 45930 | G8: CASHCARD -Governo de Alagoas, Prefeitura de Natal ? Em cima de todas as tabelas e produtos | H8: MENSAL | I8: 1000 | J8: 0.015 | O8: 1762584 | P8: 01/09/2025 10:55:25 | R8: TRUE
A9: 1- AUTOMÁTICO | B9: 8531 | C9: 09 - SETEMBRO | D9: 17938 | E9: 45901 | F9: 45930 | G9: MERCANTIL-Iremos considerar toda a produção de cartões RCC e RMC. | H9: MENSAL | I9: 0.01 | J9: 0.01 | O9: 1763007 | P9: 01/09/2025 14:22:56 | R9: FALSE
A10: 1- AUTOMÁTICO | B10: 8523 | C10: 09 - SETEMBRO | D10: 12156 | E10: 45901 | F10: 45930 | G10: TODA PRODUCAO PAN | H10: MENSAL | I10: 1000 | J10: 0.003 | O10: 1763045 | P10: 01/09/2025 14:40:48 | R10: FALSE
A11: 1- AUTOMÁTICO | B11: 8522 | C11: 09 - SETEMBRO | D11: 12776 | E11: 45901 | F11: 45930 | G11: CREFAZ TODA PRODUCAO | H11: FINAL DA CAMPANHA | I11: 0.01 | J11: 0.002 | O11: 1763268 | P11: 01/09/2025 17:04:04 | R11: FALSE
A12: 1- AUTOMÁTICO | B12: 8520 | C12: 09 - SETEMBRO | D12: 14722 | E12: 45901 | F12: 45930 | G12: PRESENÇA BANK - INSS - NOVO | H12: FINAL DA CAMPANHA | I12: 10000 | J12: 0.005 | O12: 1763273 | P12: 01/09/2025 17:08:59 | R12: TRUE
A13: 2- MANUAL | B13: 8505 | C13: 09 - SETEMBRO | D13: 14722 | E13: 45901 | F13: 45930 | G13: FACTA - INSS - NOVO | H13: FINAL DA CAMPANHA | I13: 10000 | J13: 0.0075 | O13: 1763273 | P13: 01/09/2025 17:08:59 | R13: TRUE
A14: 1- AUTOMÁTICO | B14: 8521 | C14: 09 - SETEMBRO | D14: 14722 | E14: 45901 | F14: 45930 | G14: PAN - GOVERNO DE PERNAMBUCO NOVO E REFIN | H14: FINAL DA CAMPANHA | I14: 10000 | J14: 0.005 | O14: 1763273 | P14: 01/09/2025 17:08:59 | R14: TRUE
A15: 1- AUTOMÁTICO | B15: 8516 | C15: 09 - SETEMBRO | D15: 12288 | E15: 45901 | F15: 45930 | G15: CREFAZ -PRODUCAO TOTAL | H15: MENSAL | I15: 0.01 | J15: 0.002 | O15: 1763294 | P15: 01/09/2025 17:10:48 | R15: FALSE
A16: 1- AUTOMÁTICO | B16: 8517 | C16: 09 - SETEMBRO | D16: 12288 | E16: 45901 | F16: 45930 | G16: BANCO OLÉ INSS ? CARTÕES RMC E RCC ? PRODUCAO TOTAL | H16: MENSAL | I16: 0.01 | J16: 0.002 | O16: 1763294 | P16: 01/09/2025 17:10:48 | R16: FALSE
A17: 1- AUTOMÁTICO | B17: 8518 | C17: 09 - SETEMBRO | D17: 12288 | E17: 45901 | F17: 45930 | G17: BANCO SAFRA - TODA OPERAÇÃO NOVA | H17: MENSAL | I17: 0.01 | J17: 0.002 | O17: 1763294 | P17: 01/09/2025 17:10:48 | R17: FALSE
A18: 1- AUTOMÁTICO | B18: 8519 | C18: 09 - SETEMBRO | D18: 12288 | E18: 45901 | F18: 45930 | G18: BANCO MEU CREDBANK TODA PRODUÇÃO | H18: MENSAL | I18: 0.01 | J18: 0.005 | O18: 1763294 | P18: 01/09/2025 17:10:48 | R18: FALSE
... A30: 2- MANUAL | B30: 8502 | C30: 09 - SETEMBRO | D30: 13929 | E30: 45901 | F30: 45930 | G30: CONFORME REGRAS FACTA | H30: MENSAL | I30: 10000 | J30: 0.006 | O30: 1763579 | P30: 02/09/2025 10:00:38 | R30: TRUE
A31: 1- AUTOMÁTICO | B31: 8508 | C31: 09 - SETEMBRO | D31: 15818 / 16763 | E31: 45901 | F31: 45930 | G31: PRODUCAO TOTAL BANCO MASTER | H31: MENSAL | I31: 0.01 | J31: 0.015 | O31: 1763583 | P31: 02/09/2025 10:02:09 | Q31: credito 16763 | R31: FALSE
A32: 1- AUTOMÁTICO | B32: 8508 | D32: 15818 / 16763 | E32: 45901 | F32: 45930 | G32: PRODUCAO TOTAL BANCO MASTER | H32: MENSAL | I32: 1000000 | J32: 0.017 | O32: 1763583 | P32: 02/09/2025 10:02:09 | Q32: credito 16763 | R32: FALSE
A33: 2- MANUAL | B33: 8501 | C33: 09 - SETEMBRO | D33: 8835 | E33: 45901 | F33: 45930 | G33: CONFORME REGRAS FACTA | H33: MENSAL | I33: 10000 | J33: 0.006 | O33: 1763612 | P33: 02/09/2025 10:17:12 | R33: TRUE
A34: 2- MANUAL | B34: 8500 | C34: 09 - SETEMBRO | D34: 17614 | E34: 45901 | F34: 45930 | G34: CONFORME REGRAS FACTA | H34: MENSAL | I34: 10000 | J34: 0.0075 | O34: 1763618 | P34: 02/09/2025 10:22:53 | R34: TRUE
A35: 1- AUTOMÁTICO | B35: 8530 | C35: 09 - SETEMBRO | D35: 12466 | E35: 45901 | F35: 45930 | G35: QUERO MAIS CRÉDITO (SUBSTABELECIDO) | H35: MENSAL | I35: 0.01 | J35: 0.015 | O35: 1763627 | P35: 02/09/2025 10:28:22 | R35: TRUE
A36: 2- MANUAL | B36: 8497 | C36: 09 - SETEMBRO | D36: 13611 | E36: 45901 | F36: 45930 | G36: FACTA – PRODUÇÃO TOTAL CONFORME REGRA DE FECHAMENTO DO BANCO. | H36: MENSAL | I36: 0.01 | J36: 0.0075 | O36: 1763627 | P36: 02/09/2025 10:28:22 | R36: TRUE
A37: 1- AUTOMÁTICO | B37: 8511 | C37: 09 - SETEMBRO | D37: 13611 | E37: 45901 | F37: 45930 | G37: C6 – PRODUÇÃO TOTAL | H37: MENSAL | I37: 0.01 | J37: 0.002 | O37: 1763627 | P37: 02/09/2025 10:28:22 | R37: TRUE
A38: 2- MANUAL | B38: 8529 | C38: 09 - SETEMBRO | D38: 16029 | E38: 45901 | F38: 45930 | G38: BMG – OPERAÇÕES DE CARTÕES RMC E RCC – TODAS AS TABELAS DE SAQUE COMPLEMENTAR. | H38: MENSAL | I38: 0.01 | J38: 0.005 | O38: 1763627 | P38: 02/09/2025 10:28:22 | R38: TRUE
A39: 1- AUTOMÁTICO | B39: 8507 | C39: 09 - SETEMBRO | D39: 16029 | E39: 45901 | F39: 45930 | G39: BANCO MASTER – TODOS OS PRODUTOS E CONVENIOS. | H39: MENSAL | I39: 0.01 | J39: 0.015 | O39: 1763627 | P39: 02/09/2025 10:28:22 | R39: TRUE
A40: 2- MANUAL | B40: 8528 | C40: 09 - SETEMBRO | D40: 16029 | E40: 45901 | F40: 45930 | G40: BANCO DAYCOVAL – Englobar todos os prazos, produtos e convenios que possuam campanha ativa. | H40: MENSAL | I40: 0.01 | J40: 50% DO QUE FOR REPASSADO PELO BANCO. | O40: 1763627 | P40: 02/09/2025 10:28:22 | R40: TRUE
A41: 2- MANUAL | B41: 8498 | C41: 09 - SETEMBRO | D41: 16029 | E41: 45901 | F41: 45930 | G41: FACTA – PRODUÇÃO TOTAL CONFORME REGRA DE FECHAMENTO DO BANCO | H41: MENSAL | I41: 0.01 | J41: 0.0075 | O41: 1763627 | P41: 02/09/2025 10:28:22 | R41: TRUE
A42: 2- MANUAL | B42: 8499 | C42: 09 - SETEMBRO | D42: 17514 | E42: 45901 | F42: 45930 | G42: FACTA – PRODUÇÃO TOTAL CONFORME REGRA DE FECHAMENTO DO BANCO. | H42: MENSAL | I42: 0.01 | J42: 0.0075 | O42: 1763627 | P42: 02/09/2025 10:28:22 | R42: TRUE
A43: 2- MANUAL | B43: 8496 | C43: 09 - SETEMBRO | D43: 17711 | E43: 45901 | F43: 45930 | G43: CONFORME REGRAS FACTA | H43: MENSAL | I43: 10000 | J43: 0.0075 | O43: 1763628 | P43: 02/09/2025 10:28:44 | R43: TRUE
A44: 2- MANUAL | B44: 8495 | C44: 09 - SETEMBRO | D44: 16474 | E44: 45901 | F44: 45930 | G44: CONFORME REGRAS FACTA | H44: MENSAL | I44: 0.01 | J44: 0.005 | O44: 1763639 | P44: 02/09/2025 10:32:47 | R44: TRUE
A45: 1- AUTOMÁTICO | B45: 8558 | C45: 09 - SETEMBRO | D45: 15966 | E45: 45901 | F45: 45930 | G45: EM TODOS OS PRODUTOS E TABELAS BANCO MASTER | H45: MENSAL | I45: 10000 | J45: 0.016 | O45: 1763651 | P45: 02/09/2025 10:36:55 | R45: FALSE
A46: 1- AUTOMÁTICO | B46: 8557 | C46: 09 - SETEMBRO | D46: 13782 | E46: 45901 | F46: 45930 | G46: EM TODOS OS PRODUTOS E TABELAS BANCO AMIGOZ | H46: MENSAL | I46: 10000 | J46: 0.04 | O46: 1763667 | P46: 02/09/2025 10:43:07 | R46: FALSE
A47: 2- MANUAL | B47: 8556 | C47: 09 - SETEMBRO | D47: 14452 | E47: 45901 | F47: 45930 | G47: EM TODOS OS PRODUTOS E TABELAS BANCO DAYCOVAL QUE COMTEMPLAM A CAMPANHA DE BONUS | H47: MENSAL | I47: 10000 | J47: 0.007 | O47: 1763671 | P47: 02/09/2025 10:46:45 | R47: TRUE
A48: 2- MANUAL | B48: 8555 | C48: 09 - SETEMBRO | D48: 16898 | E48: 45901 | F48: 45930 | G48: CONFORME REGRAS FACTA | H48: MENSAL | I48: 0.01 | J48: 0.0045 | O48: 1763679 | P48: 02/09/2025 10:50:14 | R48: TRUE
A49: 2- MANUAL | B49: 8554 | C49: 09 - SETEMBRO | D49: 17859 e 17918 | E49: 45901 | F49: 45930 | G49: CONFORME REGRAS FACTA | H49: MENSAL | I49: 0.01 | J49: 0.006 | O49: 1763690 | P49: 02/09/2025 10:54:34 | Q49: 17918 | R49: TRUE
A50: 1- AUTOMÁTICO | B50: 8553 | C50: 09 - SETEMBRO | D50: 15874 | E50: 45901 | F50: 45930 | G50: QUERO MAIS/ TODAS AS TABELAS E TODOS OS CONV?NIOS | H50: MENSAL | I50: 0.01 | J50: 0.005 | O50: 1763699 | P50: 02/09/2025 10:58:16 | R50: FALSE
A51: 1- AUTOMÁTICO | B51: 8552 | C51: 09 - SETEMBRO | D51: 17865 | E51: 45901 | F51: 45930 | G51: toda produ??o de cartao e cartao beneficio do banco amigoz | H51: MENSAL | I51: 50000 | J51: 0.005 | O51: 1763700 | P51: 02/09/2025 10:58:40 | R51: FALSE
A52: 1- AUTOMÁTICO | B52: 8551 | C52: 09 - SETEMBRO | D52: 16131 | E52: 45901 | F52: 45930 | G52: MEU CASH -conv?nio Prefeitura de Natal | H52: MENSAL | I52: 1000 | J52: 0.015 | O52: 1763723 | P52: 02/09/2025 11:10:09 | R52: FALSE
A53: 1- AUTOMÁTICO | B53: 8550 | C53: 09 - SETEMBRO | D53: 16131 | E53: 45901 | F53: 45930 | G53: Iremos considerar toda a prosução Governo de Alagoas-CASHCARD | H53: MENSAL | I53: 1000 | J53: 0.0025 | O53: 1763864 | P53: 02/09/2025 12:50:22 | R53: FALSE
A54: 1- AUTOMÁTICO | B54: 8549 | C54: 09 - SETEMBRO | D54: 6905 | E54: 45901 | F54: 45930 | G54: BANCO DAYCOVAL, CONVENIO PREF UBERABA, TODAS AS TABELAS E PRAZOS | H54: MENSAL | I54: 500000 | J54: 0.006 | O54: 1763996 | P54: 02/09/2025 14:22:39 | R54: FALSE
A55: 2- MANUAL | B55: 8548 | C55: 09 - SETEMBRO | D55: 9207 / 16893 / 15896 / 15942 | E55: 45901 | F55: 45930 | G55: CONFORME REGRAS FACTA | H55: MENSAL | I55: 250000 | J55: 0.005 | O55: 1764459 | P55: 03/09/2025 09:31:53 | Q55: 9207. | R55: TRUE
A56: 1- AUTOMÁTICO | B56: 8547 | C56: 09 - SETEMBRO | D56: 9207 / 16893 / 15896 / 15942 | E56: 45901 | F56: 45930 | G56: MEU CREDBANK - FGTS | H56: MENSAL | I56: 20000 | J56: 0.01 | O56: 1764463 | P56: 03/09/2025 09:33:29 | Q56: credito 9207 | R56: FALSE
A57: 2- MANUAL | B57: 8546 | C57: 09 - SETEMBRO | D57: 16238 | E57: 45901 | F57: 45930 | G57: MASTER-TODOS - EXCETO FGTS E INSS | H57: MENSAL | I57: 0.01 | J57: 0.015 | O57: 1764465 | P57: 03/09/2025 09:35:30 | R57: TRUE
A58: 1- AUTOMÁTICO | B58: 8545 | C58: 09 - SETEMBRO | D58: 4175/6961 | E58: 45901 | F58: 45930 | G58: AMIGOZ-TODA PRODUCAO | H58: MENSAL | I58: 100000 | J58: 0.015 | O58: 1764491 | P58: 03/09/2025 09:51:09 | R58: FALSE
A59: 1- AUTOMÁTICO | B59: 8544 | C59: 09 - SETEMBRO | D59: 15802 | E59: 45901 | F59: 45930 | G59: CART?O CONSIGNADO E CART?O BENEFICIO-QUERO MAIS | H59: MENSAL | I59: 1000 | J59: 0.015 | O59: 1764579 | P59: 03/09/2025 10:37:43 | R59: FALSE
A60: 1- AUTOMÁTICO | B60: 8543 | C60: 09 - SETEMBRO | D60: 14363 | E60: 45901 | F60: 45930 | G60: CART?O CONSIGNADO E CART?O BENEFICIO-QUERO MAIS | H60: MENSAL | I60: 1000 | J60: 0.015 | O60: 1764582 | P60: 03/09/2025 10:40:22 | R60: FALSE
A61: 1- AUTOMÁTICO | B61: 8542 | C61: 09 - SETEMBRO | D61: 8476 | E61: 45901 | F61: 45930 | G61: CART?O CONSIGNADO E CART?O BENEFICIO-QUERO MAIS | H61: MENSAL | I61: 1000 | J61: 0.011 | O61: 1764590 | P61: 03/09/2025 10:43:05 | R61: FALSE
A62: 2- MANUAL | B62: 8541 | C62: 09 - SETEMBRO | D62: 17102 | E62: 45901 | F62: 45930 | G62: CONFORME REGRAS FACTA | H62: MENSAL | I62: 0.01 | J62: 0.0025 | O62: 1764602 | P62: 03/09/2025 10:50:36 | R62: TRUE
A63: 1- AUTOMÁTICO | B63: 8539 | C63: 09 - SETEMBRO | D63: 11652 | E63: 45901 | F63: 45930 | G63: TODAS AS TABELAS COM SEGURO DE CONTRATO NOVO INSS MEU CRED BANK | H63: MENSAL | I63: 0.01 | J63: 0.01 | O63: 1764918 | P63: 03/09/2025 14:21:39 | R63: FALSE
A64: 1- AUTOMÁTICO | B64: 8540 | C64: 09 - SETEMBRO | D64: 11652 | E64: 45901 | F64: 45930 | G64: TODOS OS CARTÕES CONSIGNADO E BENEFICIO DO INSS AMIGOZ | H64: MENSAL | I64: 0.01 | J64: 0.03 | O64: 1764918 | P64: 03/09/2025 14:21:39 | R64: FALSE
A65: 1- AUTOMÁTICO | B65: 8535 | C65: 09 - SETEMBRO | D65: 4629 | E65: 45901 | F65: 45930 | G65: TODAS AS TABELAS COM SEGURO DE CONTRATO NOVO INSS MEU CRED BANK | H65: MENSAL | I65: 0.01 | J65: 0.01 | O65: 1764924 | P65: 03/09/2025 14:25:25 | R65: FALSE
A66: 1- AUTOMÁTICO | B66: 8536 | C66: 09 - SETEMBRO | D66: 4629 | E66: 45901 | F66: 45930 | G66: BONUS DO REFIN DA PORTABILIDADE MEU CRED BANK | H66: MENSAL | I66: 0.01 | J66: 0.005 | O66: 1764924 | P66: 03/09/2025 14:25:25 | R66: FALSE
A67: 1- AUTOMÁTICO | B67: 8537 | C67: 09 - SETEMBRO | D67: 4629 | E67: 45901 | F67: 45930 | G67: TODOS OS CARTÕES CONSIGNADO E BENEFICIO DO INSS AMIGOZ | H67: MENSAL | I67: 0.01 | J67: 0.03 | O67: 1764924 | P67: 03/09/2025 14:25:25 | R67: FALSE
A68: 1- AUTOMÁTICO | B68: 8538 | C68: 09 - SETEMBRO | D68: 4629 | E68: 45901 | F68: 45930 | G68: CARTÃO BENEFICIO E CONSIGNADO COM E SEM SEGURO - BMG | H68: MENSAL | I68: 0.01 | J68: 0.005 | O68: 1764924 | P68: 03/09/2025 14:25:25 | R68: FALSE
A69: 2- MANUAL | B69: 8565 | C69: 09 - SETEMBRO | D69: 12633 | E69: 45901 | F69: 45930 | G69: FACTA ? PRODUÇAÕ TOTAL REFIN DA PORTABILIDADE | H69: MENSAL | I69: 0.01 | J69: 0.003 | O69: 1765242 | P69: 03/09/2025 17:42:37 | R69: TRUE
A70: 1- AUTOMÁTICO | B70: 8587 | C70: 09 - SETEMBRO | D70: 12633 | E70: 45901 | F70: 45930 | G70: DIGIO ? PRODUÇAÕ TOTAL PORTABILIDADE E REFIN DA PORTABILIDADE | H70: MENSAL | I70: 0.01 | J70: 0.002 | O70: 1765242 | P70: 03/09/2025 17:42:37 | R70: TRUE
A71: 1- AUTOMÁTICO | B71: 8576 | C71: 09 - SETEMBRO | D71: 15932 | E71: 45901 | F71: 45930 | G71: PRESENÇA BANK- PRODUÇÃO TOTAL NAS TABELAS QUE RECEBEMOS BONIFICACOES - | H71: MENSAL | I71: 0.01 | J71: 75% DO QUE RECEB | O71: 1765248 | P71: 03/09/2025 17:48:36 | R71: FALSE
A72: 1- AUTOMÁTICO | B72: 8572 | C72: 09 - SETEMBRO | D72: 15932 | E72: 45901 | F72: 45930 | G72: AMIGOZ ? PRODUÇÃO TOTAL | H72: MENSAL | I72: 0.01 | J72: 0.035 | O72: 1765248 | P72: 03/09/2025 17:48:36 | R72: FALSE
A73: 1- AUTOMÁTICO | B73: 8575 | C73: 09 - SETEMBRO | D73: 15932 | E73: 45901 | F73: 45930 | G73: MEU CREDBANK ? PRODUCAO TOTAL EM TODOS OS PRODUTOS ( exceto refin da port | H73: MENSAL | I73: 0.01 | J73: 0.01 | O73: 1765248 | P73: 03/09/2025 17:48:36 | R73: FALSE
A74: 1- AUTOMÁTICO | B74: 8574 | C74: 09 - SETEMBRO | D74: 15932 | E74: 45901 | F74: 45930 | G74: MEU CREDBANK - PRODUÇÃO TOTAL REFIN DA PORT | H74: MENSAL | I74: 0.01 | J74: 0.0075 | O74: 1765248 | P74: 03/09/2025 17:48:36 | R74: FALSE
A75: 1- AUTOMÁTICO | B75: 8573 | C75: 09 - SETEMBRO | D75: 15932 | E75: 45901 | F75: 45930 | G75: CREFAZ ? PRODUÇÃO TOTA | H75: MENSAL | I75: 0.01 | J75: 0.002 | O75: 1765248 | P75: 03/09/2025 17:48:36 | R75: FALSE
A76: 1- AUTOMÁTICO | B76: 8577 | C76: 09 - SETEMBRO | D76: 5804 | E76: 45901 | F76: 45930 | G76: BANCO MEU CREDBANK ? INSS APENAS TABELAS COM SEGURO | H76: MENSAL | I76: 0.01 | J76: 0.005 | O76: 1765249 | P76: 03/09/2025 17:50:31 | R76: FALSE
A77: 1- AUTOMÁTICO | B77: 8578 | C77: 09 - SETEMBRO | D77: 18221 | E77: 45901 | F77: 45930 | G77: BMG PRODUCAO TOTAL | H77: MENSAL | I77: 0.01 | J77: 0.0015 | O77: 1765250 | P77: 03/09/2025 17:51:47 | R77: FALSE
A78: 1- AUTOMÁTICO | B78: 8580 | C78: 09 - SETEMBRO | D78: 16713 | E78: 45901 | F78: 45930 | G78: TODA PRODUCAO BMG | H78: MENSAL | I78: 0.01 | J78: 0.02 | O78: 1765845 | P78: 04/09/2025 13:41:59 | R78: FALSE
A79: 1- AUTOMÁTICO | B79: 8571 | C79: 09 - SETEMBRO | D79: 16713 | E79: 45901 | F79: 45930 | G79: TODA PRODUCAO AMIGOZ | H79: MENSAL | I79: 0.01 | J79: 0.04 | O79: 1765845 | P79: 04/09/2025 13:41:59 | R79: FALSE
A80: 1- AUTOMÁTICO | B80: 8579 | C80: 09 - SETEMBRO | D80: 16713 | E80: 45901 | F80: 45930 | G80: TODA PRODUCAO MASTER | H80: MENSAL | I80: 0.01 | J80: 0.02 | O80: 1765845 | P80: 04/09/2025 13:41:59 | R80: FALSE
A81: 1- AUTOMÁTICO | B81: 8564 | C81: 09 - SETEMBRO | D81: 14750 | E81: 45901 | F81: 45930 | G81: FACTA CONFORME REGULAMENTO | H81: MENSAL | I81: 0.01 | J81: 0.005 | O81: 1765852 | P81: 04/09/2025 13:51:56 | R81: FALSE
A82: 1- AUTOMÁTICO | B82: 8570 | C82: 09 - SETEMBRO | D82: 14750 | E82: 45901 | F82: 45930 | G82: TODA A PRODUÇÃO BANCO AMIGOZ | H82: MENSAL | I82: 0.01 | J82: 0.01 | O82: 1765852 | P82: 04/09/2025 13:51:56 | R82: FALSE
A83: 1- AUTOMÁTICO | B83: 8569 | C83: 09 - SETEMBRO | D83: 8437 | E83: 45901 | F83: 45930 | G83: TODA A PRODU??OBANCO AMIGOZ | H83: MENSAL | I83: 0.01 | J83: 0.01 | O83: 1765854 | P83: 04/09/2025 13:53:56 | R83: FALSE
A84: 1- AUTOMÁTICO | B84: 8568 | C84: 09 - SETEMBRO | D84: 9648 | E84: 45901 | F84: 45930 | G84: TODA A PRODU??O AMIGOZ | H84: MENSAL | I84: 0.01 | J84: 0.01 | O84: 1765858 | P84: 04/09/2025 13:55:58 | R84: FALSE
A85: 1- AUTOMÁTICO | B85: 8566 | C85: 09 - SETEMBRO | D85: 16153 | E85: 45901 | F85: 45930 | G85: TODA A PRODU??O AMIGOZ | H85: MENSAL | I85: 0.01 | J85: 0.01 | O85: 1765863 | P85: 04/09/2025 13:58:51 | R85: FALSE
A86: 1- AUTOMÁTICO | B86: 8567 | C86: 09 - SETEMBRO | D86: 16502 | E86: 45901 | F86: 45930 | G86: TODA A PRODU??O AMIGOZ | H86: MENSAL | I86: 0.01 | J86: 0.01 | O86: 1765863 | P86: 04/09/2025 13:58:51 | R86: FALSE
A87: 2- MANUAL | B87: 8581 | C87: 09 - SETEMBRO | D87: 7640 | E87: 45901 | F87: 45930 | G87: BANCO CAPITAL CONSIG(gov pi,gov ma,pref s?o luiz,pref picos-pi) | H87: MENSAL | I87: 0.01 | J87: 0.015 | O87: 1765866 | P87: 04/09/2025 14:00:35 | R87: TRUE
A88: 1- AUTOMÁTICO | B88: 8582 | C88: 09 - SETEMBRO | D88: 15169 | E88: 45901 | F88: 45930 | G88: PRODU??O TOTAL SIMPLIX - FGTS | H88: MENSAL | I88: 1000 | J88: 0.005 | O88: 1765872 | P88: 04/09/2025 14:05:00 | R88: FALSE
A89: 1- AUTOMÁTICO | B89: 8583 | C89: 09 - SETEMBRO | D89: 17555 | E89: 45901 | F89: 45930 | G89: TODA A PRODU??O Cart?o Bmg inss e cart?o benef?cio . | H89: MENSAL | I89: 100000 | J89: 0.005 | O89: 1765877 | P89: 04/09/2025 14:10:30 | R89: FALSE
A90: 2- MANUAL | B90: 8563 | C90: 09 - SETEMBRO | D90: 16239 | E90: 45901 | F90: 45930 | G90: PRODU??O FACTA CONFORME REGRA | H90: MENSAL | I90: 0.01 | J90: 0.0075 | O90: 1765911 | P90: 04/09/2025 14:25:57 | R90: TRUE
A91: 2- MANUAL | B91: 8562 | C91: 09 - SETEMBRO | D91: 17574 | E91: 45901 | F91: 45930 | G91: CONFORME REGRAS FACTA | H91: MENSAL | I91: 0.01 | J91: 0.005 | O91: 1766024 | P91: 04/09/2025 15:39:42 | R91: TRUE
A92: 2- MANUAL | B92: 8561 | C92: 09 - SETEMBRO | D92: 7769 | E92: 45901 | F92: 45930 | G92: Conforme regra Facta para bonifica??o | H92: MENSAL | I92: 1000 | J92: 0.003 | O92: 1766163 | P92: 04/09/2025 17:17:54 | R92: TRUE
A93: 2- MANUAL | B93: 8560 | C93: 09 - SETEMBRO | D93: 11937 / 12021 | E93: 45901 | F93: 45930 | G93: CONFORME REGRAS FACTA | H93: MENSAL | I93: 0.01 | J93: 0.005 | O93: 1766424 | P93: 05/09/2025 10:34:53 | R93: TRUE
A94: 1- AUTOMÁTICO | B94: 8584 | C94: 09 - SETEMBRO | D94: 6832 | E94: 45901 | F94: 45930 | G94: DIGIO PRODUCAO TOTAL | H94: MENSAL | I94: 100000 | J94: 0.005 | O94: 1766442 | P94: 05/09/2025 10:46:50 | R94: FALSE
A95: 1- AUTOMÁTICO | B95: 8585 | C95: 09 - SETEMBRO | D95: 17142 | E95: 45901 | F95: 45930 | G95: MASTER-TODOS OS PRODUTOS E PRAZOS | H95: MENSAL | I95: 30000 | J95: 0.005 | O95: 1766458 | P95: 05/09/2025 10:58:52 | R95: FALSE
A96: 1- AUTOMÁTICO | B96: 8586 | C96: 09 - SETEMBRO | D96: 15087 | E96: 45901 | F96: 45930 | G96: REFIN DA PORT \ MEUCREDBANK\INSS\96 E 84 X | H96: MENSAL | I96: 30000 | J96: 0.0025 | O96: 1766471 | P96: 05/09/2025 11:03:20 | R96: FALSE
A97: 2- MANUAL | B97: 8559 | C97: 09 - SETEMBRO | D97: 16382 | E97: 45901 | F97: 45930 | G97: CONFORME REGRAS FACTA | H97: MENSAL | I97: 0.01 | J97: 0.0075 | O97: 1766482 | P97: 05/09/2025 11:07:37 | R97: TRUE
A98: 1- AUTOMÁTICO | B98: 8313 | C98: 09 - SETEMBRO | D98: 14750 | E98: 45901 | F98: 45930 | G98: C6 PRODUCAO TOTAL | H98: MENSAL | I98: 0.01 | J98: 0.002 | M98: FILIAL BH2 | N98: TIAGO ROGANA FERNANDES | O98: 1766493 | P98: 05/09/2025 11:13:06 | R98: FALSE
A99: 1- AUTOMÁTICO | B99: 8614 | C99: 09 - SETEMBRO | D99: 1212 | E99: 45901 | F99: 45991 | G99: DIGIO PRODUCAO TOTAL | H99: MENSAL | I99: 0.01 | J99: 0.005 | M99: FILIAL SAO LUIZ | N99: WANDER CRISTIAN ANTUNES BARBOSA | O99: 1766691 | P99: 05/09/2025 14:01:10 | R99: FALSE
A100: 1- AUTOMÁTICO | B100: 8612 | C100: 09 - SETEMBRO | D100: 7882 | E100: 45901 | F100: 45930 | G100: PORTABILIDADE / BANCO C6 / CONVENIO INSS | H100: MENSAL | I100: 0.01 | J100: 0.02 | M100: FILIAL VITORIA | N100: RAHYZA EUSTACHIO DA SILVA | O100: 1766695 | P100: 05/09/2025 14:05:30 | R100: FALSE
A101: 1- AUTOMÁTICO | B101: 8611 | C101: 09 - SETEMBRO | D101: 15096 | E101: 45901 | F101: 45930 | G101: Banco c6(novo,port,refin da port) | H101: MENSAL | I101: 0.01 | J101: 0.02 | M101: FILIAL BH2 | N101: WANDA MARIA MARTINS | O101: 1766767 | P101: 05/09/2025 15:05:35 | R101: FALSE
A102: 1- AUTOMÁTICO | B102: 8610 | C102: 09 - SETEMBRO | D102: 15313 | E102: 45901 | F102: 45930 | G102: producao total c6 | H102: MENSAL | I102: 0.01 | J102: 0.002 | M102: FILIAL BH2 | N102: TIAGO ROGANA FERNANDES | O102: 1766777 | P102: 05/09/2025 15:09:14 | R102: FALSE
A103: 2- MANUAL | B103: 8596 | C103: 09 - SETEMBRO | D103: 15313 | E103: 45901 | F103: 45930 | G103: FACTA CONFORME REGULAMENTO | H103: MENSAL | I103: 0.01 | J103: 0.005 | M103: FILIAL BH2 | N103: WANDA MARIA MARTINS | O103: 1766777 | P103: 05/09/2025 15:09:14 | R103: TRUE
A104: 2- MANUAL | B104: 8595 | C104: 09 - SETEMBRO | D104: 13977 | E104: 45901 | F104: 45930 | G104: FACTA CONFORME REGULAMENTO | H104: MENSAL | I104: 0.01 | J104: 0.005 | M104: FILIAL UBERLANDIA | N104: JOAO EURICO PINHEIRO IGNACIO DOS SANTOS | O104: 1766787 | P104: 05/09/2025 15:14:40 | R104: TRUE
A105: 1- AUTOMÁTICO | B105: 8608 | C105: 09 - SETEMBRO | D105: 13977 | E105: 45901 | F105: 45930 | G105: AMIGOZ PRODUCAO TOTAL | H105: MENSAL | I105: 0.01 | J105: 0.035 | M105: FILIAL SALVADOR | N105: ANA BEATRIZ PIMENTA LISBOA | O105: 1766787 | P105: 05/09/2025 15:14:40 | R105: FALSE
A106: 2- MANUAL | B106: 8609 | C106: 09 - SETEMBRO | D106: 13977 | E106: 45901 | F106: 45930 | G106: DAYCOVAL PRODUCAO TOTAL -85% SOBRE RECEBIDO | H106: MENSAL | I106: 0.01 | J106: 85% DO RECEBIDO | M106: FILIAL BH2 | N106: WANDA MARIA MARTINS | O106: 1766787 | P106: 05/09/2025 15:14:40 | R106: TRUE
A107: 2- MANUAL | B107: 8607 | C107: 09 - SETEMBRO | D107: 1328 | E107: 45901 | F107: 45930 | G107: TODA PRODU??O, EXCETO TABELAS QUE POSSUEM REGRA VIP APROVADA | H107: MENSAL | I107: 300000 | J107: 0.003 | M107: FILIAL BH2 | N107: WANDA MARIA MARTINS | O107: 1766860 | P107: 05/09/2025 16:03:52 | R107: TRUE
A108: 1- AUTOMÁTICO | B108: 8606 | C108: 09 - SETEMBRO | D108: 3594 | E108: 45901 | F108: 45930 | G108: TODA PRODU??O | H108: MENSAL | I108: 200000 | J108: 200 | M108: FILIAL MC | N108: MAURICIO PEREIRA DOS SANTOS | O108: 1766867 | P108: 05/09/2025 16:20:59 | R108: FALSE
A109: 1- AUTOMÁTICO | B109: 8605 | C109: 09 - SETEMBRO | D109: 12068 | 17777 | E109: 45901 | F109: 45930 | G109: TODA PRODUCAO | H109: MENSAL | I109: 200000 | J109: 200 | M109: FILIAL CUIABA | N109: JULIANA DE ALMEIDA SIMPLICIO ROCHA | O109: 1766884 | P109: 05/09/2025 16:40:32 | Q109: credito 12068 | R109: FALSE
A110: 1- AUTOMÁTICO | B110: 8604 | C110: 09 - SETEMBRO | D110: 11599 | 17823 | E110: 45901 | F110: 45930 | G110: TODA PRODUCAO | H110: MENSAL | I110: 200000 | J110: 200 | M110: FILIAL BH2 | N110: ALESSANDRO MACHADO DA SILVA | O110: 1766890 | P110: 05/09/2025 16:44:13 | Q110: credito 11599 | R110: FALSE
A111: 2- MANUAL | B111: 8594 | C111: 09 - SETEMBRO | D111: 3566 | E111: 45901 | F111: 45930 | G111: FACTA INSS PORT / REFIN DA PORT /REFIN / NOVO / FGTS | H111: MENSAL | I111: 500000 | J111: 0.007 | M111: FILIAL BH2 | N111: ALESSANDRO MACHADO DA SILVA | O111: 1766904 | P111: 05/09/2025 16:49:54 | R111: TRUE
...

Sheet FILTRO
A1: CÓD CHAMADO | C1: CHAMADO
C2: COD CORRETOR | D2: PERIODO | E2: PARÂMETRO | F2: META | G2: PERC DE PRÊMIO | H2: MENSAGEM
A3: 1763007 | C3: {=_xlfn._xlws.FILTER(CHAMADOS!$I2:$I1500,CHAMADOS!$A2:$A1500=$A3,"Erro")} -> 17938 | D3: {=_xlfn._xlws.FILTER(CHAMADOS!$M2:$M1500,CHAMADOS!$A2:$A1500=$A3,"Erro")} -> 01/09 a 31/12 | E3: {=_xlfn._xlws.FILTER(CHAMADOS!$K2:$K1500,CHAMADOS!$A2:$A1500=$A3,"Erro")} -> DESCRI?AO | F3: {=_xlfn._xlws.FILTER(CHAMADOS!$J2:$J1500,CHAMADOS!$A2:$A1500=$A3,"Erro")} -> SEM META | G3: {=_xlfn._xlws.FILTER(CHAMADOS!$L2:$L1500,CHAMADOS!$A2:$A1500=$A3,"Erro")} -> 0,20% | H3: {=_xlfn._xlws.FILTER(CHAMADOS!$O2:$O1500,CHAMADOS!$A2:$A1500=$A3,"Erro")} -> Remetente - () Boa tarde! Iremos considerar toda a produção de cartões RCC e RMC. CODIGO DO CORRETOR: 17938 PERIODO: 01/09 a 31/12 TIPO DE FECHAMENTO: MENSAL META: SEM META PERCENTUAL DE PREMIO: 0,20% PARAMETRO: DESCRIÇAO ; Remetente - () Josi, boa tarde. Campanha parametrizada. Meta 8531,8532,8533,8534 ; Remetente - () Bom dia! Por gentielza alterar o percentual da camapanha. PERCENTUAL DE PREMIO: 0,40% PERIODO: 01/09 a 31/12; | I3: {=_xlfn.TEXTSPLIT(H3,";",";")} -> Remetente - () Boa tarde! Iremos considerar toda a produção de cartões RCC e RMC. CODIGO DO CORRETOR: 17938 PERIODO: 01/09 a 31/12 TIPO DE FECHAMENTO: MENSAL META: SEM META PERCENTUAL DE PREMIO: 0,20% PARAMETRO: DESCRIÇAO | J3: Remetente - () Josi, boa tarde. Campanha parametrizada. Meta 8531,8532,8533,8534 | K3: Remetente - () Bom dia! Por gentielza alterar o percentual da camapanha. PERCENTUAL DE PREMIO: 0,40% PERIODO: 01/09 a 31/12
C5: PLANILHA
C6: COD | D6: PERIODO | E6: PARÂMETRO | F6: META | G6: PERC DE PRÊMIO | H6: TIPO | I6: CÓD META
A7: VOLTAR | C7: {=_xlfn._xlws.FILTER('METAS 2025'!$D2:$D238,'METAS 2025'!$O2:$O238=$A$3)} -> 17938 | D7: {=_xlfn.CONCAT( TEXT(_xlfn._xlws.FILTER('METAS 2025'!$E2:$E238,'METAS 2025'!$O2:$O238=$A$3),"dd/mm/aaaa"), " a ", TEXT(_xlfn._xlws.FILTER('METAS 2025'!$F2:$F238,'METAS 2025'!$O2:$O238=$A$3),"dd/mm/aaaa"))} -> 01/09/2025 a 30/09/2025 | E7: {=_xlfn._xlws.FILTER('METAS 2025'!$G2:$G238,'METAS 2025'!$O2:$O238=$A$3)} -> MERCANTIL-Iremos considerar toda a produção de cartões RCC e RMC. | F7: {=_xlfn._xlws.FILTER('METAS 2025'!$I2:$I238,'METAS 2025'!$O2:$O238=$A$3)} -> 0.01 | G7: {=_xlfn._xlws.FILTER('METAS 2025'!$J2:$J238,'METAS 2025'!$O2:$O238=$A$3)} -> 0.01 | H7: {=_xlfn._xlws.FILTER('METAS 2025'!$H2:$H238,'METAS 2025'!$O2:$O238=$A$3)} -> MENSAL | I7: {=_xlfn._xlws.FILTER('METAS 2025'!$B2:$B238,'METAS 2025'!$O2:$O238=$A$3)} -> 8531

Sheet CHAMADOS
A1: COD. CHAMADO | B1: CATEGORIA | C1: TITULO | D1: SOLICITANTE | E1: RESPONSAVEL | F1: SITUACAO | G1: DATA ULTIMA MENSAGEM | H1: DATA CHAMADO | I1: CODIGO DO CORRETOR | J1: META | K1: PARAMETRO | L1: PERCENTUAL DE PREMIO | M1: PERIODO | N1: TIPO DE FECHAMENTO | O1: MENSAGEM
A2: 1774323 | B2: PARAMETRIZACAO DE CAMPANHA | C2: PARAMETRIZAR CAMPANHA - ID | D2: JOSIANE ARAUJO TEIXEIRA (U) | E2: Cinthia Gomes da Silva | F2: Aberto | G2: 24/09/2025 10:51:14 | H2: 17/09/2025 15:45:46 | I2: 3349 / 11938 | J2: DESCRI?AO | K2: DESCRI?AO | L2: DESCRI??O | M2: 01/09 a 30/09 | N2: MENSAL | O2: Remetente - () Boa tarde! Parametro: Toda a produção paga da parceira será contabilizada independente do produto para o atingimento da meta . Porém a bonificação nas duas escalas seja 0.10% ou 0.20% dependendo da meta atingida conforme pleito acima só deverá ser paga sobre a produção de contratos novos / convênio Inss / prazo máximo 84 meses / tabela normal com exceção do banco Itaú ( pois está na regra VIP) Lembrando que a campanha em questão contempla a soma dos 2 códigos que a parceira tem conosco ID 3349 / ID 11938. Meta / bonificação 300.000,00 - 0,10 500.000,00 - 0,20 Abonificação sera paga no codigo ID 3349 CODIGO DO CORRETOR: 3349 / 11938 PERIODO: 01/09 A 30/09 TIPO DE FECHAMENTO: MENSAL META: DESCRIÇAO PERCENTUAL DE PREMIO: DESCRIÇÃO PARAMETRO: DESCRIÇAO ; Remetente - () Josi, bom dia. Reforço que não tem como considerar tabela normal de todos bancos, pois cada um possui sua particularidade. ; Remetente - () Em tempo Portanto foi considerados todas as tabelas do INSS-NOVO- 84X;
A3: 1778432 | B3: PARAMETRIZACAO DE CAMPANHA | C3: CAMPANHA SETEMBRO I COD 9132 I BANCO DIGIO | D3: BIANCA CRISTIANE SOARES SANTOS TERENCIO (U) | F3: Aberto | G3: 24/09/2025 10:00:40 | H3: 24/09/2025 10:00:40 | I3: 9132 | J3: 1.000,00 | K3: anco Digio ? Todos os Produtos ? Todos os Prazos ? Conv?nio INSS ? Todas as Tabelas | L3: 0,20 | M3: 22/09 A 30/09 | N3: MENSAL | O3: Remetente - () Bom dia ! Gentileza parametrizar conforme solicitado. Banco Digio ? Todos os Produtos ? Todos os Prazos ? Convênio INSS ? Todas as Tabelas CODIGO DO CORRETOR: 9132 PERIODO: 22/09 A 30/09 TIPO DE FECHAMENTO: MENSAL META: 1.000,00 PERCENTUAL DE PREMIO: 0,20 PARAMETRO: anco Digio ? Todos os Produtos ? Todos os Prazos ? Convênio INSS ? Todas as Tabelas ;
A4: 1778429 | B4: PARAMETRIZACAO DE CAMPANHA | C4: PARAMAETRIZAR CAMPANHA BANCO PAN - ID 15503 | D4: JOSIANE ARAUJO TEIXEIRA (U) | F4: Aberto | G4: 24/09/2025 09:56:34 | H4: 24/09/2025 09:56:34 | I4: 15503 | J4: SEM META | K4: toda a produ??o de CONVENIOS PUBLICOS | L4: 0,40% | M4: 01/09 a 30/09 | N4: MENSAL | O4: Remetente - () Bom dia! CODIGO DO CORRETOR: 15503 PERIODO: 01/09 A 30/09 TIPO DE FECHAMENTO: MENSAL META: SEM META PERCENTUAL DE PREMIO: 0,40% PARAMETRO: toda a produção de CONVENIOS PUBLICOS ;
A5: 1772674 | B5: PARAMETRIZACAO DE CAMPANHA | C5: PARAMETRIZAR CAMPANHA - ID 6448 / 8737 | D5: JOSIANE ARAUJO TEIXEIRA (U) | E5: Cinthia Gomes da Silva | F5: Aberto | G5: 24/09/2025 09:10:23 | H5: 16/09/2025 09:42:36 | I5: 6448 / 8737 | J5: 760.000,00 | K5: TODAS AS TABELAS E PRODUTOS. DESCONSIDERAR PORT, VIP, E GRUPO 001 P/ CALCULO DO B?NUS | L5: 0,30% | M5: 01/08 A 30/09 | N5: TRIMESTRAL | O5: Remetente - () Bom dia! A bonificação sera paga no codigo ID 6448 CODIGO DO CORRETOR: 6448 / 8737 PERIODO: 01/08 A 30/09 TIPO DE FECHAMENTO: TRIMESTRAL META: 760.000,00 PERCENTUAL DE PREMIO: 0,30% PARAMETRO: TODAS AS TABELAS E PRODUTOS. DESCONSIDERAR PORT, VIP, E GRUPO 001 P/ CALCULO DO BÔNUS ; Remetente - () Boa tarde! PARAMETRO: TODAS AS TABELAS E PRODUTOS DE TODOS OS BANCO ( DESCONSIDERAR PORT, VIP, E GRUPO 001 P/ CALCULO DO BÔNUS ); Remetente - () Josi, boa tarde. Campanha parametrizada. codigo 8807 ; Remetente - () Prezados, bom dia! Favor desativar campanha. ;
A6: 1777951 | B6: PARAMETRIZACAO DE CAMPANHA | C6: CAMPANHA FACTA I 14034 | D6: BARBARA VIRGINIA RAIMUNDI DE SIQUEIRA (U) | F6: Aberto | G6: 23/09/2025 14:35:53 | H6: 23/09/2025 14:33:20 | I6: 14034 | J6: SEM META | K6: CONFORME REGRAS FACTA | L6: 0,50% | M6: 01/09 a 30/09 | N6: MENSAL | O6: Remetente - () Prezados(a), boa tarde ! Gentileza parametrizar campanha conforme solicitado pela GC Larissa Sobral e diretor Danilo Ferreira. CODIGO DO CORRETOR: 14034 PERIODO: 01/09 À 30/09 TIPO DE FECHAMENTO: MENSAL META: SEM META PERCENTUAL DE PREMIO: 0,50% PARAMETRO: CONFORME REGRAS FACTA ; Remetente - () considerar o código 13819 (Leandro José) para essa campanha. ;
A7: 1777949 | B7: PARAMETRIZACAO DE CAMPANHA | C7: CAMPANHA FACTA I 14034 | D7: BARBARA VIRGINIA RAIMUNDI DE SIQUEIRA (U) | F7: Aberto | G7: 23/09/2025 14:33:10 | H7: 23/09/2025 14:33:10 | I7: 14034 | J7: SEM META | K7: CONFORME REGRAS FACTA | L7: 0,50% | M7: 01/09 a 30/09 | N7: MENSAL | O7: Remetente - () Prezados(a), boa tarde ! Gentileza parametrizar campanha conforme solicitado pela GC Larissa Sobral e diretor Danilo Ferreira. CODIGO DO CORRETOR: 14034 PERIODO: 01/09 À 30/09 TIPO DE FECHAMENTO: MENSAL META: SEM META PERCENTUAL DE PREMIO: 0,50% PARAMETRO: CONFORME REGRAS FACTA ;
A8: 1777943 | B8: PARAMETRIZACAO DE CAMPANHA | C8: CAMPANHA FACTA I 13440 | D8: BARBARA VIRGINIA RAIMUNDI DE SIQUEIRA (U) | F8: Aberto | G8: 23/09/2025 14:29:41 | H8: 23/09/2025 14:29:41 | I8: 13440 | J8: SEM META | K8: CONFORME REGRAS FACTA | L8: 0,75% | M8: 01/09 a 30/09 | N8: MENSAL | O8: Remetente - () Prezados(a), boa tarde ! Gentileza parametrizar conforme solicitado pela GC Larissa Sobral e e acordado pelo Danilo Ferreira. CODIGO DO CORRETOR: 13440 PERIODO: 01/09 À 30/09 TIPO DE FECHAMENTO: MENSAL META: SEM META PERCENTUAL DE PREMIO: 0,75% PARAMETRO: CONFORME REGRAS FACTA ;
A9: 1777578 | B9: PARAMETRIZACAO DE CAMPANHA | C9: CAMPANHA SETEMBRO I COD 15692 I DAYCOVAL | D9: BIANCA CRISTIANE SOARES SANTOS TERENCIO (U) | F9: Aberto | G9: 23/09/2025 10:19:13 | H9: 23/09/2025 10:19:13 | I9: 15692 | J9: SEM META | K9: EM CIMA DA PRODU??O TOTAL | L9: 0,70 | M9: 01/09 a 30/09 | N9: MENSAL | O9: Remetente - () Bom dia! Gentileza parametrizar conforme solicitado. CODIGO DO CORRETOR: 15692 PERIODO: 01/09 A 30/09 TIPO DE FECHAMENTO: MENSAL META: SEM META PERCENTUAL DE PREMIO: 0,70 PARAMETRO: EM CIMA DA PRODUÇÃO TOTAL ;
A10: 1777521 | B10: PARAMETRIZACAO DE CAMPANHA | C10: CAMPANHA SETEMBRO I COD 14011 I VCTEX | D10: BIANCA CRISTIANE SOARES SANTOS TERENCIO (U) | F10: Aberto | G10: 23/09/2025 10:01:49 | H10: 23/09/2025 10:01:49 | I10: 14011 | J10: SEM META | K10: TUDO O QUE PRODUZIR NA TABELA EXP | L10: 1,0 | M10: 01/09 a 30/09 | N10: MENSAL | O10: Remetente - () Bom dia! Gentileza parametrizar conforme solicitado. TUDO O QUE PRODUZIR NA TABELA EXP -FGTS CODIGO DO CORRETOR: 14011 PERIODO: 01/09 A 30/09 TIPO DE FECHAMENTO: MENSAL META: SEM META PERCENTUAL DE PREMIO: 1,0 PARAMETRO: TUDO O QUE PRODUZIR NA TABELA EXP ;
A11: 1774925 | B11: PARAMETRIZACAO DE CAMPANHA | C11: CAMPANHA BANCO VCTEX l CÓDIGO 18307 l GC LAIS PASCOAL | D11: FABIULA RODRIGUES ARAUJO ZANONI (U) | F11: Aberto | G11: 23/09/2025 09:54:18 | H11: 18/09/2025 11:45:08 | I11: 18307 | J11: 1,00 | K11: PRODU??O BANCO VCTEX | L11: 1,00% | M11: 01/09 a 30/09 | N11: MENSAL | O11: Remetente - () Suporte, bom dia! Gentileza cadastrar campanha solicitada pela Lais e de acordo do Danilo, planilha em anexo. CODIGO DO CORRETOR: 18307 PERIODO: 01/09/2025 a 30/09/2025 TIPO DE FECHAMENTO: MENSAL META: 1,00 PERCENTUAL DE PREMIO: 1,00% PARAMETRO: PRODUÇÃO BANCO VCTEX ; Remetente - () Novo arquivo enviado: CAMPANHAVCTEXFILIPEVS_2025_09_18_11_45_08.xlsx; Remetente - () Novo arquivo enviado: CAMPANHAVCTEXFILIPEVS_2025_09_18_11_45_08_2025_09_23_09_54_18.xlsx; Remetente - () Suporte, bom dia! Segue planilha atualizada para campanha.;
A12: 1777491 | B12: PARAMETRIZACAO DE CAMPANHA | C12: CAMPANHA SETEMBRO I BANCO FACTA I MULTILOJA I 18297/18312/18343 | D12: BIANCA CRISTIANE SOARES SANTOS TERENCIO (U) | F12: Aberto | G12: 23/09/2025 09:47:41 | H12: 23/09/2025 09:47:41 | I12: 18297/18312/18343 | J12: 20.000,00 | K12: CONFORME REGRAS FACTA | L12: 0,75 | M12: 19/9 A 30/09 | N12: MENSAL | O12: Remetente - () Bom dia ! Gentileza parametrizar conforme solicitado. parametrizar as pagamentos para a empresa - G & D SOLUCOES DIGITAIS LTDA. cod 18297. CODIGO DO CORRETOR: 18297/18312/18343 PERIODO: 19/9 A 30/09 TIPO DE FECHAMENTO: MENSAL META: 20.000,00 PERCENTUAL DE PREMIO: 0,75 PARAMETRO: CONFORME REGRAS FACTA ;
A13: 1777482 | B13: PARAMETRIZACAO DE CAMPANHA | C13: CAMPANHA BANCO FACTA l CÓDIGO 18356 l GC LARISSA SOBRAL | D13: FABIULA RODRIGUES ARAUJO ZANONI (U) | F13: Aberto | G13: 23/09/2025 09:43:39 | H13: 23/09/2025 09:43:39 | I13: 18356 | J13: SEM META | K13: NAS TABELAS QUE ? NOS REPASSADO O BONUS | L13: 0,50% | M13: 01/09 a 30/09 | N13: MENSAL | O13: Remetente - () Suporte, bom dia! Gentileza cadastrar campanha solicitada pela Larissa e de acordo do Danilo, segue planilha em anexo. CODIGO DO CORRETOR: 18356 PERIODO: 01/09/2025 a 30/09/2025 TIPO DE FECHAMENTO: MENSAL META: SEM META PERCENTUAL DE PREMIO: 0,50% PARAMETRO: NAS TABELAS QUE É NOS REPASSADO O BONUS ; Remetente - () Novo arquivo enviado: BONUSFACTAPATRICIA(1)_2025_09_23_09_43_39.xlsx;
A14: 1777314 | B14: PARAMETRIZACAO DE CAMPANHA | C14: CAMPANHA BANCO BMG l CÓDIGO 16130 l GC CHRISTIANE NIELSEN | D14: FABIULA RODRIGUES ARAUJO ZANONI (U) | F14: Aberto | G14: 22/09/2025 17:29:54 | H14: 22/09/2025 17:29:54 | I14: 16130 | J14: 0,01 | K14: PRODU??O TOTAL NOVO CONV?NIO INSS | L14: 0,20% | M14: 19/09/2025 A 30/09/2025 | N14: MENSAL | O14: Remetente - () Suporte, boa tarde! Gentileza cadastrar campanha campanha solicitada pela Cris e de acordo do André. CODIGO DO CORRETOR: 16130 PERIODO: 19/09/2025 A 30/09/2025 TIPO DE FECHAMENTO: MENSAL META: 0,01 PERCENTUAL DE PREMIO: 0,20% PARAMETRO: PRODUÇÃO TOTAL NOVO CONVÊNIO INSS ;
A15: 1777286 | B15: PARAMETRIZACAO DE CAMPANHA | C15: CAMPANHA BANCO MASTER l CÓDIGO 6905 l GC ICARO FRANÇA | D15: FABIULA RODRIGUES ARAUJO ZANONI (U) | F15: Aberto | G15: 22/09/2025 17:02:52 | H15: 22/09/2025 17:02:52 | I15: 6905 | J15: 0,01 | K15: ?A campanha ? exclusiva para o produto M FACIL E CREDCESTA, no banco MASTER e conv?nio?prefeitura de UBERABA, IPSERV E CODAU em todas as tabelas e prazos. | L15: 1,23% | M15: 01/09 a 30/09 | N15: MENSAL | O15: Remetente - () Suporte, boa tarde! Gentileza cadastrar campanha solicitada pelo Icaro e de acordo do Danilo, segue planilha em anexo. CODIGO DO CORRETOR: 6905 PERIODO: 01/09/2025 a 30/09/2025 TIPO DE FECHAMENTO: MENSAL META: 0,01 PERCENTUAL DE PREMIO: 1,23% PARAMETRO: A campanha é exclusiva para o produto M FACIL E CREDCESTA, no banco MASTER e convênio prefeitura de UBERABA, IPSERV E CODAU em todas as tabelas e prazos. ; Remetente - () Novo arquivo enviado: PLANILHACAMPANHALUIZGUSTAVO6905SUBMASTER(2)(1)(1)_2025_09_22_17_02_52.xlsx;
A16: 1777277 | B16: PARAMETRIZACAO DE CAMPANHA | C16: CAMPANHA l CÓDIGO 14011 l GC LARISSA SOBRAL | D16: FABIULA RODRIGUES ARAUJO ZANONI (U) | F16: Aberto | G16: 22/09/2025 16:56:58 | H16: 22/09/2025 16:56:58 | I16: 14011 | J16: DIVERSOS | K16: DIVERSOS | L16: DIVERSOS | M16: 01/09 a 30/09 | N16: MENSAL | O16: Remetente - () Suporte, boa tarde! Gentileza cadastrar campanhas solicitadas pela Larissa e de acordo do Danilo, segue planilha em anexo. CODIGO DO CORRETOR: 14011 PERIODO: 01/09/2025 a 30/09/2025 TIPO DE FECHAMENTO: MENSAL META: DIVERSOS PERCENTUAL DE PREMIO: DIVERSOS PARAMETRO: DIVERSOS ; Remetente - () Novo arquivo enviado: BONUSFACTAFLAVIO(2)_2025_09_22_16_56_58.xlsx;
A17: 1777197 | B17: PARAMETRIZACAO DE CAMPANHA | C17: CAMPANHA BANCO FACTA l CÓDIGO 16578 l GC LARISSA SOBRAL | D17: FABIULA RODRIGUES ARAUJO ZANONI (U) | F17: Aberto | G17: 22/09/2025 16:04:56 | H17: 22/09/2025 16:04:56 | I17: 16578 | J17: SEM META | K17: NAS TABELAS QUE ? NOS REPASSADO O BONUS | L17: 0,30% | M17: 01/09 a 30/09 | N17: MENSAL | O17: Remetente - () Suporte, boa tarde! Gentileza cadastrar campanha solicitada pela Larissa e de acordo do Danilo, segue planilha em anexo. CODIGO DO CORRETOR: 16578 PERIODO: 01/09/2025 a 30/09/2025 TIPO DE FECHAMENTO: MENSAL META: SEM META PERCENTUAL DE PREMIO: 0,30% PARAMETRO: NAS TABELAS QUE É NOS REPASSADO O BONUS ; Remetente - () Novo arquivo enviado: BONUSFACTAGABRIELA_2025_09_22_16_04_56.xlsx;
... A34: 1776598 | B34: PARAMETRIZACAO DE CAMPANHA | C34: CAMPANHA BANCO FACTA l CÓDIGO 17143 l GC THAIS MELO | D34: FABIULA RODRIGUES ARAUJO ZANONI (U) | F34: Aberto | G34: 22/09/2025 10:02:14 | H34: 22/09/2025 10:02:14 | I34: 17143 | J34: 1,00 | K34: ( Conforme parametro?facta?) | L34: 0,25 | M34: 01/09 a 30/09 | N34: MENSAL | O34: Remetente - () Suporte, bom dia! Gentileza cadastrar campanha solicitada pela Thais e de acordo do Danilo, segue planilha em anexo. CODIGO DO CORRETOR: 17143 PERIODO: 01/09/2025 a 30/09/2025 TIPO DE FECHAMENTO: MENSAL META: 1,00 PERCENTUAL DE PREMIO: 0,25 PARAMETRO: ( Conforme parametro facta ) ; Remetente - () Novo arquivo enviado: PLANILHADEBONUS-FACTA_2025_09_22_10_02_14.xlsx;
A35: 1763007 | B35: PARAMETRIZACAO DE CAMPANHA | C35: PARAMETRIZAR CAMPANHA BANCO MERCANTIL - ID 17938 | D35: JOSIANE ARAUJO TEIXEIRA (U) | E35: Cinthia Gomes da Silva | F35: Aberto | G35: 22/09/2025 10:00:19 | H35: 01/09/2025 14:22:56 | I35: 17938 | J35: SEM META | K35: DESCRI?AO | L35: 0,20% | M35: 01/09 a 31/12 | N35: MENSAL | O35: Remetente - () Boa tarde! Iremos considerar toda a produção de cartões RCC e RMC. CODIGO DO CORRETOR: 17938 PERIODO: 01/09 a 31/12 TIPO DE FECHAMENTO: MENSAL META: SEM META PERCENTUAL DE PREMIO: 0,20% PARAMETRO: DESCRIÇAO ; Remetente - () Josi, boa tarde. Campanha parametrizada. Meta 8531,8532,8533,8534 ; Remetente - () Bom dia! Por gentielza alterar o percentual da camapanha. PERCENTUAL DE PREMIO: 0,40% PERIODO: 01/09 a 31/12;
A36: 1776588 | B36: PARAMETRIZACAO DE CAMPANHA | C36: CAMPANHA BANCO FACTA l CÓDIGO 15632 l GC THAIS MELO | D36: FABIULA RODRIGUES ARAUJO ZANONI (U) | F36: Aberto | G36: 22/09/2025 09:57:58 | H36: 22/09/2025 09:57:58 | I36: 15632 | J36: 1,00 | K36: ( Conforme parametro?facta?) | L36: 0,50 | M36: 01/09 a 30/09 | N36: MENSAL | O36: Remetente - () Suporte, bom dia! Gentileza cadastrar campanha solicitada pela Thais e de acordo do Danilo, segue planilha em anexo. CODIGO DO CORRETOR: 15632 PERIODO: 01/09/2025 a 30/09/2025 TIPO DE FECHAMENTO: MENSAL META: 1,00 PERCENTUAL DE PREMIO: 0,50 PARAMETRO: ( Conforme parametro facta ) ; Remetente - () Novo arquivo enviado: PLANILHADEBONUS-FACTAJUSUBj_2025_09_22_09_57_58.xlsx;
A37: 1776530 | B37: PARAMETRIZACAO DE CAMPANHA | C37: CAMPANHA BANCO C6 l CÓDIGO 11820 l GC THAYS MELO | D37: FABIULA RODRIGUES ARAUJO ZANONI (U) | F37: Aberto | G37: 22/09/2025 09:25:54 | H37: 22/09/2025 09:25:54 | I37: 11820 | J37: 1,00 | K37: DIVERSOS | L37: DIVERSOS | M37: 01/09 a 30/09 | N37: MENSAL | O37: Remetente - () Suporte, bom dia! Gentileza cadastrar campanha solicitada pela Thays e de acordo do Danilo, ressaltamos que a campanha e fechamento e enviada pelo Banco mensalmente. Segue planilha em anexo. CODIGO DO CORRETOR: 11820 PERIODO: 01/09/2025 a 30/09/2025 TIPO DE FECHAMENTO: MENSAL META: 1,00 PERCENTUAL DE PREMIO: DIVERSOS PARAMETRO: DIVERSOS ; Remetente - () Novo arquivo enviado: PLANILHADEBONUS-C6-TULIO_2025_09_22_09_25_54.xlsx;
A38: 1776525 | B38: PARAMETRIZACAO DE CAMPANHA | C38: CAMPANHA BANCO MASTER l CÓDIGO 15216 l GC THAIS MELO | D38: FABIULA RODRIGUES ARAUJO ZANONI (U) | F38: Aberto | G38: 22/09/2025 09:18:23 | H38: 22/09/2025 09:18:23 | I38: 15216 | J38: 1,00 | K38: TODA PRODU??O BANCO MASTER , DE ACORDO COM AS REGRAS DO BANCO | L38: 1,50 | M38: 01/09 a 30/09 | N38: MENSAL | O38: Remetente - () Suporte, bom dia! Gentileza cadastrar campanha solicitada pela Thais e de acordo do Danilo, segue planilha em anexo. CODIGO DO CORRETOR: 15216 PERIODO: 01/09/2025 a 30/09/2025 TIPO DE FECHAMENTO: MENSAL META: 1,00 PERCENTUAL DE PREMIO: 1,50 PARAMETRO: TODA PRODUÇÃO BANCO MASTER , DE ACORDO COM AS REGRAS DO BANCO ; Remetente - () Novo arquivo enviado: PLANILHADEBONUS-TOTEMMASTER_2025_09_22_09_18_23.xlsx;
A39: 1776512 | B39: PARAMETRIZACAO DE CAMPANHA | C39: CAMPANHA BANCO MERCANTIL l CÓDIGO 17740 l GC THAIS MELO | D39: FABIULA RODRIGUES ARAUJO ZANONI (U) | F39: Aberto | G39: 22/09/2025 09:11:10 | H39: 22/09/2025 09:11:10 | I39: 17740 | J39: 1,00 | K39: B?nus pago referente a venda de cart?o RMC E RCC | L39: 0,70 | M39: 01/09 a 30/09 | N39: MENSAL | O39: Remetente - () Suporte, bom dia! Gentileza cadastrar campanha solicitada pela Thais e de acordo do Danilo. Segue planilha em anexo. CODIGO DO CORRETOR: 17740 PERIODO: 01/09/2025 a 30/09/2025 TIPO DE FECHAMENTO: MENSAL META: 1,00 PERCENTUAL DE PREMIO: 0,70 PARAMETRO: Bônus pago referente a venda de cartão RMC E RCC ; Remetente - () Novo arquivo enviado: PLANILHADEBONUS-mercatiloliveira(1)_2025_09_22_09_11_10.xlsx;
A40: 1776346 | B40: PARAMETRIZACAO DE CAMPANHA | C40: PARAMETRIZAR CAMPANHA BANCO ID 13782 | D40: JOSIANE ARAUJO TEIXEIRA (U) | F40: Aberto | G40: 19/09/2025 16:35:27 | H40: 19/09/2025 16:35:27 | I40: 13782 | J40: 10 MIL | K40: EM TODOS OS PRODUTOS E TABELAS BANCO DAYCOVAL QUE COMTEMPLAM A CAMPANHA DE BONUS | L40: 1,2% | M40: 01/09 a 30/09 | N40: MENSAL | O40: Remetente - () Boa tarde! CODIGO DO CORRETOR: 13782 PERIODO: 01/09 A 30/09 TIPO DE FECHAMENTO: MENSAL META: 10 MIL PERCENTUAL DE PREMIO: 1,2% PARAMETRO: EM TODOS OS PRODUTOS E TABELAS BANCO DAYCOVAL QUE COMTEMPLAM A CAMPANHA DE BONUS ;
A41: 1776315 | B41: PARAMETRIZACAO DE CAMPANHA | C41: CAMPANHA BANCO VCTEX l CÓDIGO 16358 l FERNANDA OTONI | D41: FABIULA RODRIGUES ARAUJO ZANONI (U) | F41: Aberto | G41: 19/09/2025 16:11:05 | H41: 19/09/2025 16:11:05 | I41: 16358 | J41: 400.000,00 | K41: PRODUCAO TOTAL | L41: 0,25% | M41: 01/09 a 30/09 | N41: MENSAL | O41: Remetente - () Suporte, boa tarde! Gentileza cadastrar campanha solicitada pela Fernanda e de acordo do Danilo, segue planilha em anexo. CODIGO DO CORRETOR: 16358 PERIODO: 01/09/2025 a 30/09/2025 TIPO DE FECHAMENTO: MENSAL META: 400.000,00 PERCENTUAL DE PREMIO: 0,25% PARAMETRO: PRODUCAO TOTAL ; Remetente - () Novo arquivo enviado: CAMPANHAMESSETEMBROVCTEX(2)_2025_09_19_16_11_05.xlsx;
A42: 1776262 | B42: PARAMETRIZACAO DE CAMPANHA | C42: CAMPANHA FACTA l CÓDIGO 17051 l GC THAIS MELO | D42: FABIULA RODRIGUES ARAUJO ZANONI (U) | F42: Aberto | G42: 19/09/2025 15:32:16 | H42: 19/09/2025 15:32:16 | I42: 17051 | J42: 1,00 | K42: Conforme parametro?facta? | L42: 0,25 | M42: 01/09 a 30/09 | N42: MENSAL | O42: Remetente - () Suporte, boa tarde! Gentileza cadastrar campanha solicitada pela Thais e de acordo do Danilo, segue planilha em anexo. CODIGO DO CORRETOR: 17051 PERIODO: 01/09/2025 a 30/09/2025 TIPO DE FECHAMENTO: MENSAL META: 1,00 PERCENTUAL DE PREMIO: 0,25 PARAMETRO: Conforme parametro facta ; Remetente - () Novo arquivo enviado: PLANILHADEBONUS-FACTAMICHELLE(1)_2025_09_19_15_32_16.xlsx;
A43: 1776259 | B43: PARAMETRIZACAO DE CAMPANHA | C43: PARAMETRIZAR CAMPANHA BANCO - ID 7274 | D43: JOSIANE ARAUJO TEIXEIRA (U) | F43: Aberto | G43: 19/09/2025 15:28:10 | H43: 19/09/2025 15:28:10 | I43: 7274 | J43: SEM META | K43: PAN / INSS NOVO / TODAS AS TABELAS E PRAZOS | L43: 0,20 | M43: 18/09 A 30/09 | N43: MENSAL | O43: Remetente - () Boa tarde! CODIGO DO CORRETOR: 7274 PERIODO: 18/09 A 30/09 TIPO DE FECHAMENTO: MENSAL META: SEM META PERCENTUAL DE PREMIO: 0,20 PARAMETRO: PAN / INSS NOVO / TODAS AS TABELAS E PRAZOS ;
A44: 1776250 | B44: PARAMETRIZACAO DE CAMPANHA | C44: PARAMETIRZAÇAO DE CAMPANHA - ID 17303 | D44: JOSIANE ARAUJO TEIXEIRA (U) | F44: Aberto | G44: 19/09/2025 15:20:56 | H44: 19/09/2025 15:20:56 | I44: 17303 | J44: 1000 | K44: Banco Quero Mais Cr?dito ? Todos os Produtos , com EXCE??O INSS ? Todos os Prazos ? Todos os conv?nios ? Todas as Tabelas | L44: 1,9% | M44: 01/09 a 30/09 | N44: MENSAL | O44: Remetente - () Boa tarde! CODIGO DO CORRETOR: 17303 PERIODO: 01/09 A 30/09 TIPO DE FECHAMENTO: MENSAL META: 1000 PERCENTUAL DE PREMIO: 1,9% PARAMETRO: Banco Quero Mais Crédito ? Todos os Produtos , com EXCEÇÃO INSS ? Todos os Prazos ? Todos os convênios ? Todas as Tabelas ;
A45: 1776244 | B45: PARAMETRIZACAO DE CAMPANHA | C45: PARAMETRIZAR CAMPANHA - ID 14722 | D45: JOSIANE ARAUJO TEIXEIRA (U) | F45: Aberto | G45: 19/09/2025 15:13:38 | H45: 19/09/2025 15:13:38 | I45: 14722 | J45: 10.000,00 | K45: MERCANTIL ? PRODU??O DE FGTS | L45: 0,60% | M45: 18/09 A 30/09 | N45: MENSAL | O45: Remetente - () Boa tarde@! CODIGO DO CORRETOR: 14722 PERIODO: 18/09 A 30/09 TIPO DE FECHAMENTO: MENSAL META: 10.000,00 PERCENTUAL DE PREMIO: 0,60% PARAMETRO: MERCANTIL ? PRODUÇÃO DE FGTS ;
A46: 1776226 | B46: PARAMETRIZACAO DE CAMPANHA | C46: CAMPANHA BANCO FACTA l CÓDIGO 15516 l THAIS MELO | D46: FABIULA RODRIGUES ARAUJO ZANONI (U) | F46: Aberto | G46: 19/09/2025 15:02:46 | H46: 19/09/2025 15:02:46 | I46: 15516 | J46: 1,00 | K46: ( Conforme parametro?facta?) | L46: 0,50 | M46: 01/09 a 30/09 | N46: MENSAL | O46: Remetente - () Suporte, boa tarde! Gentileza cadastrar campanha solicitada pela Thais e de acordo do Danilo, segue planilha em anexo. CODIGO DO CORRETOR: 15516 PERIODO: 01/09/2025 a 30/09/2025 TIPO DE FECHAMENTO: MENSAL META: 1,00 PERCENTUAL DE PREMIO: 0,50 PARAMETRO: ( Conforme parametro facta ) ; Remetente - () Novo arquivo enviado: PLANILHADEBONUS-FACTASUBTAYLO_2025_09_19_15_02_46.xlsx;
A47: 1776219 | B47: PARAMETRIZACAO DE CAMPANHA | C47: CAMPANHA BANCO FACTA l CÓDIGO 12732 l GC THAIS MELO | D47: FABIULA RODRIGUES ARAUJO ZANONI (U) | F47: Aberto | G47: 19/09/2025 14:59:22 | H47: 19/09/2025 14:59:22 | I47: 12732 | J47: 1,00 | K47: ( Conforme parametro?facta?) | L47: 0,50 | M47: 01/09 a 30/09 | N47: MENSAL | O47: Remetente - () Suporte, boa tarde! Gentileza cadastrar campanha solicitada pela Thais e de acordo do Danilo, segue planilha em anexo. CODIGO DO CORRETOR: 12732 PERIODO: 01/09/2025 a 30/09/2025 TIPO DE FECHAMENTO: MENSAL META: 1,00 PERCENTUAL DE PREMIO: 0,50 PARAMETRO: ( Conforme parametro facta ) ; Remetente - () Novo arquivo enviado: PLANILHADEBONUS-FACTAehe_2025_09_19_14_59_22.xlsx;
... A114: 1774170 | B114: PARAMETRIZACAO DE CAMPANHA | C114: PARAMETRIZAR CAMPANHA - ID 3557 | D114: JOSIANE ARAUJO TEIXEIRA (U) | F114: Aberto | G114: 17/09/2025 14:28:54 | H114: 17/09/2025 14:28:54 | I114: 3557 | J114: SEM META | K114: Toda a produ??o FGTS MERCANTIL | L114: 0,10% | M114: 01/09 a 30/09 | N114: MENSAL | O114: Remetente - () Boa tarde! CODIGO DO CORRETOR: 3557 PERIODO: 01/09 A 30/09 TIPO DE FECHAMENTO: MENSAL META: SEM META PERCENTUAL DE PREMIO: 0,10% PARAMETRO: Toda a produção FGTS MERCANTIL ;
A115: 1775609 | B115: PARAMETRIZACAO DE CAMPANHA | C115: PARAMETRIZAR CAMPANHA - ID: 13113 | D115: LUCAS GUIMARAES EVARISTO (U) | F115: Fechado | H115: 19/09/2025 08:57:41 | I115: 13113 | J115: SEM META | K115: CONFORME DESCRI??O | L115: CONFORME DESCRI??O | M115: 01/09 a 30/09 | N115: MENSAL | O115: Remetente - () Prezados, bom dia! Favor parametrizar campanha conforme abaixo. BANCO CREDBANK - TODA PRODUÇÃO INSS e cartoes EXCETO AS TABELAS - MEU CREDBANK - INSS - MEU CREDBANK - INSS - FP - NORMAL - TX 1,85MEU CREDBANK - INSS - MEU CREDBANK - INSS - FP - SEGURO - TX 1,85 - BONUS DE 0,70%. BANCO CREDBANK - TODA PRODUÇÃO DE FGTS - BONUS DE 1,20% BANCO FACTA - TODA PRODUÇÃO CONFORME REGRA - BONUS 0,75%. CODIGO DO CORRETOR: 13113 PERIODO: 01/09/2025 a 30/09/2025 TIPO DE FECHAMENTO: MENSAL META: SEM META PERCENTUAL DE PREMIO: CONFORME DESCRIÇÃO PARAMETRO: CONFORME DESCRIÇÃO ; Remetente - () FAVOR DESCONSIDERAR; Remetente - () Chamado encerrado.;
A116: 1774262 | B116: PARAMETRIZACAO DE CAMPANHA | C116: CAMPANHA l CÓDIGO 11994 l GC LUCYANA MEDEIROS | D116: FABIULA RODRIGUES ARAUJO ZANONI (U) | E116: Cinthia Gomes da Silva | F116: Fechado | H116: 17/09/2025 15:18:49 | I116: 11994 | J116: 1000,00 | K116: DIVERSOS | L116: DIVERSOS | M116: 01/09 a 30/09 | N116: MENSA | O116: Remetente - () Suporte, boa tarde! Gentileza cadastrar campanha conforme solicitado pela Glauce e de acordo do André. Segue planilha em anexo. CODIGO DO CORRETOR: 11994 PERIODO: 01/09/2025 a 30/09/2025 TIPO DE FECHAMENTO: MENSA META: 1000,00 PERCENTUAL DE PREMIO: DIVERSOS PARAMETRO: DIVERSOS ; Remetente - () Novo arquivo enviado: CampanhaRGGlauce_2025_09_17_15_18_49.xlsx; Remetente - () Fabi, boa tarde. Campanha parametrizada. codigo8809 8819 8825 ;
A117: 1774253 | B117: PARAMETRIZACAO DE CAMPANHA | C117: CAMPANHA BANCO MERCANTIL l CODIGO 18118 l GC LUCYANA MEDEIROS | D117: FABIULA RODRIGUES ARAUJO ZANONI (U) | E117: Cinthia Gomes da Silva | F117: Fechado | H117: 17/09/2025 15:14:27 | I117: 18118 | J117: 1000,00 | K117: BANCO MERCANTIL - TODAS AS TABELAS, COM EXCE??O DO CP RESOLVE -INSS CREDITO PESSOAL | L117: 0,20% | M117: 01/09 a 30/09 | N117: MENSAL | O117: Remetente - () Suporte, boa tarde! Gentileza cadastrar campanha solicitada pela Glauce e de acordo com André. Segue planilha em anexo. CODIGO DO CORRETOR: 18118 PERIODO: 01/09/2025 a 30/09/2025 TIPO DE FECHAMENTO: MENSAL META: 1000,00 PERCENTUAL DE PREMIO: 0,20% PARAMETRO: BANCO MERCANTIL - TODAS AS TABELAS, COM EXCEÇÃO DO CP RESOLVE -INSS CREDITO PESSOAL ; Remetente - () Novo arquivo enviado: CampanhaRGGlauce_2025_09_17_15_14_27.xlsx; Remetente - () Fabi, boa tarde. Campanha parametrizada. codigo 8826 ;
A118: 1774250 | B118: PARAMETRIZACAO DE CAMPANHA | C118: PARAMETRIZAR CAMPANHA - ID 1452 | D118: JOSIANE ARAUJO TEIXEIRA (U) | E118: Cinthia Gomes da Silva | F118: Fechado | H118: 17/09/2025 15:13:22 | I118: 1452 | J118: 300 K | K118: A ?produ??o de todos os bancos e tabelas ser? levada em considera??o para pagamento de b?nus e atingimento DA META | L118: 0.10% | M118: 01/09 a 30/09 | N118: MENSAL | O118: Remetente - () Boa tarde! CODIGO DO CORRETOR: 1452 PERIODO: 01/09 A 30/09 TIPO DE FECHAMENTO: MENSAL META: 300 K PERCENTUAL DE PREMIO: 0.10% PARAMETRO: A produção de todos os bancos e tabelas será levada em consideração para pagamento de bônus e atingimento DA META ; Remetente - () Josi, boa tarde. Campanha parametrizada. codigo 8827 ; Remetente - () ; Remetente - () segue ;
A119: 1774245 | B119: PARAMETRIZACAO DE CAMPANHA | C119: CAMPANHA l CÓDIGO 17515 l GC ROMAGNOSI SOTERO | D119: FABIULA RODRIGUES ARAUJO ZANONI (U) | E119: Cinthia Gomes da Silva | F119: Fechado | H119: 17/09/2025 15:11:12 | I119: 17515 | J119: DIVERSOS | K119: DIVERSOS | L119: DIVESOS | M119: 01/09 a 30/09 | N119: MENS | O119: Remetente - () Suporte, boa tarde! Gentileza cadastrar campanha solicitada pela Glauce e de acordo com André. Segue planilha em anexo. CODIGO DO CORRETOR: 17515 PERIODO: 01/09/2025 a 30/09/2025 TIPO DE FECHAMENTO: MENS META: DIVERSOS PERCENTUAL DE PREMIO: DIVESOS PARAMETRO: DIVERSOS ; Remetente - () Novo arquivo enviado: CampanhaRGGlauce_2025_09_17_15_11_12.xlsx; Remetente - () Fabi, boa tarde. Campanha parametrizada. codigo 8820 8810 ;
A120: 1774239 | B120: PARAMETRIZACAO DE CAMPANHA | C120: PARAMETRIZAR CAMPANHA BANCO - id 12378 | D120: JOSIANE ARAUJO TEIXEIRA (U) | E120: Cinthia Gomes da Silva | F120: Fechado | H120: 17/09/2025 15:06:43 | I120: 12378 | J120: R$ 200.000 | K120: TODA A PRODU??O AMIGOZ | L120: 0,70% | M120: 01/09 a 30/09 | N120: MENSAL | O120: Remetente - () Boa tarde! CODIGO DO CORRETOR: 12378 PERIODO: 01/09 A 30/09 TIPO DE FECHAMENTO: MENSAL META: R$ 200.000 PERCENTUAL DE PREMIO: 0,70% PARAMETRO: TODA A PRODUÇÃO AMIGOZ ; Remetente - () Josi, boa tarde. Campanha parametrizada. codigo 8828 ;
A121: 1774234 | B121: PARAMETRIZACAO DE CAMPANHA | C121: CAMPANHA BANCO FACTA l CÓDIGO 17461 l DIEGO MOURA | D121: FABIULA RODRIGUES ARAUJO ZANONI (U) | E121: Cinthia Gomes da Silva | F121: Fechado | H121: 17/09/2025 15:04:08 | I121: 17461 | J121: 0,10 | K121: TODAS AS OPERA??ES CONFORME FACTA - COM EXCE??O CLT | L121: 0,75% | M121: 01/09 a 30/09 | N121: MENSAL | O121: Remetente - () Suporte, boa tarde! Gentileza cadastrar campanha conforme solicitado pela Glauce e de acordo do André. Segue planilha em anexo. CODIGO DO CORRETOR: 17461 PERIODO: 01/09/2025 a 30/09/2025 TIPO DE FECHAMENTO: MENSAL META: 0,10 PERCENTUAL DE PREMIO: 0,75% PARAMETRO: TODAS AS OPERAÇÕES CONFORME FACTA - COM EXCEÇÃO CLT ; Remetente - () Novo arquivo enviado: CampanhaRGGlauce_2025_09_17_15_04_08.xlsx; Remetente - () Fabi, boa tarde. Campanha parametrizada. codigo 8811 ;
A122: 1774224 | B122: PARAMETRIZACAO DE CAMPANHA | C122: CAMPANHA BANCO DAYCOVAL l CÓDIGO 7734 l GC DIEGO MOURA | D122: FABIULA RODRIGUES ARAUJO ZANONI (U) | E122: Cinthia Gomes da Silva | F122: Fechado | H122: 17/09/2025 15:00:15 | I122: 7734 | J122: 0,10 | K122: DAYCOVAL - 50% DO B?NUS QUE A CREDFRANCO RECEBER DO BANCO | L122: 0,50% | M122: 01/09 a 30/09 | N122: MENSAL | O122: Remetente - () Suporte, boa tarde! Gentileza cadastrar campanha conforme solicitado pela Glauce e de acordo do André. Segue planilha em anexo. CODIGO DO CORRETOR: 7734 PERIODO: 01/09/2025 a 30/09/2025 TIPO DE FECHAMENTO: MENSAL META: 0,10 PERCENTUAL DE PREMIO: 0,50% PARAMETRO: DAYCOVAL - 50% DO BÔNUS QUE A CREDFRANCO RECEBER DO BANCO ; Remetente - () Novo arquivo enviado: CampanhaRGGlauce_2025_09_17_15_00_15.xlsx; Remetente - () Fabi, boa tarde. Campanha parametrizada. codigo 8829 ;
A123: 1774218 | B123: PARAMETRIZACAO DE CAMPANHA | C123: CAMPANHA BANCO CASH CARD l CÓDIGO 7149 l GC DIEGO MOURA | D123: FABIULA RODRIGUES ARAUJO ZANONI (U) | E123: Cinthia Gomes da Silva | F123: Fechado | H123: 17/09/2025 14:56:29 | I123: 7149 | J123: 0,10 | K123: CASH CARD - TODAS AS TABELAS DO CONVENIO PREF DE NATAL - TODOS OS PRAZOS . | L123: 1,80% | M123: 01/09 a 30/09 | N123: MENSAL | O123: Remetente - () Suporte, boa tarde! Gentileza cadastrar campanha solicitada pela Glauce e com de acordo do André. Segue planilha em anexo. CODIGO DO CORRETOR: 7149 PERIODO: 01/09/2025 a 30/09/2025 TIPO DE FECHAMENTO: MENSAL META: 0,10 PERCENTUAL DE PREMIO: 1,80% PARAMETRO: CASH CARD - TODAS AS TABELAS DO CONVENIO PREF DE NATAL - TODOS OS PRAZOS . ; Remetente - () Novo arquivo enviado: CampanhaRGGlauce_2025_09_17_14_56_29.xlsx; Remetente - () Fabi, boa tarde. Campanha parametrizada. codigo 8831 ;
A124: 1774208 | B124: PARAMETRIZACAO DE CAMPANHA | C124: CAMPANHA l CÓDIGO 13220 l GC DIEGO MOURA | D124: FABIULA RODRIGUES ARAUJO ZANONI (U) | E124: Cinthia Gomes da Silva | F124: Fechado | H124: 17/09/2025 14:49:51 | I124: 13220 | J124: 0,10 | K124: DIVERSOS | L124: DIVERSOS | M124: 01/09 a 30/09 | N124: MENSAL | O124: Remetente - () Suporte, boa tarde! Gentileza cadastrar campanha conforme solicitado pela Glauce e de acordo do André. CODIGO DO CORRETOR: 13220 PERIODO: 01/09/2025 a 30/09/2025 TIPO DE FECHAMENTO: MENSAL META: 0,10 PERCENTUAL DE PREMIO: DIVERSOS PARAMETRO: DIVERSOS ; Remetente - () Novo arquivo enviado: CampanhaRGGlauce_2025_09_17_14_49_51.xlsx; Remetente - () Lucas, boa tarde. Campanha parametrizada. codigo8812 8832 8821 8333 ;
A125: 1774186 | B125: PARAMETRIZACAO DE CAMPANHA | C125: PARAMETRIZAR CAMPANHA - ID 7046 | D125: JOSIANE ARAUJO TEIXEIRA (U) | E125: Cinthia Gomes da Silva | F125: Fechado | H125: 17/09/2025 14:41:23 | I125: 7046 | J125: SEM META | K125: conforme parametro facta | L125: 0,50% | M125: 01/09 a 30/09 | N125: MENSAL | O125: Remetente - () Boa tarde! CODIGO DO CORRETOR: 7046 PERIODO: 01/09 A 30/09 TIPO DE FECHAMENTO: MENSAL META: SEM META PERCENTUAL DE PREMIO: 0,50% PARAMETRO: conforme parametro facta ; Remetente - () Josi, boa tarde. Campanha parametrizada. codigo 8813 ;
A126: 1774179 | B126: PARAMETRIZACAO DE CAMPANHA | C126: CAMPANHA BANCO FACTA l CÓDIGO 13617 l DIEGO MOURA | D126: FABIULA RODRIGUES ARAUJO ZANONI (U) | E126: Cinthia Gomes da Silva | F126: Fechado | H126: 17/09/2025 14:35:40 | I126: 13617 | J126: 0,10 | K126: FACTA - TODAS AS OPERA??ES- TODAS AS TABELAS E PRAZOS CONFORME REPASSE BONUS DO BANCO | L126: 0,75% | M126: 01/09 a 30/09 | N126: MENSAL | O126: Remetente - () Suporte, boa tarde! Gentileza cadastrar campanha conforme abaixo e planilha em anexo. CODIGO DO CORRETOR: 13617 PERIODO: 01/09/2025 a 30/09/2025 TIPO DE FECHAMENTO: MENSAL META: 0,10 PERCENTUAL DE PREMIO: 0,75% PARAMETRO: FACTA - TODAS AS OPERAÇÕES- TODAS AS TABELAS E PRAZOS CONFORME REPASSE BONUS DO BANCO ; Remetente - () Novo arquivo enviado: CampanhaRGGlauce_2025_09_17_14_35_40.xlsx; Remetente - () Fabi, boa tarde. Campanha parametrizada. codigo 8814 ;
A127: 1774159 | B127: PARAMETRIZACAO DE CAMPANHA | C127: PARAMETRIZAR CAMPANHA - ID 15216 | D127: JOSIANE ARAUJO TEIXEIRA (U) | E127: Cinthia Gomes da Silva | F127: Fechado | H127: 17/09/2025 14:20:44 | I127: 15216 | J127: SEM META | K127: B?nus pago referente a venda de cart?o RMC E RCC | L127: 0,70% | M127: 01/09 a 30/09 | N127: MENSAL | O127: Remetente - () bOA TARDE! CODIGO DO CORRETOR: 15216 PERIODO: 01/09 A 30/09 TIPO DE FECHAMENTO: MENSAL META: SEM META PERCENTUAL DE PREMIO: 0,70% PARAMETRO: Bônus pago referente a venda de cartão RMC E RCC ; Remetente - () Em tempo , Banco mercantil; Remetente - () Em tempo, O codigo corret é CODIGO DO CORRETOR: 13061; Remetente - () Josi, boa tarde. Campanha parametrizada. codigo 8835 ;
... A261: 1766904 | B261: PARAMETRIZACAO DE CAMPANHA | C261: PARAMETRIZAR A CAMPANHA - ID 3566 | D261: JOSIANE ARAUJO TEIXEIRA (U) | E261: Cinthia Gomes da Silva | F261: Fechado | H261: 05/09/2025 16:49:54 | I261: 3566 | J261: 500.000,00 | K261: FACTA INSS PORT / REFIN DA PORT /REFIN / NOVO / FGTS | L261: 0,70% | M261: 01/09 a 30/09 | N261: MENSAL | O261: Remetente - () Boa tarde! CODIGO DO CORRETOR: 3566 PERIODO: 01/09 A 30/09 TIPO DE FECHAMENTO: MENSAL META: 500.000,00 PERCENTUAL DE PREMIO: 0,70% PARAMETRO: FACTA INSS PORT / REFIN DA PORT /REFIN / NOVO / FGTS ; Remetente - () Josi, bom dia. Campanha parametrizada. Meta 8594;
A262: 1766890 | B262: PARAMETRIZACAO DE CAMPANHA | C262: PARAMETRIZAR CAMPANHA - 11599 - 17823 | D262: JOSIANE ARAUJO TEIXEIRA (U) | E262: Cinthia Gomes da Silva | F262: Fechado | H262: 05/09/2025 16:44:13 | I262: 11599
A263: 17823 | B263: 200 MIL | C263: CONSIDERAR TODA A PRODU?AO PARA APURA?AO, TODOS CONVENIOS PRAZO MAXIMO. | D263: 200,00 | E263: 01/09 A 30/09 | F263: MENSAL | G263: Remetente - () Boa tarde! A bonificação sera paga no Código: 11599 CODIGO DO CORRETOR: 11599 17823 PERIODO: 01/09 A 30/09 TIPO DE FECHAMENTO: MENSAL META: 200 MIL PERCENTUAL DE PREMIO: 200,00 PARAMETRO: CONSIDERAR TODA A PRODUÇAO PARA APURAÇAO, TODOS CONVENIOS PRAZO MAXIMO. ; Remetente - () Josi, bom dia. Campanha parametrizada. Meta 8604; Remetente - () Em tempo Não tem com considerar prazo maximo em todos os bancos, portanto foi considerado todos os prazos. ;
A264: 1766884 | B264: PARAMETRIZACAO DE CAMPANHA | C264: PARAMETRIZAR CAMPANHA BANCO MERCANTIL - ID 12068 - 17777 | D264: JOSIANE ARAUJO TEIXEIRA (U) | E264: Cinthia Gomes da Silva | F264: Fechado | H264: 05/09/2025 16:40:32 | I264: 12068
A265: 17777 | B265: 200 MIL | C265: CONSIDERAR TODA A PRODU?AO PARA APURA?AO, TODOS CONVENIOS PRAZO MAXIMO. | D265: 200,00 | E265: 01/09 A 30/09 | F265: MENSAL | G265: Remetente - () Boa tarde! A bonificação sera paga no Código: 12068 CODIGO DO CORRETOR: 12068 17777 PERIODO: 01/09 A 30/09 TIPO DE FECHAMENTO: MENSAL META: 200 MIL PERCENTUAL DE PREMIO: 200,00 PARAMETRO: CONSIDERAR TODA A PRODUÇAO PARA APURAÇAO, TODOS CONVENIOS PRAZO MAXIMO. ; Remetente - () Josi, bom dia. Campanha parametrizada. Meta 8605 Não tem como considerar prazo maximo de todos os bancos, portanto foi considerado todos os prazos. ;
A266: 1766867 | B266: PARAMETRIZACAO DE CAMPANHA | C266: PARAMETRIZAR CAMPANHA - ID: 3594 | D266: LUCAS GUIMARAES EVARISTO (U) | E266: Cinthia Gomes da Silva | F266: Fechado | H266: 05/09/2025 16:20:59 | I266: 3594 | J266: 200.000,00 | K266: TODA PRODU??O | L266: R$ 200,00 FIXO | M266: 01/09 a 30/09 | N266: MENSAL | O266: Remetente - () Prezados, boa tarde! Favor parametrizar campanha. CODIGO DO CORRETOR: 3594 PERIODO: 01/09/2025 a 30/09/2025 TIPO DE FECHAMENTO: MENSAL META: 200.000,00 PERCENTUAL DE PREMIO: R$ 200,00 FIXO PARAMETRO: TODA PRODUÇÃO ; Remetente - () Lucas, bom dia. Campanha parametrizada. Meta 8606;
A267: 1766860 | B267: PARAMETRIZACAO DE CAMPANHA | C267: PARAMETRIZAR CAMPANHA - ID: 1328 | D267: LUCAS GUIMARAES EVARISTO (U) | E267: Cinthia Gomes da Silva | F267: Fechado | H267: 05/09/2025 16:03:52 | I267: 1328 | J267: 300.000,00 | K267: TODA PRODU??O, EXCETO TABELAS QUE POSSUEM REGRA VIP APROVADA | L267: 0,30% | M267: 01/09 a 30/09 | N267: MENSAL | O267: Remetente - () Boa tarde! Favor aprovar campanha. CODIGO DO CORRETOR: 1328 PERIODO: 01/09/2025 a 30/09/2025 TIPO DE FECHAMENTO: MENSAL META: 300.000,00 PERCENTUAL DE PREMIO: 0,30% PARAMETRO: TODA PRODUÇÃO, EXCETO TABELAS QUE POSSUEM REGRA VIP APROVADA ; Remetente - () Lucas, bom dia. Campanha parametrizada. Meta 8607;
A268: 1766787 | B268: PARAMETRIZACAO DE CAMPANHA | C268: PARAMETRIZAR CAMPANHA - ID 13977 | D268: JOSIANE ARAUJO TEIXEIRA (U) | E268: Cinthia Gomes da Silva | F268: Fechado | H268: 05/09/2025 15:14:40 | I268: 13977 | J268: SEM META | K268: DESCRI?AO | L268: DESCRI??O | M268: 01/09 a 30/09 | N268: MENSAL | O268: Remetente - () CAMPANHA 1: TODO A PRODUÇÃO FACTA - SEM META - BONIFICAÇÃO 0,50 CAMPANHA 2: TODA A PRODUÇÃO AMIGOZ - SEM META - BONIFICAÇÃO 3,50% CAMPANHA 3: TODOA APRODUÇÃO DAYCOVAL - SEM META - 85% DO RECEBIDO CODIGO DO CORRETOR: 13977 PERIODO: 01/09 A 30/09 TIPO DE FECHAMENTO: MENSAL META: SEM META PERCENTUAL DE PREMIO: DESCRIÇÃO PARAMETRO: DESCRIÇAO ; Remetente - () Josi, bom dia. Campanha parametrizada. Meta 8595 8608 8609 ;
A269: 1766777 | B269: PARAMETRIZACAO DE CAMPANHA | C269: PARAMETRIZAÇÃO DE CAMPANHA - ID 15313 | D269: JOSIANE ARAUJO TEIXEIRA (U) | E269: Cinthia Gomes da Silva | F269: Fechado | H269: 05/09/2025 15:09:14 | I269: 15313 | J269: SEM META | K269: DESCRI?AO | L269: DESCRI??O | M269: 01/09 a 30/09 | N269: MENSAL | O269: Remetente - () bOA TARDE! CAMPANAH 1 : Banco c6 - TODA A PRODUÇAO NOVO- SEM META -BONIFICAÇAÕ 0,20% CAMPANHA 2 - BANCO FACTA TODA A PRODUÇÃO CONFORME REGRA - SEM META- BONIFICAÇÃO 0,50% CODIGO DO CORRETOR: 15313 PERIODO: 01/09 A 30/09 TIPO DE FECHAMENTO: MENSAL META: SEM META PERCENTUAL DE PREMIO: DESCRIÇÃO PARAMETRO: DESCRIÇAO ; Remetente - () Josi, bom dia. Campanha parametrizada. Meta 8610 8596 ;
A270: 1766695 | B270: PARAMETRIZACAO DE CAMPANHA | C270: PARAMETRIZAR DATA DE EMISSÃO DO RELATORIO - ID 7882 | D270: JOSIANE ARAUJO TEIXEIRA (U) | E270: Cinthia Gomes da Silva | F270: Fechado | H270: 05/09/2025 14:05:30 | I270: 7882 | J270: SEM META | K270: BONIFICA??O ESPECIFICA PARA O PRODUTO PORTABILIDADE / BANCO C6 / CONVENIO INSS | L270: 0,20 | M270: 01/09 a 30/09 | N270: MENSAL | O270: Remetente - () bOA TARDE! CODIGO DO CORRETOR: 7882 PERIODO: 01/09 A 30/09 TIPO DE FECHAMENTO: MENSAL META: SEM META PERCENTUAL DE PREMIO: 0,20 PARAMETRO: BONIFICAÇÃO ESPECIFICA PARA O PRODUTO PORTABILIDADE / BANCO C6 / CONVENIO INSS ; Remetente - () Josi, bom dia. Campanha parametrizada. Meta 8612;
A271: 1766691 | B271: PARAMETRIZACAO DE CAMPANHA | C271: PARAMETRIZAR CAMPANHA BANCO MERCANTIL - ID 1212 | D271: JOSIANE ARAUJO TEIXEIRA (U) | E271: Cinthia Gomes da Silva | F271: Fechado | H271: 05/09/2025 14:01:10 | I271: 1212 | J271: SEM META | K271: TODA PRODU??O BANCO DIGIO DE ACORDO COM A REGRA DA CAMPANHA DO DIGIO | L271: 0.50% | M271: 01/09 A 31/011 | N271: MENSAL | O271: Remetente - () Boa tarde! CODIGO DO CORRETOR: 1212 PERIODO: 01/09 A 31/011 TIPO DE FECHAMENTO: MENSAL META: SEM META PERCENTUAL DE PREMIO: 0.50% PARAMETRO: TODA PRODUÇÃO BANCO DIGIO DE ACORDO COM A REGRA DA CAMPANHA DO DIGIO ; Remetente - () Josi, bom dia. Campanha parametrizada. Meta 8614 8615 8616 ;
A272: 1766519 | B272: PARAMETRIZACAO DE CAMPANHA | C272: PARAMETRIZAR CAMPANHA - ID: 16502 | D272: LUCAS GUIMARAES EVARISTO (U) | E272: Cinthia Gomes da Silva | F272: Fechado | H272: 05/09/2025 11:25:17 | I272: 16502 | J272: SEM META | K272: TODA PRODU??O DO BANCO AMIGOZ | L272: 1% | M272: 01/09 a 30/09 | N272: MENSAL | O272: Remetente - () Bom dia! Favor parametrizar campanha. CODIGO DO CORRETOR: 16502 PERIODO: 01/09/2025 a 30/09/2025 TIPO DE FECHAMENTO: MENSAL META: SEM META PERCENTUAL DE PREMIO: 1% PARAMETRO: TODA PRODUÇÃO DO BANCO AMIGOZ ; Remetente - () Lucas, bom dia. Campanha ja solicitada atraves do chamado 1765863;
A273: 1766516 | B273: PARAMETRIZACAO DE CAMPANHA | C273: PARAMETRIZAR CAMPANHA - ID: 7640 | D273: LUCAS GUIMARAES EVARISTO (U) | E273: Cinthia Gomes da Silva | F273: Fechado | H273: 05/09/2025 11:23:53 | I273: 7640 | J273: SEM META | K273: BANCO CAPITAL CONSIG(gov pi,gov ma,pref s?o luiz,pref picos-pi) | L273: 1,5% | M273: 01/09 a 30/09 | N273: MENSAL | O273: Remetente - () Bom dia! Favor parametrizar campanha, Banco CAPITAL CONSIG, CONSSIDERANDO TODA PRODUÇÃO DOS CONVENIOS ABAIXO. gov pi, gov ma, pref são luiz, pref picos-pi CODIGO DO CORRETOR: 7640 PERIODO: 01/09/2025 a 30/09/2025 TIPO DE FECHAMENTO: MENSAL META: SEM META PERCENTUAL DE PREMIO: 1,5% PARAMETRO: BANCO CAPITAL CONSIG(gov pi,gov ma,pref são luiz,pref picos-pi) ; Remetente - () Lucas, bom dia Campanha ja parametrizada, atraves do chamado 1765866;
A274: 1766509 | B274: PARAMETRIZACAO DE CAMPANHA | C274: PARAMETRIZAR CAMPANHA - ID: 16153 | D274: LUCAS GUIMARAES EVARISTO (U) | E274: Cinthia Gomes da Silva | F274: Fechado | H274: 05/09/2025 11:21:52 | I274: 16153 | J274: SEM META | K274: TODA PRODU??O DO BANCO AMIGOZ | L274: 1% | M274: 01/09 a 30/09 | N274: MENSAL | O274: Remetente - () Bom dia! Favo parametrizar campanha. CODIGO DO CORRETOR: 16153 PERIODO: 01/09/2025 a 30/09/2025 TIPO DE FECHAMENTO: MENSAL META: SEM META PERCENTUAL DE PREMIO: 1% PARAMETRO: TODA PRODUÇÃO DO BANCO AMIGOZ ; Remetente - () Lucas, bom dia. Campanha parametrizada atraves do chamado 1765863;
A275: 1766504 | B275: PARAMETRIZACAO DE CAMPANHA | C275: PARAMETRIZAR CAMPANHA - ID: 9648 | D275: LUCAS GUIMARAES EVARISTO (U) | E275: Cinthia Gomes da Silva | F275: Fechado | H275: 05/09/2025 11:19:54 | I275: 9648 | J275: SEM META | K275: TODA PRODU??O DO BANCO AMIGOZ | L275: 1% | M275: 01/09 a 30/09 | N275: MENSAL | O275: Remetente - () Bom dia! Favor parametrizar campanha. CODIGO DO CORRETOR: 9648 PERIODO: 01/09/2025 a 30/09/2025 TIPO DE FECHAMENTO: MENSAL META: SEM META PERCENTUAL DE PREMIO: 1% PARAMETRO: TODA PRODUÇÃO DO BANCO AMIGOZ ; Remetente - () Lucas, bom dia. Campanha parametrizada atraves do chamado 1765858;
A276: 1766497 | B276: PARAMETRIZACAO DE CAMPANHA | C276: PARAMETRIZAR CAMPANHA - ID: 8437 | D276: LUCAS GUIMARAES EVARISTO (U) | E276: Cinthia Gomes da Silva | F276: Fechado | H276: 05/09/2025 11:17:24 | I276: 8437 | J276: SEM META | K276: TODA PRODU??O DO BANCO AMIGOZ | L276: 1% | M276: 01/09 a 30/09 | N276: MENSAL | O276: Remetente - () Bom dia! Favor parametrizar campanha. CODIGO DO CORRETOR: 8437 PERIODO: 01/09/2025 a 30/09/2025 TIPO DE FECHAMENTO: MENSAL META: SEM META PERCENTUAL DE PREMIO: 1% PARAMETRO: TODA PRODUÇÃO DO BANCO AMIGOZ ; Remetente - () Lucas, bom dia. Campanha parametrizada atraves do chamado 1765858;
A277: 1766493 | B277: PARAMETRIZACAO DE CAMPANHA | C277: PARAMETRIZAR CAMPANHA - ID: 14750 | D277: LUCAS GUIMARAES EVARISTO (U) | E277: Cinthia Gomes da Silva | F277: Fechado | H277: 05/09/2025 11:13:06 | I277: 14750 | J277: SEM META | K277: CONFORME DESCRI??O | L277: CONFORME DESCRI??O | M277: 01/09 a 30/09 | N277: MENSAL | O277: Remetente - () Bom dia! Favor parametrizar campanha conforme abaixo. *BANCO FACTA - CONSIDERAR TODA PRODUÇÃO CONFORME REGRA FACTA - SEM META - BONUS DE 0,50% *BANCO AMIGOZ - CONSIDERAR TODA PRODUÇÃO - SEM META - BONUS 1%. *BANCO C6 - CONSIDERAR TODA PRODUÇÃO - SEM META- BONUS DE 0,20%. CODIGO DO CORRETOR: 14750 PERIODO: 01/09/2025 a 30/09/2025 TIPO DE FECHAMENTO: MENSAL META: SEM META PERCENTUAL DE PREMIO: CONFORME DESCRIÇÃO PARAMETRO: CONFORME DESCRIÇÃO ; Remetente - () Lucas, bom dia . Campanha Facta e Amigoz, ja parametrizado atraves do chamado 1765852; Remetente - () Lucas, bom dia. Campanha parametrizada. Meta 8313 ;
... A339: 1743354 | B339: PARAMETRIZACAO DE CAMPANHA | C339: CAMPNAHA AGOSTO I COD 3024 - 6839 I | D339: BIANCA CRISTIANE SOARES SANTOS TERENCIO (U) | E339: Cinthia Gomes da Silva | F339: Fechado | H339: 04/08/2025 09:40:53 | I339: 3024 - 6839 | J339: SEM META | K339: TODOS OS BANCOS E AS TABELAS EXCETO DO BANCO PAN | L339: 0,30 | M339: 01/08 A 31/12 | N339: SEMESTRAL | O339: Remetente - () Bom dia ! Gentileza renovar campanha conforme solicitado. TODOS OS BANCOS E AS TABELAS EXCETO DO BANCO PAN CODIGO DO CORRETOR: 3024 - 6839 PERIODO: 01/08 A 31/12 TIPO DE FECHAMENTO: SEMESTRAL META: SEM META PERCENTUAL DE PREMIO: 0,30 PARAMETRO: TODOS OS BANCOS E AS TABELAS EXCETO DO BANCO PAN ; Remetente - () ; Remetente - () ; Remetente - () ; Remetente - () Campanha parametrtizada cod meta 7905 Favor informar qual codigo sera realizado ao credito. ; Remetente - () Boa tarde! O crédito deverá ser realizado no jarvis 6839; Remetente - () Obrigada pelo retorno ;

Sheet AGO - 25
A1: 08 - AGOSTO | B1: QUANTIDADE DE METAS: | D1: =COUNTIF($C:$C,$A$1) -> 556
A2: TIPO DE FECHAMETO | B2: CÓD META | C2: FECHAMENTO | D2: COD | E2: INICIO | F2: FIM | G2: PARÂMETRO | H2: PERÍODO FECHAMENTO | I2: META | J2: PERC DE PRÊMIO | K2: PRODUÇÃO MÊS | L2: CRÉDITO | M2: FILIAL | N2: GERENTE | O2: CHAMADO / E-MAIL | P2: DATA-CHAM/E-MAIL | Q2: OBS
A3: 2- MANUAL | B3: 6194 | C3: 08 - AGOSTO | D3: 4310 | 13955 | E3: 45870 | F3: 45900 | G3: IREMOS CONSIDERAR TODA A PRODUÇÃO / EXCETO AS TABELAS QUE POSSUEM VIP | H3: MENSAL | I3: 300000 | J3: 0.004 | M3: FILIAL BH2 | N3: WANDA MARIA MARTINS | O3: PARAMETRIZAR CAMPNAHA - BANCO FACTA - ID 4310 /13955 | P3: 45728 | Q3: CREDITO PARA O 14603
A4: 1- AUTOMÁTICO | B4: 6209 | C4: 08 - AGOSTO | D4: 7934 | E4: 45870 | F4: 45900 | G4: TODO A PRODUÇÃO | H4: MENSAL | I4: 1000 | J4: 0.002 | M4: FILIAL JOAO PESSOA | N4: WELLINGTON DE MELO COUTINHO CHAVES | O4: PARAMETRIZAR CAMPANHA - ID 7934 - TODA A PRODUÇÃO | P4: 45734
A5: 1- AUTOMÁTICO | B5: 6246 | C5: 08 - AGOSTO | D5: 1729 | 8125 | E5: 45870 | F5: 45900 | G5: TODA A PRODUÇÃO | H5: MENSAL | I5: 600000 | J5: 0.005 | M5: FILIAL BH2 | N5: WANDA MARIA MARTINS | O5: PARAMETRIZAR CAMPANHA - ID: 1729 / 8125 - REF: MARÇO 2025 | P5: 45737 | Q5: CREDITO PARA O 1729
A6: 2- MANUAL | B6: calcular e informar no e-mail | C6: - | D6: 12765 | E6: 45870 | F6: 45900 | G6: TODA PRODUÇÃO - CASO ATINJA OU NÃO, APENAS RETORNAR NO E-MAIL COMUNICANDO A PRODUÇÃO | H6: MENSAL | I6: 1000000 | J6: 0 | M6: FILIAL VITORIA | N6: RAHYZA EUSTACHIO DA SILVA | O6: Re: Antecipação de valores RL Rangel Serviços LTDA - 12765 (Projeto de ampliação Call Center) | P6: 45740
A7: 2- MANUAL | B7: 6307 | C7: 08 - AGOSTO | D7: 14533 | E7: 45706 | F7: 45900 | G7: TODA A PRODUÇÃO DOS BANCOS:C6 , FACTA , PAN , DAYCOVAL ,MEU CRED BANK , AMIGOZ ,BMG --em agosto, caso a parceira atinja 50% da meta anual, iremos pagar 50% do Bônus. | H7: MENSAL | I7: 25000000 | J7: 0.0005 | M7: FILIAL SAO LUIZ | N7: WANDER CRISTIAN ANTUNES BARBOSA | O7: PARAMETRIZAR CAMPANHA - ID 14533 - PRODUÇÃO TOTAL | P7: 45748
A8: 1- AUTOMÁTICO | B8: 6381 | C8: 08 - AGOSTO | D8: 2911 | 11402 | E8: 45870 | F8: 45900 | G8: TODOS BANCOS - INSS / SIAPE - TODOS OS PRODUTOS - EXCETO REFIN - PRAZO DE 84x e 96x | H8: MENSAL | I8: 0.01 | J8: 0.002 | M8: FILIAL VITORIA | N8: NIKHOLLI MARCELLE LEMOS | O8: PARAMETRIZAR CAMPANHA - 2911 E 11402 - ABRIL 2025 | P8: 45754 | Q8: CREDITO PARA O 2911
A9: 2- MANUAL | B9: 8488 | C9: 08 - AGOSTO | D9: 2911 | 11402 | E9: 45870 | F9: 45900 | G9: BANCO FACTA - CONFORME REGULAMENTO | H9: MENSAL | I9: 0.01 | J9: 0.002 | M9: FILIAL VITORIA | N9: NIKHOLLI MARCELLE LEMOS | O9: PARAMETRIZAR CAMPANHA - 2911 E 11402 - ABRIL 2025 | P9: 45754 | Q9: CREDITO PARA O 2911
A10: 2- MANUAL | B10: 6756 | C10: 08 - AGOSTO | D10: 2598 | E10: 45870 | F10: 45900 | G10: TODOS OS BANCOS E TODOS OS PRODUTOS. Exceto banco BMG E ITAU E TABELAS QUE POSSUEM REGRAS VIP APROVADAS) | H10: MENSAL | I10: 0.01 | J10: 0.0025 | M10: FILIAL BH1 | N10: CAROLINE ADRIANA DOS SANTOS BRAGA | O10: PARAMETRIZAR CAMPANHA - ID: 2598 - REF: MAIO 2025 | P10: 45779
A11: 1- AUTOMÁTICO | B11: 7186 | C11: 08 - AGOSTO | D11: 936 | E11: 45870 | F11: 45900 | G11: LOTUS FGTS | H11: MENSAL | I11: 500000 | J11: 0.002 | M11: FILIAL BH2 | N11: ALESSANDRO MACHADO DA SILVA | O11: PARAMETRIZAR CAMPAHA - ID: 936 - REF: JUNHO | P11: 45824
A12: 1- AUTOMÁTICO | B12: 7805 | C12: 08 - AGOSTO | D12: 936 | E12: 45870 | F12: 45900 | G12: LOTUS FGTS | H12: MENSAL | I12: 0.01 | J12: 0.0055 | M12: FILIAL BH2 | N12: ALESSANDRO MACHADO DA SILVA | O12: PARAMETRIZAR CAMPAHA - ID: 936 - REF: JUNHO | P12: 45824
A13: 1- AUTOMÁTICO | B13: 7258 | C13: 08 - AGOSTO | D13: 17354 | E13: 45870 | F13: 45900 | G13: TODA OPERAÇÃO CASH CARD | H13: MENSAL | I13: 0.01 | J13: 0.006 | M13: FILIAL CUIABA | N13: JULIANA DE ALMEIDA SIMPLICIO ROCHA | O13: PARAMETRIZAR CAMPANHA - ID 17353 - CASH CARD | P13: 45828
A14: 2- MANUAL | B14: 7509 | C14: 08 - AGOSTO | D14: 12340 | E14: 45870 | F14: 45900 | G14: TODA A PRODUÇÃO PARA ATINGIMENTO - PAGAMENTO PARA TODA A PRODUÇÃO - EXCETO BMG - VIP | H14: MENSAL | I14: 300000 | J14: 0.0005 | M14: FILIAL UBERLANDIA | N14: MATHEUS REZENDE SUDRE | O14: PARAMETRIZAR CAMPANHA ID 12340 - REF: JULHO 2025 | P14: 45849
A15: 2- MANUAL | B15: 7509 | C15: 08 - AGOSTO | D15: 12340 | E15: 45870 | F15: 45900 | G15: TODA A PRODUÇÃO PARA ATINGIMENTO - PAGAMENTO PARA TODA A PRODUÇÃO - EXCETO BMG - VIP | H15: MENSAL | I15: 500000 | J15: 0.001 | M15: FILIAL UBERLANDIA | N15: MATHEUS REZENDE SUDRE | O15: PARAMETRIZAR CAMPANHA ID 12340 - REF: JULHO 2025 | P15: 45849
A16: 1- AUTOMÁTICO | B16: 7513 | C16: 08 - AGOSTO | D16: 4079 | E16: 45870 | F16: 45900 | G16: MEU CREDBANK - INSS - MEU CREDBANK - INSS - FP - SEGURO TOP - TAXA 1,85 / MEU CREDBANK - INSS - MEU CREDBANK - INSS - FP - SEGURO - TX 1,85 / MEU CREDBANK - INSS - MEU CREDBANK - INSS - FP - SEGURO FLEX | H16: MENSAL | I16: 0.01 | J16: 0.005 | M16: FILIAL UBERLANDIA | N16: JOAO EURICO PINHEIRO IGNACIO DOS SANTOS | O16: PARAMETRIZAR CAMPANHA - ID 4079 - BANCO MEU CREDBANK | P16: 45849
A17: 2- MANUAL | B17: 7535 | C17: 08 - AGOSTO | D17: 17894 | E17: 45870 | F17: 45900 | G17: BANCO FACTA - CONFORME REGULAMENTO | H17: MENSAL | I17: 0.01 | J17: 0.0075 | M17: FILIAL UBERLANDIA | N17: JOAO EURICO PINHEIRO IGNACIO DOS SANTOS | O17: PARAMETRIZACAO CAMPANHA I BANCO FACTA I COD 17894 - JULHO | P17: 45845
A18: 2- MANUAL | B18: 7114 | C18: 08 - AGOSTO | D18: 4079 | E18: 45809 | F18: 45900 | G18: BANCO FACTA - CONFORME REGULAMENTO | H18: MENSAL | I18: 0.01 | J18: 0.0075 | M18: FILIAL UBERLANDIA | N18: JOAO EURICO PINHEIRO IGNACIO DOS SANTOS | O18: PARAMETRIZAR CAMPANHA - ID: 4079 - | P18: 45819
A19: 1- AUTOMÁTICO | B19: 7694 | C19: 08 - AGOSTO | D19: 7460 | 12006 | E19: 45870 | F19: 45900 | G19: CONSIDERAR TODA A PRODUÇAO PARA APURAÇAO DA META E bonificacao | H19: MENSAL | I19: 800000 | J19: 0.001 | M19: FILIAL UBERLANDIA | N19: JOAO EURICO PINHEIRO IGNACIO DOS SANTOS | O19: PARAMETRIZAR CAMPANHA - 7460 / 12006 | P19: 45854 | Q19: CREDITO PARA O 7460
A20: 1- AUTOMÁTICO | B20: 7811 | C20: 08 - AGOSTO | D20: 4190 | E20: 45870 | F20: 45900 | G20: CONSIDERAR TODA A PRODUÇAO DO DIGIO PARA APURAÇAO. | H20: MENSAL | I20: 2000 | J20: 0.002 | M20: FILIAL UBERLANDIA | N20: MATHEUS REZENDE SUDRE | O20: PARAMETRIZAR CAMPANHA - ID 4190 | P20: 45862
A21: 1- AUTOMÁTICO | B21: 7814 | C21: 08 - AGOSTO | D21: 4190 | E21: 45870 | F21: 45900 | G21: CONSIDERAR TODA A PRODUÇAO DO SAFRA PARA APURAÇAO. | H21: MENSAL | I21: 2000 | J21: 0.002 | M21: FILIAL UBERLANDIA | N21: MATHEUS REZENDE SUDRE | O21: PARAMETRIZAR CAMPANHA - ID 4190 | P21: 45862
A22: 2- MANUAL | B22: 7817 | C22: 08 - AGOSTO | D22: 4190 | E22: 45870 | F22: 45900 | G22: BANCO FACTA - CONFORME REGULAMENTO | H22: MENSAL | I22: 2000 | J22: 0.002 | M22: FILIAL UBERLANDIA | N22: MATHEUS REZENDE SUDRE | O22: PARAMETRIZAR CAMPANHA - ID 4190 | P22: 45862
A23: 1- AUTOMÁTICO | B23: 7820 | C23: 08 - AGOSTO | D23: 4190 | E23: 45870 | F23: 45900 | G23: CONSIDERAR TODA A PRODUÇAO DO BANRISUL PARA APURAÇAO. | H23: MENSAL | I23: 2000 | J23: 0.002 | M23: FILIAL UBERLANDIA | N23: MATHEUS REZENDE SUDRE | O23: PARAMETRIZAR CAMPANHA - ID 4190 | P23: 45862
A24: 1- AUTOMÁTICO | B24: 7824 | C24: 08 - AGOSTO | D24: 4190 | E24: 45870 | F24: 45900 | G24: CONSIDERAR TODA A PRODUÇAO DO BMG PARA APURAÇAO. | H24: MENSAL | I24: 2000 | J24: 0.002 | M24: FILIAL UBERLANDIA | N24: MATHEUS REZENDE SUDRE | O24: PARAMETRIZAR CAMPANHA - ID 4190 | P24: 45862
A25: 1- AUTOMÁTICO | B25: 7827 | C25: 08 - AGOSTO | D25: 4190 | E25: 45870 | F25: 45900 | G25: CONSIDERAR TODA A PRODUÇAO DO PAN PARA APURAÇAO. | H25: MENSAL | I25: 2000 | J25: 0.002 | M25: FILIAL UBERLANDIA | N25: MATHEUS REZENDE SUDRE | O25: PARAMETRIZAR CAMPANHA - ID 4190 | P25: 45862
A26: 1- AUTOMÁTICO | B26: 7830 | C26: 08 - AGOSTO | D26: 4190 | E26: 45870 | F26: 45900 | G26: CONSIDERAR TODA A PRODUÇAO DO MEU CREDBANKPARA APURAÇAO. | H26: MENSAL | I26: 2000 | J26: 0.002 | M26: FILIAL UBERLANDIA | N26: MATHEUS REZENDE SUDRE | O26: PARAMETRIZAR CAMPANHA - ID 4190 | P26: 45862
A27: 1- AUTOMÁTICO | B27: 7839 | C27: 08 - AGOSTO | D27: 7337 | E27: 45860 | F27: 45891 | G27: BMG -TODA A PRODUÇÃO | H27: FINAL DE CAMPANHA | I27: 0.01 | J27: 0.02 | M27: FILIAL PORTO ALEGRE | N27: GUSTAVO DANERES BERNEIRA | O27: PARAMETRIZAR CAMPANH - BANCO BMG - ID 7337 | P27: 45861
A28: 1- AUTOMÁTICO | B28: 7833 | C28: 08 - AGOSTO | D28: 2404 | E28: 45870 | F28: 45900 | G28: DAYCOVAL - PORTABILIDADE NOS CONVENIOS SEPLAG / PMMG / IPSM / IPSEMG | H28: MENSAL | I28: 0.01 | J28: 0.005 | M28: FILIAL MC | N28: MAURICIO PEREIRA DOS SANTOS | O28: PARAMETRIZAR CAMPANHA - ID 2404 - PORTABILIDADE DAYCOVAL | P28: 45862
A29: 1- AUTOMÁTICO | B29: 7846 | C29: 08 - AGOSTO | D29: 13891 | E29: 45870 | F29: 45900 | G29: TODA A PRODUÇÃO BANCO MASTER | H29: MENSAL | I29: 0.01 | J29: 0.0125 | M29: FILIAL PORTO ALEGRE | N29: GUSTAVO DANERES BERNEIRA | O29: CAMPANHA BANCO MASTER I JUNHO-AGOSTO I ANDRÉ MEDEIROS | P29: 45862
A30: 2- MANUAL | B30: 6166 | C30: 08 - AGOSTO | D30: 3184 | 12430 | E30: 45870 | F30: 45900 | G30: TODA A PRODUÇÃO PARA ATINGIR A META E CONTABILIZAR-META DESCONSIDERAR BMG E C6 ( INSS /NOVO ) | H30: MENSAL | I30: 300000 | J30: 0.002 | M30: FILIAL BH2 | N30: TIAGO ROGANA FERNANDES | O30: PARAMETRIZAR CAMPANHA - ID 3184/12430 | P30: 45721 | Q30: CREDITO PARA O 3184
A31: 2- MANUAL | B31: 7928 | C31: 08 - AGOSTO | D31: 17711 | E31: 45870 | F31: 45900 | G31: BANCO FACTA - CONFORME REGULAMENTO | H31: MENSAL | I31: 0.01 | J31: 0.0075 | M31: FILIAL SP CAPITAL | N31: GUSTAVO ANDRÉ FERRARI | O31: 1744911 | P31: 45874
A32: 2- MANUAL | B32: 7927 | C32: 08 - AGOSTO | D32: 16898 | E32: 45870 | F32: 45900 | G32: BANCO FACTA - CONFORME REGULAMENTO | H32: MENSAL | I32: 0.01 | J32: 0.0045 | M32: FILIAL SP CAPITAL | N32: GUSTAVO ANDRÉ FERRARI | O32: 1744845 | P32: 45874.6
A33: 1- AUTOMÁTICO | B33: 7926 | C33: 08 - AGOSTO | D33: 14363 | E33: 45870 | F33: 45900 | G33: TODA A PRODUÇÃO DOS CARTÕES RMC E RCC SIAPE - QUERO MAIS CRÉDITO | H33: MENSAL | I33: 1000 | J33: 0.015 | M33: FILIAL FLORIANOPOLIS | N33: JULIO CEZAR DE PAULA ALANO | O33: 1743157 | P33: 45870.735
A34: 2- MANUAL | B34: 7925 | C34: 08 - AGOSTO | D34: 17253 | E34: 45870 | F34: 45900 | G34: BANCO FACTA - CONFORME REGULAMENTO | H34: MENSAL | I34: 0.01 | J34: 0.0075 | M34: FILIAL RJ | N34: IGOR DE ALMEIDA RODRIGUES | O34: 1744722 | P34: 45874.535
A35: 2- MANUAL | B35: 7924 | C35: 08 - AGOSTO | D35: 14129 | E35: 45870 | F35: 45900 | G35: BANCO FACTA - CONFORME REGULAMENTO | H35: MENSAL | I35: 0.01 | J35: 0.0075 | M35: FILIAL RJ | N35: IGOR DE ALMEIDA RODRIGUES | O35: 1744722 | P35: 45874.535
A36: 2- MANUAL | B36: 7923 | C36: 08 - AGOSTO | D36: 2240 | E36: 45870 | F36: 45900 | G36: BANCO FACTA - CONFORME REGULAMENTO | H36: MENSAL | I36: 0.01 | J36: 0.0075 | M36: FILIAL RJ | N36: IGOR DE ALMEIDA RODRIGUES | O36: 1744722 | P36: 45874.535
A37: 1- AUTOMÁTICO | B37: 7922 | C37: 08 - AGOSTO | D37: 17714 | E37: 45870 | F37: 45900 | G37: (PRODUÇÃO GERAL BANCO MASTER) | H37: MENSAL | I37: 1000 | J37: 0.0045 | M37: FILIAL RJ | N37: IGOR DE ALMEIDA RODRIGUES | O37: 1744722 | P37: 45874.535
A38: 1- AUTOMÁTICO | B38: 7921 | C38: 08 - AGOSTO | D38: 14129 | E38: 45870 | F38: 45900 | G38: (PRODUÇÃO GERAL BANCO DÍGIO) | H38: 0 | I38: 1000 | J38: 0.005 | M38: FILIAL RJ | N38: IGOR DE ALMEIDA RODRIGUES | O38: 1744722 | P38: 45874.535
A39: 2- MANUAL | B39: 7920 | C39: 08 - AGOSTO | D39: 8835 | E39: 45870 | F39: 45900 | G39: BANCO FACTA - INSS / FGTS - CONFORME REGULAMENTO | H39: MENSAL | I39: 0.01 | J39: 0.006 | M39: FILIAL SP CAPITAL | N39: DANIELA PRADO BULDO | O39: 1744703 | P39: 45874.525
A40: 2- MANUAL | B40: 7919 | C40: 08 - AGOSTO | D40: 13929 | E40: 45870 | F40: 45900 | G40: BANCO FACTA - INSS / FGTS - CONFORME REGULAMENTO | H40: MENSAL | I40: 0.01 | J40: 0.006 | M40: FILIAL SP CAPITAL | N40: DANIELA PRADO BULDO | O40: 1744571 | P40: 45874.471
A41: 1- AUTOMÁTICO | B41: 7918 | C41: 08 - AGOSTO | D41: 15332 | E41: 45870 | F41: 45900 | G41: PRODUÇÃO GERAL BANCO MASTER | H41: MENSAL | I41: 0.01 | J41: 0.01 | M41: FILIAL BH2 | N41: WANDA MARIA MARTINS | O41: 1744553 | P41: 45874.467
A42: 2- MANUAL | B42: 7913 | C42: 08 - AGOSTO | D42: 17614 | E42: 45870 | F42: 45900 | G42: BANCO FACTA - CONFORME REGULAMENTO | H42: MENSAL | I42: 0.01 | J42: 0.0075 | M42: FILIAL SP CAPITAL | N42: DANIELA PRADO BULDO | O42: 1744544 | P42: 45874.464
A43: 2- MANUAL | B43: 7912 | C43: 08 - AGOSTO | D43: 13007 | E43: 45870 | F43: 45900 | G43: BANCO FACTA - CONFORME REGULAMENTO | H43: MENSAL | I43: 0.01 | J43: 0.005 | M43: FILIAL PRESIDENTE PRUDENTE | N43: HAROLDO PERATELLI RODRIGUES DA COSTA | O43: 1744536 | P43: 45874.462
A44: 1- AUTOMÁTICO | B44: 7911 | C44: 08 - AGOSTO | D44: 15874 | E44: 45870 | F44: 45900 | G44: PRODUÇÃO GERAL QUERO + CRÉDITO | H44: MENSAL | I44: 0.01 | J44: 0.005 | M44: FILIAL BH2 | N44: CAROLINE ADRIANA DOS SANTOS BRAGA | O44: 1744531 | P44: 45874.46
A45: 2- MANUAL | B45: 7910 | C45: 08 - AGOSTO | D45: 12021 | E45: 45870 | F45: 45900 | G45: BANCO FACTA - CONFORME REGULAMENTO | H45: MENSAL | I45: 0.01 | J45: 0.005 | M45: FILIAL SAO LUIZ | N45: WANDER CRISTIAN ANTUNES BARBOSA | O45: 1744420 | P45: 45874.423
A46: 2- MANUAL | B46: 8280 | C46: 08 - AGOSTO | D46: 11937 | E46: 45870 | F46: 45900 | G46: BANCO FACTA - CONFORME REGULAMENTO | H46: MENSAL | I46: 0.01 | J46: 0.005 | M46: FILIAL SAO LUIZ | N46: WANDER CRISTIAN ANTUNES BARBOSA | O46: 1744420 | P46: 45874.423
A47: 1- AUTOMÁTICO | B47: 7909 | C47: 08 - AGOSTO | D47: 8476 | E47: 45870 | F47: 45900 | G47: PRODUÇÃO GERAL DE CARTÃO CONSIGNADO E CARTÃO BENEFÍCIO (TODOS OS CONVÊNIOS) | H47: MENSAL | I47: 1000 | J47: 0.011 | M47: FILIAL FLORIANOPOLIS | N47: JULIO CEZAR DE PAULA ALANO | O47: 1744373 | P47: 45874.404
A48: 2- MANUAL | B48: 7908 | C48: 08 - AGOSTO | D48: 17859 | 17918 | E48: 45870 | F48: 45900 | G48: BANCO FACTA - CONFORME REGULAMENTO | H48: MENSAL | I48: 0.01 | J48: 0.006 | M48: FILIAL SP CAPITAL | N48: GUSTAVO ANDRÉ FERRARI | O48: 1743759 | P48: 45873.57 | Q48: CREDITO PARA O 17859
A49: 1- AUTOMÁTICO | B49: 7907 | C49: 08 - AGOSTO | D49: 17938 | E49: 45870 | F49: 45900 | G49: BANCO MERCANTIL - TODA A PRODUÇÃO DE CARTÕES | H49: MENSAL | I49: 0.01 | J49: 0.002 | M49: FILIAL BH2 | N49: ALESSANDRO MACHADO DA SILVA | O49: 1743775 | P49: 45873.577
A50: 1- AUTOMÁTICO | B50: 7906 | C50: 08 - AGOSTO | D50: 15818 | 16763 | E50: 45870 | F50: 45900 | G50: BANCO MASTER - TODA A PRODUÇÃO | H50: MENSAL | I50: 0.01 | J50: 0.015 | M50: FILIAL SP CAPITAL | N50: GUSTAVO ANDRÉ FERRARI | O50: 1743556 | P50: 45873.471 | Q50: CREDITO PARA O 16763
A51: 2- MANUAL | B51: 7904 | C51: 08 - AGOSTO | D51: 10940 | E51: 45870 | F51: 45900 | G51: BANCO FACTA - CONFORME REGULAMENTO | H51: MENSAL | I51: 0.01 | J51: 0.004 | M51: FILIAL BH2 | N51: TATIANA BRUNA DOS SANTOS MIGUEL | O51: 1743315 | P51: 45873.4
A52: 1- AUTOMÁTICO | B52: 7903 | C52: 08 - AGOSTO | D52: 6680 | E52: 45870 | F52: 45900 | G52: BANCO QUERO MAIS - SIAPE - TODA A PRODUÇÃO | H52: MENSAL | I52: 1000 | J52: 0.015 | M52: FILIAL UBERLANDIA | N52: MAURICIO PEREIRA DOS SANTOS | O52: 1743154 | P52: 45870.734
A53: 2- MANUAL | B53: 7971 | C53: 08 - AGOSTO | D53: 16358 | E53: 45870 | F53: 45900 | G53: BANCO FACTA - CONFORME REGULAMENTO | H53: MENSAL | I53: 0.01 | J53: 0.006 | M53: FILIAL SP CAPITAL | N53: FERNANDA SOARES OTANI | O53: 1748975 | P53: 45880
A54: 2- MANUAL | B54: 7972 | C54: 08 - AGOSTO | D54: 18120 | E54: 45870 | F54: 45900 | G54: BANCO FACTA - CONFORME REGULAMENTO | H54: MENSAL | I54: 0.01 | J54: 0.0075 | M54: FILIAL SP CAPITAL | N54: FERNANDA SOARES OTANI | O54: 1748961 | P54: 45880
A55: 2- MANUAL | B55: 7973 | C55: 08 - AGOSTO | D55: 9321 | 14244 | 13184 | E55: 45870 | F55: 45900 | G55: TODA A PRODUÇÃO - EXCETO PORT E CLT | H55: MENSAL | I55: 150000 | J55: 0.003 | M55: FILIAL SALVADOR | N55: DANIELA SANTOS DA SILVA | O55: 1748747 | P55: 45880 | Q55: CREDITO PARA O 9321
A56: 2- MANUAL | B56: 7974 | C56: 08 - AGOSTO | D56: 16819 | E56: 45870 | F56: 45900 | G56: BANCO FACTA - CONFORME REGULAMENTO | H56: MENSAL | I56: 0.01 | J56: 0.005 | M56: FILIAL SP CAPITAL | N56: LAIS PASCOAL PEREIRA | O56: 1748874 | P56: 45880
A57: 2- MANUAL | B57: 7975 | C57: 08 - AGOSTO | D57: 14482 | E57: 45870 | F57: 45900 | G57: DAYCOVAL -TODAS AS TABELAS QUE CONTEMPLA | H57: MENSAL | I57: 0.01 | J57: 0.007 | M57: FILIAL SP CAPITAL | N57: LAIS PASCOAL PEREIRA | O57: 1748869 | P57: 45880
A58: 2- MANUAL | B58: 7976 | C58: 08 - AGOSTO | D58: 6962 | E58: 45870 | F58: 45900 | G58: BANCO DAYCOVAL - TABELAS QUE RECEBEMOS BÔNUS | H58: MENSAL | I58: 0.01 | J58: 34% DO QUE FOR RECEBIDO PELO BANCO | M58: FILIAL SALVADOR | N58: LARISSA CERQUEIRA SOUSA | O58: 1748861 | P58: 45880
A59: 2- MANUAL | B59: 7977 | C59: 08 - AGOSTO | D59: 16382 | E59: 45870 | F59: 45900 | G59: BANCO FACTA - CONFORME REGULAMENTO | H59: MENSAL | I59: 0.01 | J59: 0.0075 | M59: FILIAL BELEM | N59: KARLA SUANE AZEVEDO DOS SANTOS | O59: 1748847 | P59: 45880
A60: 1- AUTOMÁTICO | B60: 7978 | C60: 08 - AGOSTO | D60: 15087 | E60: 45870 | F60: 45900 | G60: REFIN DA PORT \ MEUCREDBANK\INSS\96 E 84 X | H60: MENSAL | I60: 30000 | J60: 0.0025 | M60: FILIAL BELEM | N60: KARLA SUANE AZEVEDO DOS SANTOS | O60: 1748762 | P60: 45880
A61: 1- AUTOMÁTICO | B61: 7979 | C61: 08 - AGOSTO | D61: 17142 | E61: 45870 | F61: 45900 | G61: MASTER-TODOS OS PRODUTOS E PRAZOS | H61: MENSAL | I61: 30000 | J61: 0.005 | M61: FILIAL BELEM | N61: KARLA SUANE AZEVEDO DOS SANTOS | O61: 1748752 | P61: 45880
A62: 2- MANUAL | B62: 7980 | C62: 08 - AGOSTO | D62: 14482 | E62: 45870 | F62: 45900 | G62: BANCO FACTA - CONFORME REGULAMENTO | H62: MENSAL | I62: 0.01 | J62: 0.0075 | M62: FILIAL SP CAPITAL | N62: LAIS PASCOAL PEREIRA | O62: 1748748 | P62: 45880
A63: 1- AUTOMÁTICO | B63: 7981 | C63: 08 - AGOSTO | D63: 17352 | E63: 45870 | F63: 45900 | G63: master-PRODUÇÃO GERAL | H63: MENSAL | I63: 300000 | J63: 0.018 | M63: FILIAL MACAPA | N63: ADAN YURI MACIEL DE ARAUJO | O63: 1748741 | P63: 45880
A64: 2- MANUAL | B64: 7982 | C64: 08 - AGOSTO | D64: 16988 | E64: 45870 | F64: 45900 | G64: BANCO FACTA - CONFORME REGULAMENTO | H64: MENSAL | I64: 0.01 | J64: 0.0075 | M64: FILIAL SP CAPITAL | N64: FERNANDA SOARES OTANI | O64: 1748595 | P64: 45880
A65: 1- AUTOMÁTICO | B65: 7983 | C65: 08 - AGOSTO | D65: 16977 | E65: 45870 | F65: 45900 | G65: AMIGOZ-TODAS AS TABELAS RMC E RCC INSS | H65: MENSAL | I65: 0.01 | J65: 0.035 | M65: FILIAL SP CAPITAL | N65: FERNANDA SOARES OTANI | O65: 1748581 | P65: 45880
A66: 1- AUTOMÁTICO | B66: 7984 | C66: 08 - AGOSTO | D66: 16977 | E66: 45870 | F66: 45900 | G66: PRESENÇA BANK-TODAS AS TABELAS DE NOVO E FGTS | H66: MENSAL | I66: 0.01 | J66: 0.008 | M66: FILIAL SP CAPITAL | N66: FERNANDA SOARES OTANI | O66: 1748573 | P66: 45880
A67: 2- MANUAL | B67: 7986 | C67: 08 - AGOSTO | D67: 9061 | 9564 | E67: 45870 | F67: 45900 | G67: CONSIDERAR TODA A PRODUÇÃO PARA ATINGIMENTO - PAGAR SOMENTE SOBRE MARGEM LIVRE - EXCETO ITAU | H67: MENSAL | I67: 400000 | J67: 0.001 | M67: FILIAL GOIANIA | N67: ANGELITA ALVES DA SILVA | O67: 1746915 | P67: 45876 | Q67: CREDITO PARA O 9061
A68: 2- MANUAL | B68: 7929 | C68: 08 - AGOSTO | D68: 16130 | E68: 45870 | F68: 45900 | G68: PAN -INSS (NOVO E REFIN / FGTS TODAS AS TABELAS ( EXCEÇÃO TABELAS DE INVALIDEZ) | H68: MENSAL | I68: 10000 | J68: 0.005 | M68: FILIAL JOAO PESSOA | N68: CHRISTIANE NIELSEN SILVA ARAUJO | O68: 1746672 | P68: 45876 | Q68: ESPELHAR A CAMPANHA CASCATA DO BANCO
A69: 2- MANUAL | B69: 7930 | C69: 08 - AGOSTO | D69: 16130 | E69: 45870 | F69: 45900 | G69: CONVÊNIOS PÚBLICOS (TODOS OS PRODUTOS E TABELAS) do Pan, | H69: MENSAL | I69: 10000 | J69: 0.02 | M69: FILIAL JOAO PESSOA | N69: CHRISTIANE NIELSEN SILVA ARAUJO | O69: 1746672 | P69: 45876
A70: 2- MANUAL | B70: 7931 | C70: 08 - AGOSTO | D70: 16130 | E70: 45870 | F70: 45900 | G70: BANCO PAN SAQUE COMPLEMENTAR TODOS OS CONVÊNIOS | H70: MENSAL | I70: 10000 | J70: 0.0275 | M70: FILIAL JOAO PESSOA | N70: CHRISTIANE NIELSEN SILVA ARAUJO | O70: 1746672 | P70: 45876
A71: 2- MANUAL | B71: 7932 | C71: 08 - AGOSTO | D71: 16130 | E71: 45870 | F71: 45900 | G71: BANCO PAN CARTÃO COM SAQUE | H71: MENSAL | I71: 10000 | J71: 0.0075 | M71: FILIAL JOAO PESSOA | N71: CHRISTIANE NIELSEN SILVA ARAUJO | O71: 1746672 | P71: 45876
A72: 1- AUTOMÁTICO | B72: 7933 | C72: 08 - AGOSTO | D72: 16130 | E72: 45870 | F72: 45900 | G72: BANCO PAN FGTS INSS CLT CAMPANHA FIDELIZA MARGEM LIVRE | H72: MENSAL | I72: 10000 | J72: 0.005 | M72: FILIAL JOAO PESSOA | N72: CHRISTIANE NIELSEN SILVA ARAUJO | O72: 1746672 | P72: 45876 | Q72: ESPELHAR A CAMPANHA FIDELIZA DO BANCO
A73: 1- AUTOMÁTICO | B73: 7935 | C73: 08 - AGOSTO | D73: 16130 | E73: 45870 | F73: 45900 | G73: 0,50% FGTS- Pan - informar que não temos acesso ao bonus desafio | H73: MENSAL | I73: 10000 | J73: 0.005 | M73: FILIAL JOAO PESSOA | N73: CHRISTIANE NIELSEN SILVA ARAUJO | O73: 1746672 | P73: 45876
A74: 1- AUTOMÁTICO | B74: 7934 | C74: 08 - AGOSTO | D74: 16130 | E74: 45870 | F74: 45900 | G74: c6-PRODUÇÃO GERAL | H74: MENSAL | I74: 10000 | J74: 0.002 | M74: FILIAL JOAO PESSOA | N74: CHRISTIANE NIELSEN SILVA ARAUJO | O74: 1746672 | P74: 45876
A75: 1- AUTOMÁTICO | B75: 7936 | C75: 08 - AGOSTO | D75: 16130 | E75: 45870 | F75: 45900 | G75: BANCO AKI CAPITAL CARTÕES TODOS OS CONVÊNIOS | H75: MENSAL | I75: 10000 | J75: 0.0195 | M75: FILIAL JOAO PESSOA | N75: CHRISTIANE NIELSEN SILVA ARAUJO | O75: 1746672 | P75: 45876
A76: 1- AUTOMÁTICO | B76: 7937 | C76: 08 - AGOSTO | D76: 16130 | E76: 45870 | F76: 45900 | G76: BANCO AKI CAPITAL EMPRESTIMO TODOS OS CONVÊNIOS | H76: MENSAL | I76: 10000 | J76: 0.0045 | M76: FILIAL JOAO PESSOA | N76: CHRISTIANE NIELSEN SILVA ARAUJO | O76: 1746672 | P76: 45876
A77: 1- AUTOMÁTICO | B77: 7938 | C77: 08 - AGOSTO | D77: 17204 | 17960 | E77: 45870 | F77: 45900 | G77: TODA A PRODUÇÃO QUERO MAIS | H77: MENSAL | I77: 10000 | J77: 0.0195 | M77: FILIAL JOAO PESSOA | N77: CHRISTIANE NIELSEN SILVA ARAUJO | O77: 1746672 | P77: 45876
A78: 1- AUTOMÁTICO | B78: 7939 | C78: 08 - AGOSTO | D78: 17204 | 17960 | E78: 45870 | F78: 45900 | G78: QUERO MAIS- SIAPE | H78: MENSAL | I78: 10000 | J78: 0.0083 | M78: FILIAL JOAO PESSOA | N78: CHRISTIANE NIELSEN SILVA ARAUJO | O78: 1746672 | P78: 45876
A79: 2- MANUAL | B79: 7940 | C79: 08 - AGOSTO | D79: 17204 | 17960 | E79: 45870 | F79: 45900 | G79: BANCO FACTA - CONFORME REGULAMENTO | H79: MENSAL | I79: 10000 | J79: 0.002 | M79: FILIAL JOAO PESSOA | N79: CHRISTIANE NIELSEN SILVA ARAUJO | O79: 1746672 | P79: 45876
A80: 2- MANUAL | B80: 7941 | C80: 08 - AGOSTO | D80: 15086 | E80: 45870 | F80: 45900 | G80: BANCO FACTA - CONFORME REGULAMENTO | H80: MENSAL | I80: 10000 | J80: 0.005 | M80: FILIAL JOAO PESSOA | N80: CHRISTIANE NIELSEN SILVA ARAUJO | O80: 1746672 | P80: 45876
A81: 1- AUTOMÁTICO | B81: 7942 | C81: 08 - AGOSTO | D81: 15086 | E81: 45870 | F81: 45900 | G81: c6PRODUÇÃO GERAL | H81: MENSAL | I81: 10000 | J81: 0.005 | M81: FILIAL JOAO PESSOA | N81: CHRISTIANE NIELSEN SILVA ARAUJO | O81: 1746672 | P81: 45876
A82: 1- AUTOMÁTICO | B82: 7943 | C82: 08 - AGOSTO | D82: 15086 | E82: 45870 | F82: 45900 | G82: MEU CASH PRODUÇÃO GERAL | H82: MENSAL | I82: 10000 | J82: 0.002 | M82: FILIAL JOAO PESSOA | N82: CHRISTIANE NIELSEN SILVA ARAUJO | O82: 1746672 | P82: 45876
A83: 1- AUTOMÁTICO | B83: 7944 | C83: 08 - AGOSTO | D83: 9286 | E83: 45870 | F83: 45900 | G83: TODA A PRODUÇÃO DIGIO | H83: MENSAL | I83: 30000 | J83: 0.002 | M83: FILIAL SALVADOR | N83: LARISSA CERQUEIRA SOUSA | O83: 1746325 | P83: 45875
A84: 1- AUTOMÁTICO | B84: 7945 | C84: 08 - AGOSTO | D84: 8819 | E84: 45870 | F84: 45900 | G84: TODA A PRODUÇÃO DIGIO | H84: MENSAL | I84: 50000 | J84: 0.003 | M84: FILIAL SALVADOR | N84: LARISSA CERQUEIRA SOUSA | O84: 1746323 | P84: 45875
A85: 1- AUTOMÁTICO | B85: 7946 | C85: 08 - AGOSTO | D85: 6245 | E85: 45870 | F85: 45900 | G85: TODA A PRODUÇÃO DIGIO | H85: MENSAL | I85: 50000 | J85: 0.003 | M85: FILIAL SALVADOR | N85: LARISSA CERQUEIRA SOUSA | O85: 1746323 | P85: 45875
A86: 1- AUTOMÁTICO | B86: 7947 | C86: 08 - AGOSTO | D86: 9286 | E86: 45870 | F86: 45900 | G86: REFIN DA PORT MEU CREDANK | H86: MENSAL | I86: 100000 | J86: 0.001 | M86: FILIAL SALVADOR | N86: LARISSA CERQUEIRA SOUSA | O86: 1746285 | P86: 45875
A87: 1- AUTOMÁTICO | B87: 7948 | C87: 08 - AGOSTO | D87: 1929 | E87: 45870 | F87: 45900 | G87: REFIN DA PORT MEU CREDANK-INSS | H87: MENSAL | I87: 1000 | J87: 0.001 | M87: FILIAL SALVADOR | N87: LARISSA CERQUEIRA SOUSA | O87: 1746285 | P87: 45875
A88: 1- AUTOMÁTICO | B88: 7949 | C88: 08 - AGOSTO | D88: 7769 | E88: 45870 | F88: 45900 | G88: REFIN DA PORT MEU CREDANK-INSS | H88: MENSAL | I88: 1000 | J88: 0.001 | M88: FILIAL SALVADOR | N88: LARISSA CERQUEIRA SOUSA | O88: 1746285 | P88: 45875
A89: 1- AUTOMÁTICO | B89: 7950 | C89: 08 - AGOSTO | D89: 12153 | E89: 45870 | F89: 45900 | G89: REFIN DA PORT MEU CREDANK-INSS | H89: MENSAL | I89: 1000 | J89: 0.001 | M89: FILIAL SALVADOR | N89: LARISSA CERQUEIRA SOUSA | O89: 1746285 | P89: 45875
A90: 1- AUTOMÁTICO | B90: 7951 | C90: 08 - AGOSTO | D90: 7481 | E90: 45870 | F90: 45900 | G90: REFIN DA PORT MEU CREDANK-INSS | H90: MENSAL | I90: 1000 | J90: 0.001 | M90: FILIAL SALVADOR | N90: LARISSA CERQUEIRA SOUSA | O90: 1746285 | P90: 45875
A91: 1- AUTOMÁTICO | B91: 7952 | C91: 08 - AGOSTO | D91: 6048 | E91: 45870 | F91: 45900 | G91: REFIN DA PORT MEU CREDANK-INSS | H91: MENSAL | I91: 1000 | J91: 0.001 | M91: FILIAL SALVADOR | N91: LARISSA CERQUEIRA SOUSA | O91: 1746285 | P91: 45875
... A98: 2- MANUAL | B98: 7959 | C98: 08 - AGOSTO | D98: 16474 | E98: 45870 | F98: 45900 | G98: BANCO FACTA - CONFORME REGULAMENTO | H98: MENSAL | I98: 0.01 | J98: 0.005 | M98: FILIAL SP CAPITAL | N98: GUSTAVO ANDRÉ FERRARI | O98: 1745858 | P98: 45875
A99: 2- MANUAL | B99: 7960 | C99: 08 - AGOSTO | D99: 12378 | 16872 | E99: 45870 | F99: 45900 | G99: BANCO FACTA - CONFORME REGULAMENTO | H99: MENSAL | I99: 0.01 | J99: 0.006 | M99: FILIAL GOIANIA | N99: ALEX SILVA GARCIA | O99: 1745640 | P99: 45875 | Q99: CREDITO PARA O 16872
A100: 2- MANUAL | B100: 7961 | C100: 08 - AGOSTO | D100: 16101 | 12291 | E100: 45870 | F100: 45900 | G100: BANCO FACTA - CONFORME REGULAMENTO | H100: MENSAL | I100: 500000 | J100: 0.005 | M100: FILIAL BOA VISTA | N100: VITORIA MOTTA BARBOSA | O100: 1745617 | P100: 45875 | Q100: CREDITO PARA O 16101
A101: 1- AUTOMÁTICO | B101: 7962 | C101: 08 - AGOSTO | D101: 4629 | E101: 45870 | F101: 45900 | G101: TODAS AS TABELAS COM SEGURO DE CONTRATO NOVO INSS MEU CRED BANK - | H101: MENSAL | I101: 0.01 | J101: 0.01 | M101: FILIAL SAO LUIZ | N101: WANDER CRISTIAN ANTUNES BARBOSA | O101: 1745599 | P101: 45875
A102: 1- AUTOMÁTICO | B102: 7963 | C102: 08 - AGOSTO | D102: 4629 | E102: 45870 | F102: 45900 | G102: BONUS DO REFIN DA PORTABILIDADE MEU CRED BANK ( INSS ) | H102: MENSAL | I102: 0.01 | J102: 0.005 | M102: FILIAL SAO LUIZ | N102: WANDER CRISTIAN ANTUNES BARBOSA | O102: 1745599 | P102: 45875
A103: 1- AUTOMÁTICO | B103: 7964 | C103: 08 - AGOSTO | D103: 4629 | E103: 45870 | F103: 45900 | G103: ODOS OS CARTÕES CONSIGNADO E BENEFÍCIO DO INSS AMIGOZ - | H103: MENSAL | I103: 0.01 | J103: 0.03 | M103: FILIAL SAO LUIZ | N103: WANDER CRISTIAN ANTUNES BARBOSA | O103: 1745599 | P103: 45875
A104: 1- AUTOMÁTICO | B104: 7965 | C104: 08 - AGOSTO | D104: 11652 | E104: 45870 | F104: 45900 | G104: TODAS AS TABELAS COM SEGURO DE CONTRATO NOVO INSS MEU CRED BANK | H104: MENSAL | I104: 0.01 | J104: 0.01 | M104: FILIAL SAO LUIZ | N104: WANDER CRISTIAN ANTUNES BARBOSA | O104: 1745564 | P104: 45875
A105: 1- AUTOMÁTICO | B105: 7966 | C105: 08 - AGOSTO | D105: 11652 | E105: 45870 | F105: 45900 | G105: TODOS OS CARTÕES CONSIGNADO E BENEFÍCIO DO INSS AMIGOZ | H105: MENSAL | I105: 0.01 | J105: 0.03 | M105: FILIAL SAO LUIZ | N105: WANDER CRISTIAN ANTUNES BARBOSA | O105: 1745564 | P105: 45875
A106: 1- AUTOMÁTICO | B106: 7967 | C106: 08 - AGOSTO | D106: 6846 | E106: 45870 | F106: 45900 | G106: MEU CREDBANK - (TODA PRODUÇÃO INSS EXCETO AS TABELAS FP - NORMAL - TX 1,85MEU CREDBANK – INSS - MEU CREDBANK - INSS - FP - SEGURO - TX 1,85) | H106: MENSAL | I106: 0.01 | J106: 0.005 | M106: FILIAL UBERLANDIA | N106: JOAO EURICO PINHEIRO IGNACIO DOS SANTOS | O106: 1745527 | P106: 45875
...

Sheet JUL - 25
A1: Nº | B1: FECHAMENTO | C1: COD | D1: INICIO | E1: FIM | F1: PERÍODO FECHAMENTO | G1: META | H1: PRÊMIO GANHO | I1: FILIAL | J1: SOLICITAÇÃO (E-MAIL) | K1: ASSUNTO (E-MAIL) | L1: PARÂMETRO
A2: 894 | C2: 10452 | D2: 45748 | E2: 45777 | F2: MENSAL | G2: 200000 | H2: 0.002 | I2: FILIAL PORTO ALEGRE | J2: 45756 | K2: PARAMETRIZAÇÃO CAMPANHA I BANCO FACTA I COD 10452 I ABRIL | L2: BANCO FACTA - CONFORME REGULAMENTO
A3: 895 | C3: 10452 | D3: 45748 | E3: 45777 | F3: MENSAL | G3: 300000 | H3: 0.003 | I3: FILIAL PORTO ALEGRE | J3: 45756 | K3: PARAMETRIZAÇÃO CAMPANHA I BANCO FACTA I COD 10452 I ABRIL | L3: BANCO FACTA - CONFORME REGULAMENTO
A4: 896 | C4: 10452 | D4: 45748 | E4: 45777 | F4: MENSAL | G4: 400000 | H4: 0.004 | I4: FILIAL PORTO ALEGRE | J4: 45756 | K4: PARAMETRIZAÇÃO CAMPANHA I BANCO FACTA I COD 10452 I ABRIL | L4: BANCO FACTA - CONFORME REGULAMENTO
A5: 897 | C5: 10452 | D5: 45748 | E5: 45777 | F5: MENSAL | G5: 500000 | H5: 0.005 | I5: FILIAL PORTO ALEGRE | J5: 45756 | K5: PARAMETRIZAÇÃO CAMPANHA I BANCO FACTA I COD 10452 I ABRIL | L5: BANCO FACTA - CONFORME REGULAMENTO
A6: 985 | C6: 3349 / 11938 | D6: 45748 | E6: 45777 | F6: MENSAL | G6: 500000 | H6: 0.002 | I6: FILIAL UBERLANDIA | J6: 45761 | K6: PARAMETRIZAR CAMPANHA - 3349 E 11938 sub | L6: TODA PRODUCAO PARA CONTABILIZAR -META INSS-NOVO-84X -EXCETO ITAU-CREDITO 11938
A7: 1166 | C7: 8465/1363/3728/3729 | D7: 45748 | E7: 45808 | F7: FINAL DE CAMPANHA | G7: 1000000 | H7: 0.02 | I7: FILIAL BH1 | J7: 45749 | K7: PARAMETRIZAR CAMPANHA - ID 8465/1363/3728/3729 - BANCO AMIGOZ | L7: TODA A PRODUÇÃO AMIGOZ-CREDITO o 8465.
A8: 1171 | C8: 1212 | D8: 45778 | E8: 45808 | F8: MENSAL | G8: 500000 | H8: 0.005 | I8: FILIAL UBERLANDIA | J8: 45764 | K8: PARAMETRIZAR CAMPANHA - ID: 1212 - REF: ABRIL E MAIO | L8: BANCO DIGIO CONVENIO SIAPE
A9: 1233 | C9: 16995 | D9: 45778 | E9: 45808 | F9: MENSAL | G9: 200000 | H9: 0.004 | I9: FILIAL PORTO ALEGRE | J9: 45783 | K9: PARAMETRIZAÇÃO CAMPANHA I BANCO FACTA I COD 16995 -MAIO | L9: FACTA CONFORME REGULAMENTO
A10: 1234 | C10: 16995 | D10: 45778 | E10: 45808 | F10: MENSAL | G10: 100000 | H10: 0.003 | I10: FILIAL PORTO ALEGRE | J10: 45783 | K10: PARAMETRIZAÇÃO CAMPANHA I BANCO FACTA I COD 16995 -MAIO | L10: FACTA CONFORME REGULAMENTO
A11: 1237 | C11: 17421 | D11: 45778 | E11: 45808 | F11: MENSAL | G11: 200000 | H11: 0.004 | I11: FILIAL PORTO ALEGRE | J11: 45783 | K11: PARAMETRIZAR CAMPANHA I BANCO FACTA I COD 17421 - MAIO | L11: FACTA CONFORME REGULAMENTO
A12: 1238 | C12: 17421 | D12: 45778 | E12: 45808 | F12: MENSAL | G12: 100000 | H12: 0.003 | I12: FILIAL PORTO ALEGRE | J12: 45783 | K12: PARAMETRIZAR CAMPANHA I BANCO FACTA I COD 17421 - MAIO | L12: FACTA CONFORME REGULAMENTO
A13: 1248 | C13: 10649 | D13: 45778 | E13: 45808 | F13: MENSAL | G13: 200000 | H13: 0.003 | I13: FILIAL RJ | J13: 45784 | K13: PARAMETRIZAR CAMPANHA - GC IGOR | L13: PRODUCAO TOTAL ATINGIR A META-BONIFICACAO NOVOS INSS C 6 ,FACTA , CREDBANK, PRESENÇA E VCTEX
A14: 1336 | C14: 16955 | D14: 45778 | E14: 45808 | F14: MENSAL | G14: 800000 | H14: 0.003 | I14: FILIAL PORTO ALEGRE | J14: 45793 | K14: CAMPANHA BANCO FACTA I 16955 I MAIO | L14: Banco Facta - Novo, cartão, FGTS, refin da port - parcelas todas
A15: 1337 | C15: 16955 | D15: 45778 | E15: 45808 | F15: MENSAL | G15: 1000000 | H15: 0.004 | I15: FILIAL PORTO ALEGRE | J15: 45793 | K15: CAMPANHA BANCO FACTA I 16955 I MAIO | L15: Banco Facta - Novo, cartão, FGTS, refin da port - parcelas todas
A16: 1338 | C16: 16955 | D16: 45778 | E16: 45808 | F16: MENSAL | G16: 1500000 | H16: 0.005 | I16: FILIAL PORTO ALEGRE | J16: 45793 | K16: CAMPANHA BANCO FACTA I 16955 I MAIO | L16: Banco Facta - Novo, cartão, FGTS, refin da port - parcelas todas
A17: 1484 | C17: 6843 | D17: 45778 | E17: 45808 | F17: MENSAL | G17: 0.01 | H17: 0.002 | I17: FILIAL UBERLANDIA | J17: 45805 | K17: PARAMETRIZAR CAMPANHAS 6843 | MAIO | BANCO DIGIO | L17: DIGIO - TODA PRODUÇÃO NÃO LANÇAR CRÉDITO, PARA REGISTRO INTERNO E ABATIMENTO DE DÍVIDA DO CÓDIGO 1419.
A18: 1848 | B18: 07 - JULHO | C18: 12765 | D18: 45839 | E18: 45869 | F18: MENSAL | G18: 1000000 | H18: 0 | I18: 0 | J18: 45740 | K18: Re: Antecipação de valores RL Rangel Serviços LTDA - 12765 (Projeto de ampliação Call Center) | L18: TODA PRODUÇÃO - CASO ATINJA OU NÃO, APENAS RETORNAR NO E-MAIL COMUNICANDO A PRODUÇÃO
A19: 1849 | B19: 07 - JULHO | C19: 17740 | D19: 45839 | E19: 45858 | F19: MENSAL | G19: 0.01 | H19: 0.005 | I19: FILIAL VITORIA | J19: 45854 | K19: CAMPANHA MES JULHO I BANCO MERCANTIL I COD 17740 | L19: BANCO MERCANTIL - Bônus pago referente a venda de cartão RMC E RCC
A20: 1850 | B20: 07 - JULHO | C20: 13718 | D20: 45839 | E20: 45869 | F20: MENSAL | G20: 0.01 | H20: 0.005 | I20: FILIAL BH2 | J20: 45855 | K20: CAMPANHA MES JULHO I COD 13718 | L20: BANCO PRESENÇA - INSS - TODA A PRODUÇÃO
A21: 1851 | B21: 07 - JULHO | C21: 13718 | D21: 45839 | E21: 45869 | F21: MENSAL | G21: 0.01 | H21: 0.035 | I21: FILIAL GOIANIA | J21: 45855 | K21: CAMPANHA MES JULHO I COD 13718 | L21: BANCO AMIGOZ - TODA A PRODUÇÃO EXCETO ( EXCETO PREF RECIFE / TJ MG / JUIZ DE FORA)
A22: 1852 | B22: 07 - JULHO | C22: 11820 | D22: 45839 | E22: 45869 | F22: MENSAL | G22: 0.01 | H22: 0.0075 | I22: FILIAL GOIANIA | J22: 45854 | K22: CAMPANHA MES JULHO I BANCO FACTA I COD 11820 | L22: Bonus pago em cima de contrato novo com seguro/prazo maximo e Refin port até a flex 2 ( Conforme parametro facta )
A23: 1853 | B23: 07 - JULHO | C23: 2619 | D23: 45839 | E23: 45869 | F23: MENSAL | G23: 0.01 | H23: 0.01 | I23: FILIAL BH2 | J23: 45847 | K23: PARAMETRIZAR CAMPANHA - ID 2619 - VCTEX | L23: BANCO VCTEX - TODA A PRODUÇÃO
A24: 1854 | B24: 07 - JULHO | C24: 3895 | D24: 45839 | E24: 45869 | F24: MENSAL | G24: 0.01 | H24: 0.005 | I24: FILIAL GOIANIA | J24: 45854 | K24: PARAMETRIZAR CAMPANHA - BANOC MERCANTIL - ID 3895 | L24: BANCO MERCANTIL - CARTÕES - GRUPO MINAS
A25: 1855 | B25: 07 - JULHO | C25: 17051 | D25: 45839 | E25: 45869 | F25: MENSAL | G25: 0.01 | H25: 0.0015 | I25: FILIAL BH2 | J25: 45854 | K25: CAMAPANHA MES JULHO I BANCO FACTA I COD 17051 | L25: Bonus pago em cima de contrato novo com seguro/prazo maximo e Refin port até a flex 2 ( Conforme parametro facta )
A26: 1856 | B26: 07 - JULHO | C26: 1452 | D26: 45839 | E26: 45869 | F26: MENSAL | G26: 300000 | H26: 0.001 | I26: FILIAL BH2 | J26: 45854 | K26: PARAMETRIZAR CAMPANHA - ID: 1452 - REF: JULHO 2025 | L26: TODA A PRODUÇÃO PARA ATINGIMENTO - TODA A PRODUÇÃO EXCETO ITAU PARA PAGAMENTO
A27: 1857 | B27: 07 - JULHO | C27: 3349 / 11938 | D27: 45839 | E27: 45869 | F27: MENSAL | G27: 300000 | H27: 0.001 | I27: FILIAL UBERLANDIA | J27: 45854 | K27: PARAMETRIZAR CAMPANHA - 11938 / 3349 | L27: TODA A PRODUÇÃO atingir a meta- bonificação TODA A PRODUÇÃO novo-inss-84x exceto banco itau.
A28: 1858 | B28: 07 - JULHO | C28: 3349 / 11938 | D28: 45839 | E28: 45869 | F28: MENSAL | G28: 500000 | H28: 0.002 | I28: FILIAL UBERLANDIA | J28: 45854 | K28: PARAMETRIZAR CAMPANHA - 11938 / 3349 | L28: TODA A PRODUÇÃO atingir a meta- bonificação TODA A PRODUÇÃO novo-inss-84x exceto banco itau.
A29: 1859 | B29: 07 - JULHO | C29: 15516 | D29: 45839 | E29: 45869 | F29: MENSAL | G29: 0.01 | H29: 0.005 | I29: FILIAL UBERLANDIA | J29: 45854 | K29: CAMPANHA MES JULHO I BANCO FACTA I COD 15516 | L29: Bonus pago em cima de contrato novo com seguro/prazo maximo e Refin port até a flex 2 ( Conforme parametro facta )
A30: 1860 | B30: 07 - JULHO | C30: 12732 | D30: 45839 | E30: 45869 | F30: MENSAL | G30: 0.01 | H30: 0.005 | I30: FILIAL BH2 | J30: 45854 | K30: CAMPANHA MES JULHO I BANCO FACTA I COD 12732 | L30: Bonus pago em cima de contrato novo com seguro/prazo maximo e Refin port até a flex 2 ( Conforme parametro facta )
A31: 1861 | B31: 07 - JULHO | C31: 16892 | D31: 45839 | E31: 45869 | F31: MENSAL | G31: 0.01 | H31: 0.003 | I31: FILIAL BH1 | J31: 45854 | K31: CAMPANHA MES JULHO I BANCO FACTA I COD 16892 | L31: Bonus pago em cima de contrato novo com seguro/prazo maximo e Refin port até a flex 2 ( Conforme parametro facta )
A32: 1862 | B32: 07 - JULHO | C32: 13389 | D32: 45860 | E32: 45869 | F32: MENSAL | G32: 0.01 | H32: 0.009 | I32: FILIAL BH2 | J32: 45860 | K32: PARAMETRIZAR CAMPANHA - ID 13389 | L32: BANCO DIGIO - TODA A PRODUÇÃO
A33: 1863 | B33: 07 - JULHO | C33: 14482 | D33: 45839 | E33: 45869 | F33: MENSAL | G33: 0.01 | H33: 0.7 | I33: FILIAL SP | J33: 45860 | K33: Re: BONUS SUB ZERO DAYCOVAL IEV - 14482 | L33: BANCO DAYCOVAL - 70% DO PERCENTUAL DE BÔNUS QUE RECEBEMOS
A34: 1864 | B34: 07 - JULHO | C34: 6799 | D34: 45859 | E34: 45869 | F34: MENSAL | G34: 0.01 | H34: 0.0025 | I34: FILIAL SP | J34: 45860 | K34: PARAMETRIZAR CAMPANHA - ID 6799 - MERCANTIL - FGTS | L34: BANCO MERCANTIL - FGTS
A35: 1865 | B35: 07 - JULHO | C35: 14186 | D35: 45859 | E35: 45869 | F35: MENSAL | G35: 50000 | H35: 0.005 | I35: FILIAL LONDRINA | J35: 45860 | K35: PARAMETRIZAR CAMPANHA - BANCO DIGIO - ID 14186 | L35: BANCO DIGIO - TODA A PRODUÇÃO
A36: 1866 | B36: 07 - JULHO | C36: 17111 | D36: 45855 | E36: 45869 | F36: MENSAL | G36: 300000 | H36: 0.003 | I36: FILIAL SALVADOR | J36: 45856 | K36: PARAMETRIZAR COMPANHA - ID: 17111 - REF: JULHO | L36: BANCO OLE - TODA A PRODUÇÃO
A37: 1867 | B37: 07 - JULHO | C37: 4353 | D37: 45855 | E37: 45869 | F37: MENSAL | G37: 0.01 | H37: 0.34 | I37: FILIAL SP | J37: 45856 | K37: PARAMETRIZAR CAMPANHA - ID 4353 - BANCO DAYCOVAL | L37: BANCO DAYCOVAL - 34% DO PERCENTUAL DE BÔNUS QUE RECEBEMOS - EXCETO TABELAS ABAIXO : DAYCOVAL - GOVERNO DE PERNAMBUCO - DAYCOVAL - GOVERNO DE PERNAMBUCO - GOV PE 1 (991780) DAYCOVAL - GOVERNO DE PERNAMBUCO - DAYCOVAL - GOVERNO DE PERNAMBUCO - GOV PE 2 (991781) DAYCOVAL - GOVERNO DE PERNAMBUCO - DAYCOVAL - GOVERNO DE PERNAMBUCO - GOV PE 3 (991782)- No prazo de 120
A38: 1868 | B38: 07 - JULHO | C38: 16363 | D38: 45839 | E38: 45855 | F38: MENSAL | G38: 0.01 | H38: 0.005 | I38: FILIAL RECIFE | J38: 45856 | K38: CAMPANHA MES JULHO I BANCO DIGIO I COD 16363 | L38: BONUS SOBRE A PRODUÇÃO BANCO DIGIO- TODOS OS PRODUTOS E PRAZO NAS TABELAS QUE INCIDE O BÔNUS
A39: 1869 | B39: 07 - JULHO | C39: 5736 / 17484 | D39: 45810 | E39: 45869 | F39: MENSAL | G39: 600000 | H39: 0.003 | I39: FILIAL RECIFE | J39: 45856 | K39: PARAMETRIZAR CAMPANHA I COD 5736 / 17484 | L39: TODAS AS TABELAS E PRODUTOS P/ ATINGIMENTO DA META. DESCONSIDERAR PORT, VIP, E GRUPO 001 P/ CALCULO DO BÔNUS.
A40: 1870 | B40: 07 - JULHO | C40: 13336 | D40: 45839 | E40: 45869 | F40: MENSAL | G40: 0.01 | H40: 0.0025 | I40: FILIAL LONDRINA | J40: 45846 | K40: PARAMETRIZAR CAMPANHA - ID 13336 | L40: bônus sobre toda a produção, desconsiderando as tabelas VIP
A41: 1871 | B41: 07 - JULHO | C41: 13669 | D41: 45839 | E41: 45869 | F41: MENSAL | G41: 0.01 | H41: 0.003 | I41: FILIAL GOIANIA | J41: 45855 | K41: Re: Campanha Facta Sub - COD WEBSUB: 13669 -SUB - LIMA E BISPO SOLUCOES E DESENVOLVI - BONUS 0,30% - 07 - 2025 | L41: BANCO FACTA - CONFORME REGULAMENTO
A42: 1872 | B42: 07 - JULHO | C42: 9207-16893-15896-15942 | D42: 45839 | E42: 45869 | F42: MENSAL | G42: 0.01 | H42: 0.005 | I42: FILIAL PRESIDENTE PRUDENTE | J42: 45855 | K42: Re: CAMPANHA - BONUS BANCO FACTA - 07/2025 - ARKAD | L42: BANCO FACTA - CONFORME REGULAMENTO
A43: 1873 | B43: 07 - JULHO | C43: 9207-16893-15896-15942 | D43: 45839 | E43: 45869 | F43: MENSAL | G43: 1000 | H43: 0.01 | I43: FILIAL BH2 | J43: 45855 | K43: Re: CAMPANHA - BONUS BANCO MEU CREDBANK - 07/2025 - ARKAD | L43: MEU CREDBAK-FGTS-TODA A PRODUÇÃO
A44: 1874 | B44: 07 - JULHO | C44: 16238 | D44: 45839 | E44: 45869 | F44: MENSAL | G44: 0.01 | H44: 0.015 | I44: FILIAL BH2 | J44: 45855 | K44: Re: CAMPANHA - BONUS BANCO MASTER - 07/2025 - 16238 - SUB - LC NEGÓCIOS LTDA | L44: MASTER-TODA A PRODUÇÃO EXCETO FGTS E INSS
A45: 1875 | B45: 07 - JULHO | C45: 15692 | D45: 45839 | E45: 45869 | F45: MENSAL | G45: 0.01 | H45: 0.007 | I45: FILIAL BH2 | J45: 45855 | K45: Re: Campanha Sub - BANCO DAYCOVAL - WEBSUB: 15692 - SUB - ABM ASSESSORIA E PROCESSAMENTO DE - CREDGOL - 07-2025 | L45: BANCO DAYCOVAL - TODA A PRODUÇÃO
A46: 1876 | B46: 07 - JULHO | C46: 14291 | D46: 45839 | E46: 45869 | F46: MENSAL | G46: 0.01 | H46: 0.005 | I46: FILIAL PRESIDENTE PRUDENTE | J46: 45855 | K46: Campanha Facta Sub - COD WEBSUB: 14291 - SOUZA & BATALINI SOCIEDADE LTDA - TEODORO SAMPAIO - SP - 07 2025 | L46: BANCO FACTA - CONFORME REGULAMENTO
A47: 1877 | B47: 07 - JULHO | C47: 17636 | D47: 45839 | E47: 45869 | F47: MENSAL | G47: 0.01 | H47: 0.007 | I47: FILIAL PRESIDENTE PRUDENTE | J47: 45855 | K47: Campanha Facta Sub - COD WEBSUB: 17636 -SUB - ANDRESSA PATRICIA KETELHUT JORDAO - BONUS 0,70% - | L47: BANCO FACTA - CONFORME REGULAMENTO
A48: 1878 | B48: 07 - JULHO | C48: 13128 | D48: 45839 | E48: 45869 | F48: MENSAL | G48: 0.01 | H48: 0.005 | I48: FILIAL PRESIDENTE PRUDENTE | J48: 45855 | K48: Campanha Facta Sub - COD WEBSUB: 13128 - SUB - DANIELLE LIMA BEVENUTO 32674022809 - ANDRADINA - SP - 07 - 2025 | L48: BANCO FACTA - CONFORME REGULAMENTO
A49: 1879 | B49: 07 - JULHO | C49: 14511 | D49: 45839 | E49: 45869 | F49: MENSAL | G49: 0.01 | H49: 0.007 | I49: FILIAL PRESIDENTE PRUDENTE | J49: 45855 | K49: Campanha Facta Sub - COD WEBSUB: 14511 - SUB - LEROY LUIZ ARAUJO NOGUEIRA MACARIO - ANDRADINA - SP - JULHO - 2025 | L49: BANCO FACTA - CONFORME REGULAMENTO
A50: 1880 | B50: 07 - JULHO | C50: 11301 | D50: 45839 | E50: 45869 | F50: MENSAL | G50: 0.01 | H50: 0.003 | I50: FILIAL PRESIDENTE PRUDENTE | J50: 45855 | K50: Campanha Facta Sub - COD WEBSUB: 11301 - LUIZ ANTONIO MAIA LTDA - OSVALDO CRUZ - SP - 07 - 2025 | L50: BANCO FACTA - CONFORME REGULAMENTO
A51: 1881 | B51: 07 - JULHO | C51: 17192 | D51: 45839 | E51: 45869 | F51: MENSAL | G51: 0.01 | H51: 0.003 | I51: FILIAL PRESIDENTE PRUDENTE | J51: 45855 | K51: Campanha Facta Sub - COD WEBSUB: 17192 - SUB - SUB RECEBAMAIS SOLUCOES EM CREDITO LTDA - BARRETOS - SP - JULHO - 2025 | L51: BANCO FACTA - CONFORME REGULAMENTO
A52: 1882 | B52: 07 - JULHO | C52: 7274 / 17461 | D52: 45839 | E52: 45869 | F52: MENSAL | G52: 300000 | H52: 0.005 | I52: FILIAL PRESIDENTE PRUDENTE | J52: 45855 | K52: PARAMETRIZAR CAMPANHA - 7274/74161 - REF JULHO | L52: PRODUCAO TOTAL : BANCOS BMG( exceto : cartão / cartão beneficio,siape/ inss,todos os prazos) , PRESENÇA BANK e FACTA ( Conforme parametro do banco )
A53: 1883 | B53: 07 - JULHO | C53: 6905 | D53: 45839 | E53: 45869 | F53: MENSAL | G53: 0.01 | H53: 0.0123 | I53: FILIAL NATAL | J53: 45855 | K53: CAMPANHA MES JULHO I BANCO MASTER I COD 6905 | L53: MASTER- M FACIL E CREDCESTA, prefeitura de UBERABA, IPSERV E CODAU-TODOS OS PRAZOS
A54: 1884 | B54: 07 - JULHO | C54: 6846 | D54: 45839 | E54: 45869 | F54: MENSAL | G54: 0.01 | H54: 0.01 | I54: FILIAL UBERLANDIA | J54: 45855 | K54: CAMPANHA MES JULHO I COD 6846 | L54: MEU CREDBANK-TODA PRODUÇAO DE FGTS
A55: 1885 | B55: 07 - JULHO | C55: 6846 | D55: 45839 | E55: 45869 | F55: MENSAL | G55: 0.01 | H55: 0.005 | I55: FILIAL UBERLANDIA | J55: 45855 | K55: CAMPANHA MES JULHO I COD 6846 | L55: MEU CREDBANK-TODA A PRODUÇÃO INSS, EXCETO : MEU CREDBANK - INSS - MEU CREDBANK - INSS - FP - NORMAL - TX 1,85 MEU CREDBANK - INSS - MEU CREDBANK - INSS - FP - SEGURO - TX 1,85
A56: 1886 | B56: 07 - JULHO | C56: 15908 | D56: 45839 | E56: 45868 | F56: MENSAL | G56: 1000 | H56: 0.0075 | I56: FILIAL UBERLANDIA | J56: 45855 | K56: CAMPANHA MES JULHO I COD 15908 | L56: BANCO FACTA - CONFORME REGULAMENTO
A57: 1887 | B57: 07 - JULHO | C57: 15908 | D57: 45839 | E57: 45868 | F57: MENSAL | G57: 1000 | H57: 0.008 | I57: FILIAL RIBEIRAO PRETO | J57: 45855 | K57: CAMPANHA MES JULHO I COD 15908 | L57: SOBRE TODA PRODUÇÃO VCTEX
A58: 1888 | B58: 07 - JULHO | C58: 13113 | D58: 45839 | E58: 45858 | F58: MENSAL | G58: 0.01 | H58: 0.01 | I58: FILIAL RIBEIRAO PRETO | J58: 45855 | K58: Fwd: 13113 - CAMPANHA 07/2025 | L58: MEU CREDBANK-TODA PRODUÇAO DE FGTS
A59: 1889 | B59: 07 - JULHO | C59: 13113 | D59: 45839 | E59: 45858 | F59: MENSAL | G59: 0.01 | H59: 0.005 | I59: FILIAL RIBEIRAO PRETO | J59: 45855 | K59: Fwd: 13113 - CAMPANHA 07/2025 | L59: MEU CREDBANK-TODA A PRODUÇÃO INSS, EXCETO : MEU CREDBANK - INSS - MEU CREDBANK - INSS - FP - NORMAL - TX 1,85 MEU CREDBANK - INSS - MEU CREDBANK - INSS - FP - SEGURO - TX 1,85
A60: 1890 | B60: 07 - JULHO | C60: 13113 | D60: 45859 | E60: 45869 | F60: MENSAL | G60: 0.01 | H60: 0.012 | I60: FILIAL RIBEIRAO PRETO | J60: 45855 | K60: Fwd: 13113 - CAMPANHA 07/2025 | L60: MEU CREDBANK-TODA PRODUÇAO DE FGTS
A61: 1891 | B61: 07 - JULHO | C61: 13113 | D61: 45859 | E61: 45869 | F61: MENSAL | G61: 0.01 | H61: 0.007 | I61: FILIAL RIBEIRAO PRETO | J61: 45855 | K61: Fwd: 13113 - CAMPANHA 07/2025 | L61: MEU CREDBANK-TODA A PRODUÇÃO INSS, EXCETO : MEU CREDBANK - INSS - MEU CREDBANK - INSS - FP - NORMAL - TX 1,85 MEU CREDBANK - INSS - MEU CREDBANK - INSS - FP - SEGURO - TX 1,85
A62: 1892 | B62: 07 - JULHO | C62: 13910-8810 | D62: 45839 | E62: 45869 | F62: MENSAL | G62: 0.01 | H62: 0.0025 | I62: FILIAL RIBEIRAO PRETO | J62: 45854 | K62: CAMPANHA MES JULHO I BANCO FACTA I COD 13910/8810 | L62: BANCO FACTA - INSS / FGTS - CONFORME REGULAMENTO
A63: 1893 | B63: 07 - JULHO | C63: 13368 | D63: 45839 | E63: 45869 | F63: MENSAL | G63: 0.01 | H63: 0.015 | I63: FILIAL SP | J63: 45855 | K63: CAMPANHA MES JULHO I COD 13368 | L63: MEU CREDBANK-TODA PRODUÇAO DE FGTS
A64: 1894 | B64: 07 - JULHO | C64: 13368 | D64: 45839 | E64: 45869 | F64: MENSAL | G64: 0.01 | H64: 0.005 | I64: FILIAL GOIANIA | J64: 45855 | K64: CAMPANHA MES JULHO I COD 13368 | L64: MEU CREDBANK-INSS TODA A PRODUÇÃO, EXCETO : MEU CREDBANK - INSS - MEU CREDBANK - INSS - FP - NORMAL - TX 1,85 MEU CREDBANK - INSS - MEU CREDBANK - INSS - FP - SEGURO - TX 1,85
A65: 1895 | B65: 07 - JULHO | C65: 13368 | D65: 45839 | E65: 45869 | F65: MENSAL | G65: 0.01 | H65: 0.015 | I65: FILIAL GOIANIA | J65: 45855 | K65: CAMPANHA MES JULHO I COD 13368 | L65: MASTER TODA A PRODUÇÃO
A66: 1896 | B66: 07 - JULHO | C66: 13368 | D66: 45839 | E66: 45869 | F66: MENSAL | G66: 0.01 | H66: 0.005 | I66: FILIAL GOIANIA | J66: 45855 | K66: CAMPANHA MES JULHO I COD 13368 | L66: BANCO FACTA - CONFORME REGULAMENTO
A67: 1897 | B67: 07 - JULHO | C67: 15503 | D67: 45839 | E67: 45869 | F67: MENSAL | G67: 0.01 | H67: 0.0075 | I67: FILIAL GOIANIA | J67: 45854 | K67: PARAMETRIZAR CAMPANHA - ID: 15503 - REF: JULHO 2025 | L67: PRESENÇA INSS
A68: 1898 | B68: 07 - JULHO | C68: 15932 | D68: 45839 | E68: 45869 | F68: MENSAL | G68: 0.01 | H68: 0.0075 | I68: FILIAL GOIANIA | J68: 45847 | K68: PARAMETRIZAR AS CAMPANHA - ID 12633 / 5804 / 15932 | L68: PRESENÇA BANK- TODA A PRODUÇÃO NAS TABELAS QUE RECEBEMOS BONIFICACOES
A69: 1899 | B69: 07 - JULHO | C69: 13007 | D69: 45839 | E69: 45869 | F69: MENSAL | G69: 0.01 | H69: 0.004 | I69: FILIAL JOAO PESSOA | J69: 45855 | K69: Re: Campanha Sub - COD WEBSUB: 13007 : JULIENE MONREAL DOS SANTOS SORROCHE - 41.659.209/0001-49 - BONUS 0,40% - JULHO - 2025 | L69: BANCO FACTA - CONFORME REGULAMENTO
A70: 1900 | B70: 07 - JULHO | C70: 15008 | D70: 45839 | E70: 45869 | F70: MENSAL | G70: 200000 | H70: 0.0075 | I70: FILIAL PRESIDENTE PRUDENTE | J70: 45855 | K70: Re: :: CAMPANHA FACTA - MEDCRED - 07.2025 :: | L70: BANCO FACTA - INSS / FGTS - CONFORME REGULAMENTO
A71: 1901 | B71: 07 - JULHO | C71: 16578 | D71: 45839 | E71: 45869 | F71: MENSAL | G71: 0.01 | H71: 0.003 | I71: FILIAL SP | J71: 45855 | K71: Re: 16578 - GABRIELA FONSECA | BONUS JULHO | PARAMETRIZAÇÃO | L71: BANCO FACTA - CONFORME REGULAMENTO
A72: 1902 | B72: 07 - JULHO | C72: 15421 | D72: 45839 | E72: 45869 | F72: MENSAL | G72: 0.01 | H72: 0.003 | I72: FILIAL PRESIDENTE PRUDENTE | J72: 45855 | K72: Re: 15421 - MIKELY SUB FACTA | BONUS JULHO | PARAMETRIZAÇÃO | L72: BANCO FACTA - CONFORME REGULAMENTO
A73: 1903 | B73: 07 - JULHO | C73: 14011 | D73: 45839 | E73: 45869 | F73: MENSAL | G73: 450000 | H73: 0.005 | I73: FILIAL PRESIDENTE PRUDENTE | J73: 45855 | K73: Re: 14011 - SUB MIX SOLUÇÕES | BONUS | VCTEX E FACTA | JULHO | L73: VCTEX-FGTS
A74: 1904 | B74: 07 - JULHO | C74: 14011 | D74: 45839 | E74: 45869 | F74: MENSAL | G74: 0.01 | H74: 0.005 | I74: FILIAL PRESIDENTE PRUDENTE | J74: 45855 | K74: Re: 14011 - SUB MIX SOLUÇÕES | BONUS | VCTEX E FACTA | JULHO | L74: BANCO FACTA - CONFORME REGULAMENTO
... A78: 1908 | B78: 07 - JULHO | C78: 15564 | D78: 45839 | E78: 45869 | F78: MENSAL | G78: 0.01 | H78: 0.003 | I78: FILIAL PRESIDENTE PRUDENTE | J78: 45855 | K78: Re: 15564 - FERNANDA SUB FACTA | BONUS DE JULHO | PARAMETRIZAÇÃO | L78: BANCO FACTA - CONFORME REGULAMENTO
A79: 1909 | B79: 07 - JULHO | C79: 16102 | D79: 45839 | E79: 45869 | F79: MENSAL | G79: 1000 | H79: 0.02 | I79: FILIAL PRESIDENTE PRUDENTE | J79: 45855 | K79: PARAMETRIZAR CAMPANHA - BANCO MASTER - ID 16102 | L79: BANCO MASTER TODOS OS CONVENIOS, PRAZOS E TABELAS.
A80: 1910 | B80: 07 - JULHO | C80: 16085 | D80: 45853 | E80: 45869 | F80: MENSAL | G80: 0.01 | H80: 0.001 | I80: FILIAL RECIFE | J80: 45855 | K80: CAMPANHA MES JULHO I BANCO FACTA I COD 16085 | L80: BANCO FACTA - CONFORME REGULAMENTO
A81: 1911 | B81: 07 - JULHO | C81: 14105 | D81: 45839 | E81: 45869 | F81: MENSAL | G81: 0.01 | H81: 0.02 | I81: FILIAL GOIANIA | J81: 45855 | K81: CAMPANHA MES JULHO I COD 14105 | L81: PAN-TODA PRODUÇÃO DE NOVO E REFIN , EXCETO SIAPE, INSS, GOV DO PARANA, E FGTS
A82: 1912 | B82: 07 - JULHO | C82: 14105 | D82: 45839 | E82: 45869 | F82: MENSAL | G82: 0.01 | H82: 0.002 | I82: FILIAL GOIANIA | J82: 45855 | K82: CAMPANHA MES JULHO I COD 14105 | L82: QUERO + SOMENTE SOBRE CONVENIO SIAPE
A83: 1913 | B83: 07 - JULHO | C83: 17859 / 17918 | D83: 45839 | E83: 45869 | F83: MENSAL | G83: 0.01 | H83: 0.006 | I83: FILIAL GOIANIA | J83: 45855 | K83: CAMPANHA MES JULHO I BANCO FACTA I COD 17859 / 17918 | L83: BANCO FACTA - CONFORME REGULAMENTO
A84: 1914 | B84: 07 - JULHO | C84: 14003 | D84: 45839 | E84: 45869 | F84: MENSAL | G84: 0.01 | H84: 0.005 | I84: FILIAL SP CAPITAL | J84: 45855 | K84: CAMPANHA MES JULHO I BANCO FACTA I COD 14003 | L84: BANCO FACTA - CONFORME REGULAMENTO
A85: 1915 | B85: 07 - JULHO | C85: 13560-13750 | D85: 45839 | E85: 45869 | F85: MENSAL | G85: 200000 | H85: 0.0075 | I85: FILIAL SP | J85: 45854 | K85: CAMPANHA MES JULHO I BANCO FACTA I COD 13560 / 13750 | L85: BANCO FACTA - CONFORME REGULAMENTO
A86: 1916 | B86: 07 - JULHO | C86: 14054 | D86: 45854 | E86: 45869 | F86: MENSAL | G86: 50000 | H86: 0.005 | I86: FILIAL SP | J86: 45854 | K86: PARAMETRIZAR CAMPANHA - BANCO MASTER - ID 14054 | L86: MASTER-TODOS OS CONVÊNIOS E PRODUTOS MFACIL, CREDCESTA, REFIN CREDCESTA.
A87: 1917 | B87: 07 - JULHO | C87: 16754 | D87: 45839 | E87: 45868 | F87: MENSAL | G87: 0.01 | H87: 0.01 | I87: FILIAL SALVADOR | J87: 45854 | K87: PARAMETRIZAR CAMPANHA - ID 16754 - BANCO AMIGOZ | L87: AMIGOZ TODA A PRODUÇÃO EXCETO Prefeitura de Juiz de Fora, TJMG e Prefeitura de Recife.)
A88: 1918 | B88: 07 - JULHO | C88: 11820 | D88: 45839 | E88: 45869 | F88: MENSAL | G88: 0.01 | H88: 0.002 | I88: FILIAL CAMPO GRANDE | J88: 45854 | K88: Re: Campanha C6 PARC 11820 LILIANE MARIA | L88: 1,799% a 1,750% calcular a média, das taxas de refin de port
A89: 1919 | B89: 07 - JULHO | C89: 11820 | D89: 45839 | E89: 45869 | F89: MENSAL | G89: 0.01 | H89: 0.005 | I89: FILIAL BH2 | J89: 45854 | K89: Re: Campanha C6 PARC 11820 LILIANE MARIA | L89: 1,80% a 1,829% calcular a média, das taxas de refin de port
A90: 1920 | B90: 07 - JULHO | C90: 11820 | D90: 45839 | E90: 45869 | F90: MENSAL | G90: 0.01 | H90: 0.015 | I90: FILIAL BH2 | J90: 45854 | K90: Re: Campanha C6 PARC 11820 LILIANE MARIA | L90: 1,83% a 1,85% calcular a média, das taxas de refin de port
A91: 1921 | B91: 07 - JULHO | C91: 14495 | D91: 45839 | E91: 45869 | F91: MENSAL | G91: 0.01 | H91: 0.005 | I91: FILIAL BH2 | J91: 45854 | K91: CAMPANHA MES JULHO I BANCO FACTA I COD 14194/14495 | L91: BANCO FACTA - CONFORME REGULAMENTO
A92: 1922 | B92: 07 - JULHO | C92: 14194 | D92: 45839 | E92: 45869 | F92: MENSAL | G92: 0.01 | H92: 0.005 | I92: FILIAL SP | J92: 45854 | K92: CAMPANHA MES JULHO I BANCO FACTA I COD 14194/14495 | L92: BANCO FACTA - CONFORME REGULAMENTO
A93: 1923 | B93: 07 - JULHO | C93: 17683 | D93: 45839 | E93: 45869 | F93: MENSAL | G93: 0.01 | H93: 0.0065 | I93: FILIAL SP | J93: 45854 | K93: CAMPANHA MES JULHO I BANCO FACTA I COD 17683 | L93: BANCO FACTA - INSS / FGTS - CONFORME REGULAMENTO
A94: 1924 | B94: 07 - JULHO | C94: 9248 | D94: 45839 | E94: 45869 | F94: MENSAL | G94: 0.01 | H94: 0.005 | I94: FILIAL SP | J94: 45854 | K94: CAMPANHA MES JULHO I BANCO QUERO + CREDITO I COD 9248 | L94: QUERO MAIS INSS E SIAPE - CARTÃO BENEFÍCIO
A95: 1925 | B95: 07 - JULHO | C95: 9248 | D95: 45839 | E95: 45869 | F95: MENSAL | G95: 0.01 | H95: 0.0065 | I95: FILIAL SP | J95: 45854 | K95: CAMPANHA MES JULHO I BANCO FACTA I COD 9248 | L95: BANCO FACTA - INSS / FGTS - CONFORME REGULAMENTO
A96: 1926 | B96: 07 - JULHO | C96: 3566 | D96: 45839 | E96: 45869 | F96: MENSAL | G96: 0.01 | H96: 0.005 | I96: FILIAL SP | J96: 45854 | K96: PARAMETRIZAR CAMPANHA - 3566 - BANCO QUERO MAIS - REF: JULHO 2025 | L96: QUERO MAIS INSS E SIAPE - CARTÃO BENEFÍCIO
A97: 1927 | B97: 07 - JULHO | C97: 3566 | D97: 45839 | E97: 45869 | F97: MENSAL | G97: 500000 | H97: 0.007 | I97: FILIAL SP | J97: 45854 | K97: PARAMETRIZAR CAMPANHA - ID: 3566 - REF: JUNHO 2025 | L97: BANCO FACTA - INSS / FGTS - CONFORME REGULAMENTO
A98: 1928 | B98: 07 - JULHO | C98: 14910 | D98: 45839 | E98: 45869 | F98: MENSAL | G98: 200000 | H98: 0.005 | I98: FILIAL SP | J98: 45854 | K98: PARAMETRIZAR CAMPANHA - ID: 14910 - REF: JULHO 2025 | L98: BANCO FACTA - INSS - CONFORME REGULAMENTO
A99: 1929 | B99: 07 - JULHO | C99: 7460 / 12006 | D99: 45839 | E99: 45869 | F99: MENSAL | G99: 800000 | H99: 0.001 | I99: FILIAL SP | J99: 45854 | K99: PARAMETRIZAR CAMPANHA - 7460 / 12006 | L99: CONSIDERAR TODA A PRODUÇAO PARA APURAÇAO DA META E PAGAMENTO DA BONIFICAÇÃO EM AMBOS OS CODIGOS 7460 / 12006
A100: 1930 | B100: 07 - JULHO | C100: 2649 / 7018 | D100: 45839 | E100: 45869 | F100: MENSAL | G100: 0.01 | H100: 0.001 | I100: FILIAL UBERLANDIA | J100: 45854 | K100: PARAMETRIZAR CAMPANHA - ID 2649 / ID 7018 | L100: TODA A PRODUÇÃO -EXCETO TABELAS VIP
A101: 1931 | B101: 07 - JULHO | C101: 16418 | D101: 45853 | E101: 45869 | F101: MENSAL | G101: 1000 | H101: 0.035 | I101: FILIAL UBERLANDIA | J101: 45854 | K101: CAMPANHA MES DE JULHO I BANCO AMIGOZ I COD 16418 | L101: Banco Amigoz – Todos os Produtos – Todos os Prazos – Todos os convênios – Todas as Tabelas
A102: 1932 | B102: 07 - JULHO | C102: 3446 | D102: 45839 | E102: 45869 | F102: MENSAL | G102: 0.01 | H102: 0.005 | I102: FILIAL JOAO PESSOA | J102: 45854 | K102: PARAMETRIZAÇÃO DE CAMPANHA - BANCO MERCANTIL - ID 3446 | L102: MERCANTIL-cartão RMC e RCC (CBMG / IPSEMG / IPSM / PMMG / SEPLAG)
A103: 1933 | B103: 07 - JULHO | C103: 15463/5407 | D103: 45839 | E103: 45869 | F103: MENSAL | G103: 300000 | H103: 0.0015 | I103: FILIAL BH1 | J103: 45854 | K103: CAMPANHA MES JULHO I COD 15463/5407 | L103: TODA A PRODUÇÃO -
...

Sheet JUN - 25
A1: Nº | B1: FECHAMENTO | C1: COD | D1: INICIO | E1: FIM | F1: PERÍODO FECHAMENTO | G1: META | H1: PRÊMIO GANHO | I1: FILIAL | J1: SOLICITAÇÃO (E-MAIL) | K1: ASSUNTO (E-MAIL) | L1: PARÂMETRO
A2: 1490 | B2: 06 - JUNHO | C2: 726 / 13552 | D2: 45809 | E2: 45838 | F2: MENSAL | G2: 0.01 | H2: 0.001 | I2: FILIAL BH1 | J2: 45580 | K2: PARAMETRIZAR CAMPANHA - 726 E 13552 SUB | L2: TODOS OS BANCOS E TODOS OS PRODUTOS.-CREDITO 13522
A3: 1491 | B3: 06 - JUNHO | C3: 7460 / 12006 | D3: 45809 | E3: 45838 | F3: MENSAL | G3: 800000 | H3: 0.001 | I3: FILIAL UBERLANDIA | J3: 45730 | K3: PARAMETRIZAR CAMPANHA - 7460 / 12006 | L3: PRODUÇÃO TOTAL - PAGAMENTO DA BONIFICAÇÃO EM AMBOS OS CODIGOS 7460 / 12006
A4: 1492 | B4: 06 - JUNHO | C4: 3184-12430 | D4: 45809 | E4: 45838 | F4: MENSAL | G4: 300000 | H4: 0.002 | I4: FILIAL BH2 | J4: 45721 | K4: PARAMETRIZAR CAMPANHA - ID 3184/12430 | L4: PRODUCAO TOTAL PARA ATINGIR A META E CONTABILIZAR-META DESCONSIDERAR BMG E C6 ( INSS /NOVO )
A5: 1493 | B5: 06 - JUNHO | C5: 4310 / 13955 | D5: 45809 | E5: 45838 | F5: MENSAL | G5: 300000 | H5: 0.004 | I5: FILIAL BH2 | J5: 45728 | K5: PARAMETRIZAR CAMPNAHA - BANCO FACTA - ID 4310 /13955 | L5: IREMOS CONSIDERAR TODA A PRODUÇÃO / EXCETO AS TABELAS QUE POSSUEM VIP-credito 14603
A6: 1494 | B6: 06 - JUNHO | C6: 7934 | D6: 45809 | E6: 45838 | F6: MENSAL | G6: 1000 | H6: 0.002 | I6: FILIAL JOAO PESSOA | J6: 45734 | K6: PARAMETRIZAR CAMPANHA - ID 7934 - TODA A PRODUÇÃO | L6: TODO A PRODUÇÃO
A7: 1495 | B7: 06 - JUNHO | C7: 1729/8125 | D7: 45809 | E7: 45838 | F7: MENSAL | G7: 600000 | H7: 0.005 | I7: FILIAL BH2 | J7: 45737 | K7: PARAMETRIZAR CAMPANHA - ID: 1729 / 8125 - REF: MARÇO 2025 | L7: PRODUCAO TOTAL -CREDITO 1729
A8: 1496 | B8: 06 - JUNHO | C8: 16988 | D8: 45809 | E8: 45838 | F8: MENSAL | G8: 0.01 | H8: 0.0075 | I8: FILIAL SP CAPITAL | J8: 45754 | K8: Re: CAMPANHA MES ABRIL 2025 - FACTA - GM PROMOTORA 16988 (ERICK VIEIRA) | L8: BANCO FACTA - CONFORME REGULAMENTO
A9: 1497 | B9: 06 - JUNHO | C9: 2911-11402 | D9: 45809 | E9: 45838 | F9: MENSAL | G9: 0.01 | H9: 0.002 | I9: FILIAL BH1 | J9: 45754 | K9: PARAMETRIZAR CAMPANHA - 2911 E 11402 - ABRIL 2025 | L9: TODOS BANCOS / INSS-SIAPE/novo / port/refin de port /cartao rmc /cartao benefcio / 84x E 96x TODAS AS TABELASCREDITO 2911
A10: 1498 | B10: 06 - JUNHO | C10: 2911-11402 | D10: 45809 | E10: 45838 | F10: MENSAL | G10: 0.01 | H10: 0.002 | I10: FILIAL BH1 | L10: BANCO FACTA - INSS - CONFORME REGULAMENTO - credito 2911
A11: 1499 | B11: 06 - JUNHO | C11: 3209-13857 | D11: 45809 | E11: 45838 | F11: MENSAL | G11: 300000 | H11: 0.002 | I11: FILIAL BH2 | J11: 45763 | K11: PARAMETRIZAR CAMPANHA - ID 3209/13857 | L11: PRODUCAO TOTAL Exceto (INSS-NOVO-BMG)-CREDITO 3209
A12: 1500 | B12: 06 - JUNHO | C12: 15001 / 6935 | D12: 45809 | E12: 45838 | F12: MENSAL | G12: 200000 | H12: 0.005 | I12: FILIAL UBERLANDIA | J12: 45762 | K12: PARAMETRIZAR CAMPANHA - 15001 | 6935 | L12: BANCO FACTA - CONFORME REGULAMENTO - CREDITO 6935
A13: 1501 | B13: 06 - JUNHO | C13: 15001 / 6935 | D13: 45809 | E13: 45838 | F13: MENSAL | G13: 200000 | H13: 0.005 | I13: FILIAL UBERLANDIA | J13: 45762 | K13: PARAMETRIZAR CAMPANHA - 15001 | 6935 | L13: TODA A PRODUÇAO NO DIGIO .-CREDITO 6935
A14: 1502 | B14: 06 - JUNHO | C14: 15001 / 6935 | D14: 45809 | E14: 45838 | F14: MENSAL | G14: 150000 | H14: 0.0025 | I14: FILIAL UBERLANDIA | J14: 45762 | K14: PARAMETRIZAR CAMPANHA - 15001 | 6935 | L14: TODA A PRODUÇAO NO MEU CREDBANK.-CREDITO 6935
A15: 1503 | B15: 06 - JUNHO | C15: 16403 | D15: 45809 | E15: 45838 | F15: MENSAL | G15: 150000 | H15: 0.0025 | I15: FILIAL UBERLANDIA | J15: 45763 | K15: PARAMETRIZAR CAMPANHA - ID 16403/17375 | L15: PRODUCAO TOTAL DIGIO (INSS)
A16: 1504 | B16: 06 - JUNHO | C16: 16403 | D16: 45809 | E16: 45838 | F16: MENSAL | G16: 100000 | H16: 0.003 | I16: FILIAL UBERLANDIA | J16: 45763 | K16: PARAMETRIZAR CAMPANHA - ID 16403/17375 | L16: BANCO FACTA - CONFORME REGULAMENTO
A17: 1505 | B17: 06 - JUNHO | C17: 17375 | D17: 45809 | E17: 45838 | F17: MENSAL | G17: 40000 | H17: 0.005 | I17: FILIAL UBERLANDIA | J17: 45763 | K17: PARAMETRIZAR CAMPANHA - ID 16403/17375 | L17: PRODUÇÃO TOTAL DO BANCO VCTEX PARA APURAÇAO E ATINGIMENTO DA META.
A18: 1506 | B18: 06 - JUNHO | C18: 12340 | D18: 45809 | E18: 45838 | F18: MENSAL | G18: 300.000,00 / 500.000,00 | H18: 0.10% / 0,20% | I18: FILIAL UBERLANDIA | J18: 45763 | K18: PARAMETRIZAR CAMPANHA - ID 12340 | L18: PRODUCAO TOTAL PARA CONTABILIZAR-META PRODUCAO TOTAL DESCONSIDERANDO BANCO BMG
A19: 1507 | B19: 06 - JUNHO | C19: 3190 / 6950 / 7036 | D19: 45809 | E19: 45838 | F19: MENSAL | G19: 300.000,00 / 500.000,00 | H19: 0.10% / 0,20% | I19: FILIAL UBERLANDIA | J19: 45762 | K19: PARAMETRIZAR CAMPANHA - ID´s 3190 / 6950 / 7036 | L19: PRODUCAO TOTAL PARA CONTABILIZAR E META-BONIFICACAO EXCETO TABELAS VIP-ECREDITO 3190
A20: 1508 | B20: 06 - JUNHO | C20: 1427 | D20: 45809 | E20: 45838 | F20: MENSAL | G20: 0.01 | H20: 0.0045 | I20: FILIAL BH2 | J20: 45721 | K20: PARAMETRIZAR CAMPANHA - ID 1427 - BANCO FACTA | L20: BANCO FACTA - INSS - CONFORME REGULAMENTO
A21: 1509 | B21: 06 - JUNHO | C21: 16754 | D21: 45809 | E21: 45838 | F21: MENSAL | G21: 0.01 | H21: 0.01 | I21: FILIAL CAMPO GRANDE | J21: 45807 | K21: PARAMETRIZAR CAMPANHA - ID: 16754 | L21: AMIGOZ-PRODUCAO TOTAL -EXCETO Prefeitura de Juiz de Fora, TJMG e Prefeitura de Recife.)
A22: 1510 | B22: 06 - JUNHO | C22: 17711 | D22: 45809 | E22: 45838 | F22: MENSAL | G22: 0.01 | H22: 0.0075 | I22: FILIAL SP CAPITAL | J22: 45803 | K22: PARAMETRIZAR CAMPANHA l BANCO FACTA l CÓDIGO 17711 | L22: BANCO FACTA - CONFORME REGULAMENTO
A23: 1511 | B23: 06 - JUNHO | C23: 10473 | D23: 45809 | E23: 45838 | F23: MENSAL | G23: 300000 | H23: 0.004 | I23: FILIAL LONDRINA | J23: 45811 | K23: PARAMETRIZAÇAO CAMPANHA I BANCO C6 I COD 10473 - JUNHO | L23: C6 BANK - INSS - C6 BANK - INSS - DIGITAL WEB NOVO NORMAL (210180) - TAXA 1,85% - C/ Pacote C6 BANK - INSS - C6 BANK - INSS - DIGITAL WEB NOVO REPRESENTANTE LEGAL (210184) - TAXA 1,85% - C/ Pacote
A24: 1512 | B24: 06 - JUNHO | C24: 16572 | D24: 45809 | E24: 45838 | F24: MENSAL | G24: 0.01 | H24: 0.003 | I24: FILIAL RJ | J24: 45811 | K24: PARAMETRIZAÇAO CAMPANHA I BANCO MASTER I COD 16572 -JUNHO | L24: BANCO MASTER SOMENTE EMPRÉSTIMOS GOV RIO - TODOS OS PRAZOS
A25: 1513 | B25: 06 - JUNHO | C25: 17350 | D25: 45809 | E25: 45838 | F25: MENSAL | G25: 1000 | H25: 0.005 | I25: FILIAL FLORIANOPOLIS | J25: 45811 | K25: PARAMETRIZAR CAMPANHA - ID: 17350 - JUNHO 2025 | L25: BANCO FACTA - CONFORME REGULAMENTO
A26: 1514 | B26: 06 - JUNHO | C26: 16446 | D26: 45809 | E26: 45838 | F26: MENSAL | G26: 30000 | H26: 0.0026 | I26: FILIAL BELEM | J26: 45811 | K26: PARAMETRIZAÇÃO CAMPANHA I BANCO C6 I COD 16446 -JUNHO | L26: C6-INSS(PRODUCAO TOTAL ) PRAZO 84 E 96
A27: 1515 | B27: 06 - JUNHO | C27: 16446 | D27: 45809 | E27: 45838 | F27: MENSAL | G27: 30000 | H27: 0.018 | I27: FILIAL BELEM | J27: 45811 | K27: PARAMETRIZAÇÃO CAMPANHA I BANCO MASTER I COD 16446 -JUNHO | L27: TODOS MASTER OS PRODUTOS E PRAZOS
A28: 1516 | B28: 06 - JUNHO | C28: 17142 | D28: 45809 | E28: 45838 | F28: MENSAL | G28: 30000 | H28: 0.005 | I28: FILIAL BELEM | J28: 45811 | K28: PARAMETRIZAÇAO CAMPANHA I BANCO MASTER I COD 17142 -JUNHO | L28: MASTER-TODOS OS PRODUTOS E PRAZOS
A29: 1517 | B29: 06 - JUNHO | C29: 14363 | D29: 45809 | E29: 45838 | F29: MENSAL | G29: 1000 | H29: 0.015 | I29: FILIAL FLORIANOPOLIS | J29: 45807 | K29: PARAMETRIZAR CAMPANHA - ID: 14363 - REF: JUNHO 2025 | L29: QUERO MAIS -SIAPE CARTÃO CONSIGNADO E CARTÃO BENEFICIO
A30: 1518 | B30: 06 - JUNHO | C30: 6211 | D30: 45809 | E30: 45838 | F30: MENSAL | G30: 500000 | H30: 0.01 | I30: FILIAL VITORIA | K30: PARAMETRIZAR CAMPANHA - ID: 6211 - REF: JUNHO 2025 | L30: PRODUCAO TOTAL ATINGIR A META-BONIFICACAO: NOVO INSS (COM SEGURO) , TODOS OS PRAZOS,BANCO MEU CREDBANK.- FGTS TODOS OS PRAZOS ,BANCO MEU CREDBANK.
A31: 1519 | B31: 06 - JUNHO | C31: 17204 | D31: 45809 | E31: 45838 | F31: MENSAL | G31: 0.01 | H31: 0.0175 | I31: FILIAL JOAO PESSOA | J31: 45811 | K31: Fwd: PLANILHA SUB CAMPANHA - JUNHO - CHRISTIANE ARAUJO | L31: QUERO MAIS – PRODUÇÃO TOTAL
A32: 1520 | B32: 06 - JUNHO | C32: 15086 | D32: 45809 | E32: 45838 | F32: MENSAL | G32: 0.01 | H32: 0.005 | I32: FILIAL JOAO PESSOA | J32: 45811 | K32: Fwd: PLANILHA SUB CAMPANHA - JUNHO - CHRISTIANE ARAUJO | L32: BANCO FACTA - CONFORME REGULAMENTO
A33: 1521 | B33: 06 - JUNHO | C33: 15086 | D33: 45809 | E33: 45838 | F33: MENSAL | G33: 0.01 | H33: 0.005 | I33: FILIAL JOAO PESSOA | J33: 45811 | K33: Fwd: PLANILHA SUB CAMPANHA - JUNHO - CHRISTIANE ARAUJO | L33: C6 – TODOS OS CONVENIOS, NAS TABELAS ELEGIVEIS
A34: 1522 | B34: 06 - JUNHO | C34: 15086 | D34: 45809 | E34: 45838 | F34: MENSAL | G34: 0.01 | H34: 0.02 | I34: FILIAL JOAO PESSOA | J34: 45811 | K34: Fwd: PLANILHA SUB CAMPANHA - JUNHO - CHRISTIANE ARAUJO | L34: MEU CASH CARD – TODAS OS PRODUTOS E TABELAS
A35: 1523 | B35: 06 - JUNHO | C35: 14170 | D35: 45805 | E35: 45838 | F35: MENSAL | G35: 0.01 | H35: 0.009 | I35: FILIAL GOIANIA | J35: 45807 | K35: PARAMETRIZAR CAMPANHA - ID: 14170 | L35: AMIGOZ-PRODUCAO TOTAL
A36: 1524 | B36: 06 - JUNHO | C36: 15078 | D36: 45805 | E36: 45838 | F36: MENSAL | G36: 0.01 | H36: 0.009 | I36: FILIAL GOIANIA | J36: 45807 | K36: PARAMETRIZAR CAMPANHA - ID: 15078 | L36: PAGAREMOS O BONUS SOBRE A PRODUCAO O BANCO AMIGOZ
A37: 1525 | B37: 06 - JUNHO | C37: 3038 | D37: 45810 | E37: 45838 | F37: MENSAL | G37: 0.01 | H37: 0.002 | I37: FILIAL BH2 | J37: 45810 | K37: PARAMETRIZAR CAMPANHA - ID: 3038 - REF: JUNHO 2025 | L37: PAN - GRUPO MINAS (PMMG, SEPLAG. BOMBEIRO, IPSEMG, IPSM) - NOVO - REFIN
A38: 1526 | B38: 06 - JUNHO | C38: 12765 | D38: 45809 | E38: 45838 | F38: MENSAL | G38: 800000 | H38: 0.005 | I38: FILIAL VITORIA | J38: 45810 | K38: PARAMETRIZAR CAMPANHA - ID: 12765 - REF: JUNHO 2025 | L38: PRODUCAO TOTAL FACTA ATINGIR A META-BONIFICACAO : FACTA- NOVO-CARTÕES-FGTS-CLT .
A39: 1527 | B39: 06 - JUNHO | C39: 15087 | D39: 45809 | E39: 45817 | F39: MENSAL | G39: 30000 | H39: 0.005 | I39: FILIAL BELEM | J39: 45810 | K39: PARAMETRIZAR CAMPANHA - ID: 15087 - REF: JUNHO 2025 | L39: NOVO COM E SEM SEGURO \ PRESENÇA BANK \INSS\96 E 84 X
A40: 1528 | B40: 06 - JUNHO | C40: 15087 | D40: 45809 | E40: 45838 | F40: MENSAL | G40: 30000 | H40: 0.0025 | I40: FILIAL BELEM | J40: 45810 | K40: PARAMETRIZAR CAMPANHA - ID: 15087 | L40: REFIN DA PORT \ MEUCREDBANK\INSS\96 E 84 X
A41: 1529 | B41: 06 - JUNHO | C41: 15332 | D41: 45809 | E41: 45838 | F41: MENSAL | G41: 0.01 | H41: 0.01 | I41: FILIAL BH2 | J41: 45811 | K41: CADASTRAR CAMPANHA | JARVIS 15332 | BANCO MASTER | L41: BANCO MASTER / TODOS OS PRODUTOS E CONVENIOS EXCETO O INSS
A42: 1530 | B42: 06 - JUNHO | C42: 12633 | D42: 45809 | E42: 45838 | F42: MENSAL | G42: 0.01 | H42: 0.003 | I42: FILIAL JOAO PESSOA | J42: 45811 | K42: PARAMETRIZAR CAMPANHAS - GC CRISTIANE - REF: JUNHO 2025 | L42: BANCO FACTA - CONFORME REGULAMENTO
A43: 1531 | B43: 06 - JUNHO | C43: 5804 | D43: 45809 | E43: 45838 | F43: MENSAL | G43: 0.01 | H43: 0.005 | I43: FILIAL JOAO PESSOA | J43: 45811 | K43: PARAMETRIZAR CAMPANHAS - GC CRISTIANE - REF: JUNHO 2025 | L43: BANCO MEU CREDBANK – INSS APENAS TABELAS COM SEGURO
A44: 1532 | B44: 06 - JUNHO | C44: 15932 | D44: 45818 | E44: 45838 | F44: MENSAL | G44: 0.01 | H44: 0.0075 | I44: FILIAL JOAO PESSOA | J44: 45811 | K44: PARAMETRIZAR CAMPANHAS - GC CRISTIANE - REF: JUNHO 2025 | L44: PRESENÇA BANK- PRODUÇÃO TOTAL
A45: 1533 | B45: 06 - JUNHO | C45: 15932 | D45: 45809 | E45: 45838 | F45: MENSAL | G45: 0.01 | H45: 0.035 | I45: FILIAL JOAO PESSOA | J45: 45811 | K45: PARAMETRIZAR CAMPANHAS - GC CRISTIANE - REF: JUNHO 2025 | L45: AMIGOZ – PRODUÇÃO TOTAL
A46: 1534 | B46: 06 - JUNHO | C46: 15932 | D46: 45809 | E46: 45838 | F46: MENSAL | G46: 0.01 | H46: 0.01 | I46: FILIAL JOAO PESSOA | J46: 45811 | K46: PARAMETRIZAR CAMPANHAS - GC CRISTIANE - REF: JUNHO 2025 | L46: MEU CREDBANK - PRODUÇÃO TOTAL EM TODOS OS PRODUTOS
... A50: 1538 | B50: 06 - JUNHO | C50: 14722 | D50: 45809 | E50: 45838 | F50: MENSAL | G50: 10000 | H50: 0.0075 | I50: FILIAL RECIFE | J50: 45812 | K50: PARAMETRIZAR CAMPANHAS - ID 14722 / 15366 / 12288 / 9212 / 17154 | L50: BANCO FACTA - INSS - NOVO - 96X
A51: 1539 | B51: 06 - JUNHO | C51: 15366 | D51: 45809 | E51: 45838 | F51: MENSAL | G51: 1000 | H51: 0.0022 | I51: FILIAL FORTALEZA | J51: 45812 | K51: PARAMETRIZAR CAMPANHAS - ID 14722 / 15366 / 12288 / 9212 / 17154 | L51: BANCO C6 – NOVO INSS PRODUÇÃO TOTAL
A52: 1540 | B52: 06 - JUNHO | C52: 12288 | D52: 45809 | E52: 45838 | F52: MENSAL | G52: 1000 | H52: 0.005 | I52: FILIAL FORTALEZA | J52: 45812 | K52: PARAMETRIZAR CAMPANHAS - ID 14722 / 15366 / 12288 / 9212 / 17154 | L52: MEU CREDBANK – TABELAS VIGENTES NA CAMPANHA.
A53: 1541 | B53: 06 - JUNHO | C53: 12288 | D53: 45809 | E53: 45838 | F53: MENSAL | G53: 1000 | H53: 0.02 | I53: FILIAL FORTALEZA | J53: 45812 | K53: PARAMETRIZAR CAMPANHAS - ID 14722 / 15366 / 12288 / 9212 / 17154 | L53: BANCO MASTER – OPERAÇÕES DE CARTÕES EM TODOS OS CONVENIOS VIGENTES NA CAMPANHA.
A54: 1542 | B54: 06 - JUNHO | C54: 12288 | D54: 45809 | E54: 45838 | F54: MENSAL | G54: 1000 | H54: 0.0175 | I54: FILIAL FORTALEZA | J54: 45812 | K54: PARAMETRIZAR CAMPANHAS - ID 14722 / 15366 / 12288 / 9212 / 17154 | L54: BANCO MASTER – OPERAÇÕES DE EMPRÉSTIMO EM TODOS OS CONVENIO, PRAZOS E TABELAS VIGENTES NA CAMPANHA.
A55: 1543 | B55: 06 - JUNHO | C55: 17154 | D55: 45809 | E55: 45838 | F55: MENSAL | G55: 1000 | H55: 0.0022 | I55: FILIAL FORTALEZA | J55: 45812 | K55: PARAMETRIZAR CAMPANHAS - ID 14722 / 15366 / 12288 / 9212 / 17154 | L55: BANCO C6 – NOVO INSS PRODUÇÃO TOTAL
A56: 1544 | B56: 06 - JUNHO | C56: 9212 | D56: 45809 | E56: 45838 | F56: MENSAL | G56: 1000 | H56: 0.0075 | I56: FILIAL FORTALEZA | J56: 45812 | K56: PARAMETRIZAR CAMPANHAS - ID 14722 / 15366 / 12288 / 9212 / 17154 | L56: BANCO FACTA - CONFORME REGULAMENTO
A57: 1545 | B57: 06 - JUNHO | C57: 13053 | D57: 45811 | E57: 45838 | F57: MENSAL | G57: 1000 | H57: 0.015 | I57: FILIAL SALVADOR | J57: 45812 | K57: PARAMETRIZAR CAMPANHA I JUNHO I PB SERVICO DE CONSTRUCAO I CNPJ: 27.150.447/0001-01 | L57: MASTER-TODOS OS CONVENIOS E PRODUTOS MFACIL CREDCESTA REFIN CREDCESTA -EMPRESTIMO GOVERNOS E PREFEITURAS -
A58: 1546 | B58: 06 - JUNHO | C58: 16713 | D58: 45809 | E58: 45838 | F58: MENSAL | G58: 0.01 | H58: 0.03 | I58: FILIAL PORTO ALEGRE | J58: 45812 | K58: PARAMETRIZAR CAMPANHA - ID: 16713 - REF: JUNHO | L58: AMIGOZ-TODOS OS CONVENIOS - NOVO, CARTÃO BENEFICIO E CARTÃO | M58: NOVO, CARTÃO BENEFICIO E CARTÃO
A59: 1547 | B59: 06 - JUNHO | C59: 16713 | D59: 45809 | E59: 45838 | F59: MENSAL | G59: 0.01 | H59: 0.019 | I59: FILIAL PORTO ALEGRE | J59: 45812 | K59: PARAMETRIZAR CAMPANHA - ID: 16713 - REF: JUNHO | L59: MASTER-TODOS OS CONVENIOS E PRAZOS-NOVO, CARTÃO BENEFICIO E CARTÃO
A60: 1548 | B60: 06 - JUNHO | C60: 8075 | D60: 45809 | E60: 45838 | F60: MENSAL | G60: 200000 | H60: 200 | I60: FILIAL GOIANIA | J60: 45812 | K60: PARAMETRIZAR CAMPANHA - ID 8075 | L60: PRODUCAO TOTAL
A61: 1549 | B61: 06 - JUNHO | C61: 3752 | D61: 45809 | E61: 45838 | F61: MENSAL | G61: 200000 | H61: 200 | I61: FILIAL GOIANIA | J61: 45812 | K61: PARAMETRIZAR CAMPANHA - ID 3752 | L61: PRODUCAO TOTAL
A62: 1550 | B62: 06 - JUNHO | C62: 3594 | D62: 45809 | E62: 45838 | F62: MENSAL | G62: 200000 | H62: 200 | I62: FILIAL GOIANIA | J62: 45812 | K62: PARAMETRIZAR CMAPANHA - ID 3594 | L62: PRODUCAO TOTAL
A63: 1551 | B63: 06 - JUNHO | C63: 3443 | D63: 45809 | E63: 45838 | F63: MENSAL | G63: 200000 | H63: 200 | I63: FILIAL GOIANIA | J63: 45812 | K63: PARAMETRIZAR CAMPANHA - ID 3443 | L63: PRODUCAO TOTAL
A64: 1552 | B64: 06 - JUNHO | C64: 3422/16482/ 6894 SUB | D64: 45809 | E64: 45811 | F64: MENSAL | G64: 400000 | H64: 0.001 | I64: FILIAL GOIANIA | J64: 45812 | K64: PARAMETRIZAR CAMPANHA - 3422 / 16482 / 6894 SUB | L64: PRODUCAO TOTAL PARA CONTABILIZAR E META-BONIFICACAO EXCETO :o tabelas que estão no GRUPO 001 --CREDITO 3422 E BANCOS Mercantil / Amigoz / Itaú
A65: 1553 | B65: 06 - JUNHO | C65: 17102 | D65: 45809 | E65: 45838 | F65: MENSAL | G65: 0.01 | H65: 0.0025 | I65: FILIAL SP CAPITAL | J65: 45812 | K65: PARAMETRIZAR CAMPANHA I JARVIS 17102 l BANCO FACTA | L65: BANCO FACTA - CONFORME REGULAMENTO
A66: 1554 | B66: 06 - JUNHO | C66: 15216 | D66: 45809 | E66: 45838 | F66: MENSAL | G66: 0.01 | H66: 0.015 | I66: FILIAL BH1 | J66: 45812 | K66: CAMPANHA BANCO MASTER I 15216 I JUNHO I TOTEM SERVICOS E CADASTROS LTDA I CNPJ: 37.529.928/0001-78 | L66: PRODUÇÃO GERAL BANCO MASTER
A67: 1555 | B67: 06 - JUNHO | C67: 16977 | D67: 45809 | E67: 45838 | F67: MENSAL | G67: 0.01 | H67: 0.008 | I67: FILIAL SP CAPITAL | J67: 45813 | K67: CAMPANHA BANCO PRESENÇA BANK I 16977 I JUNHO | L67: PRESENÇA BANK-TODAS AS TABELAS DE NOVO (TODOS OS CONVÊNIOS) E PRODUÇÃO GERAL DE FGTS
A68: 1556 | B68: 06 - JUNHO | C68: 16358 | D68: 45809 | E68: 45838 | F68: MENSAL | G68: 0.01 | H68: 0.006 | I68: FILIAL SP CAPITAL | J68: 45813 | K68: PARAMETRIZAR CAMPANHA I CÓDIGO 16358 l BANCO FACTA | L68: BANCO FACTA - CONFORME REGULAMENTO
A69: 1557 | B69: 06 - JUNHO | C69: 16977 | D69: 45809 | E69: 45838 | F69: MENSAL | G69: 0.01 | H69: 0.035 | I69: FILIAL SP CAPITAL | J69: 45813 | K69: CAMPANHA AMIGOZ I JUNHO I 16977 | L69: AMIGOZ - 3.5 % EM CIMA DE TODAS AS TABELAS RMC E RCC INSS
A70: 1558 | B70: 06 - JUNHO | C70: 16898 | D70: 45810 | E70: 45838 | F70: MENSAL | G70: 200000 | H70: 0.0025 | I70: FILIAL SP CAPITAL | J70: 45813 | K70: CAMPANHA BANCO FACTA I 16898 | L70: BANCO FACTA - CONFORME REGULAMENTO
A71: 1559 | B71: 06 - JUNHO | C71: 17225 | D71: 45809 | E71: 45838 | F71: MENSAL | G71: 0.01 | H71: 0.006 | I71: FILIAL SP | J71: 45813 | K71: PARAMETRIZAR CAMPANHA I BANCO FACTA I COD 17225 - JUNHO | L71: BANCO FACTA - CONFORME REGULAMENTO
A72: 1560 | B72: 06 - JUNHO | C72: 12466 | D72: 45809 | E72: 45838 | F72: MENSAL | G72: 0.01 | H72: 0.02 | I72: FILIAL FORTALEZA | J72: 45813 | K72: CAMPANHAS ANDRÉ MEDEIROS I JUNHO I GC EMMANOEL | L72: PRODUCAO TOTAL -MEU CASH CARD
A73: 1561 | B73: 06 - JUNHO | C73: 12466 | D73: 45809 | E73: 45838 | F73: MENSAL | G73: 0.01 | H73: 0.015 | I73: FILIAL FORTALEZA | J73: 45813 | K73: CAMPANHAS ANDRÉ MEDEIROS I JUNHO I GC EMMANOEL | L73: PRODUCAO TOTAL QUERO MAIS
A74: 1562 | B74: 06 - JUNHO | C74: 16709 | D74: 45809 | E74: 45838 | F74: MENSAL | G74: 0.01 | H74: 0.0075 | I74: FILIAL FORTALEZA | J74: 45813 | K74: CAMPANHAS ANDRÉ MEDEIROS I JUNHO I GC EMMANOEL | L74: BANCO FACTA - CONFORME REGULAMENTO
A75: 1563 | B75: 06 - JUNHO | C75: 16029 | D75: 45809 | E75: 45838 | F75: MENSAL | G75: 0.01 | H75: 0.0075 | I75: FILIAL FORTALEZA | J75: 45813 | K75: CAMPANHAS ANDRÉ MEDEIROS I JUNHO I GC EMMANOEL | L75: BANCO DAYCOVAL (PRODUÇÃO GERAL/TABELAS COMISSIONADAS PELO BANCO)
A76: 1564 | B76: 06 - JUNHO | C76: 13611 | D76: 45809 | E76: 45838 | F76: MENSAL | G76: 0.01 | H76: 0.0075 | I76: FILIAL FORTALEZA | J76: 45813 | K76: CAMPANHAS ANDRÉ MEDEIROS I JUNHO I GC EMMANOEL | L76: BANCO FACTA - CONFORME REGULAMENTO
A77: 1565 | B77: 06 - JUNHO | C77: 17514 | D77: 45809 | E77: 45838 | F77: MENSAL | G77: 0.01 | H77: 0.0026 | I77: FILIAL RECIFE | J77: 45813 | K77: CAMPANHAS ANDRÉ MEDEIROS I JUNHO I GC EMMANOEL | L77: C6 - INSS CONTRATO NOVO - PRAZO 84 e 96 MESES (exceto tabelas com RL)
A78: 1566 | B78: 06 - JUNHO | C78: 17514 | D78: 45809 | E78: 45838 | F78: MENSAL | G78: 0.01 | H78: 0.0021 | I78: FILIAL RECIFE | J78: 45813 | K78: CAMPANHAS ANDRÉ MEDEIROS I JUNHO I GC EMMANOEL | L78: C6 - INSS CONTRATO NOVO - PRAZO 84 e 96 MESES (tabelas com RL)
A79: 1567 | B79: 06 - JUNHO | C79: 15980 | D79: 45809 | E79: 45838 | F79: MENSAL | G79: 0.01 | H79: 0.007 | I79: FILIAL SP | J79: 45813 | K79: PARAMETRIZAÇÃO CAMPANHA I JUNHO I DAYCOVAL I 15980 | L79: DAYCOVAL-70% DO QUE RECEBEMOS DE BONUS DO BANCO.
A80: 1568 | B80: 06 - JUNHO | C80: 15908 | D80: 45809 | E80: 45838 | F80: MENSAL | G80: 0.01 | H80: 0.0075 | I80: FILIAL RIBEIRAO PRETO | J80: 45813 | K80: CAMPANHA BANCO FACTA I JUNHO I 15908 - WASHINGTON MOREIRA DIAS NEVES | L80: BANCO FACTA - CONFORME REGULAMENTO
A81: 1569 | B81: 06 - JUNHO | C81: 8687 | D81: 45809 | E81: 45838 | F81: MENSAL | G81: 0.01 | H81: 0.001 | I81: FILIAL SAO LUIZ | J81: 45814 | K81: PARAMETRIZAR CAMPANHA - GC EDVAN - REF: JUNHO 2025 - PF | L81: BANCO FACTA - INSS - CONFORME REGULAMENTO
A82: 1570 | B82: 06 - JUNHO | C82: 10461 | D82: 45809 | E82: 45838 | F82: MENSAL | G82: 0.01 | H82: 0.01 | I82: FILIAL SAO LUIZ | J82: 45814 | K82: PARAMETRIZAR CAMPANHA - GC EDVAN - REF: JUNHO 2025 - PF | L82: BANCO QUERO MAIS CREDITO - INSS - CARTÃO RMC e CB
A83: 1571 | B83: 06 - JUNHO | C83: 12385 | D83: 45809 | E83: 45838 | F83: MENSAL | G83: 0.01 | H83: 0.01 | I83: FILIAL SAO LUIZ | J83: 45814 | K83: PARAMETRIZAR CAMPANHA - GC EDVAN - REF: JUNHO 2025 - PF | L83: BANCO QUERO MAIS CREDITO - INSS - CARTÃO RMC e CB
A84: 1572 | B84: 06 - JUNHO | C84: 12385 | D84: 45809 | E84: 45838 | F84: MENSAL | G84: 0.01 | H84: 0.005 | I84: FILIAL SAO LUIZ | J84: 45814 | K84: PARAMETRIZAR CAMPANHA - GC EDVAN - REF: JUNHO 2025 - PF | L84: BANCO FACTA - INSS - CONFORME REGULAMENTO
A85: 1573 | B85: 06 - JUNHO | C85: 17743 | D85: 45809 | E85: 45838 | F85: MENSAL | G85: 1 | H85: 0.005 | I85: FILIAL SP | J85: 45814 | K85: PARAMETRIZAR CAMPANHA I JARVIS 17743 | L85: BANCO FACTA - CONFORME REGULAMENTO
A86: 1574 | B86: 06 - JUNHO | C86: 7146 / 9434 | D86: 45809 | E86: 45838 | F86: MENSAL | G86: 250000 | H86: 200 | I86: FILIAL GOIANIA | J86: 45814 | K86: PARAMETRIZAR CAMPANHA - REF: JUNHO 2025 - ID: 7146 / 9434 | L86: PRODUCAO TOTAL .-CREDITO
A87: 1575 | B87: 06 - JUNHO | C87: 14496 | 17540 | D87: 45809 | E87: 45838 | F87: MENSAL | G87: 0.01 | H87: 0.005 | I87: FILIAL CURITIBA | J87: 45814 | K87: PARAMETRIZAR CAMPANHA - ID: 14496 - REF: JUNHO 2025 | L87: BANCO FACTA - CONFORME REGULAMENTO - Crédito cod: 14496
A88: 1576 | B88: 06 - JUNHO | C88: 15980 | D88: 45809 | E88: 45838 | F88: MENSAL | G88: 1 | H88: 0.0075 | I88: FILIAL SP | J88: 45814 | K88: PARAMETRIZAR CAMPANHA l CODIGO 15980 l BANCO FACTA | L88: BANCO FACTA - CONFORME REGULAMENTO
A89: 1577 | B89: 06 - JUNHO | C89: 5948 | D89: 45809 | E89: 45838 | F89: MENSAL | G89: R$ 200.000,00 - R$ 400.000.,00 | H89: R$ 250- R$ 500,0 | I89: FILIAL SAO LUIZ | J89: 45814 | K89: PARAMETRIZAR CAMPANHA - GC EDVAN - REF: JUNHO 2025 | L89: TODOS OS BANCOS - INSS - 96X - TODOS OS PRODUTOS
A90: 1578 | B90: 06 - JUNHO | C90: 5725 | D90: 45809 | E90: 45838 | F90: MENSAL | G90: R$ 200.000,00 - R$ 400.000.,00 | H90: R$ 250- R$ 500,0 | I90: FILIAL SAO LUIZ | J90: 45814 | K90: PARAMETRIZAR CAMPANHA - GC EDVAN - REF: JUNHO 2025 | L90: TODOS OS BANCOS - INSS - 96X - TODOS OS PRODUTOS
A91: 1579 | B91: 06 - JUNHO | C91: 14382 | D91: 45809 | E91: 45838 | F91: MENSAL | G91: R$ 200.000,00 - R$ 400.000.,00 | H91: R$ 250- R$ 500,0 | I91: FILIAL SAO LUIZ | J91: 45814 | K91: PARAMETRIZAR CAMPANHA - GC EDVAN - REF: JUNHO 2025 | L91: TODOS OS BANCOS - INSS - 96X - TODOS OS PRODUTOS
A92: 1580 | B92: 06 - JUNHO | C92: 10400 | D92: 45809 | E92: 45838 | F92: MENSAL | G92: R$ 200.000,00 - R$ 400.000.,00 | H92: R$ 300-R$ 500,0 | I92: FILIAL SAO LUIZ | J92: 45814 | K92: PARAMETRIZAR CAMPANHA - GC EDVAN - REF: JUNHO 2025 | L92: TODOS OS BANCOS - INSS - 96X - TODOS OS PRODUTOS
A93: 1581 | B93: 06 - JUNHO | C93: 5596 | D93: 45809 | E93: 45838 | F93: MENSAL | G93: R$ 200.000,00 - R$ 400.000.,00 | H93: R$ 300-R$ 500,0 | I93: FILIAL SAO LUIZ | J93: 45814 | K93: PARAMETRIZAR CAMPANHA - GC EDVAN - REF: JUNHO 2025 | L93: TODOS OS BANCOS - INSS - 96X - TODOS OS PRODUTOS
A94: 1582 | B94: 06 - JUNHO | C94: 6359 | D94: 45809 | E94: 45838 | F94: MENSAL | G94: R$ 200.000,00 - R$ 400.000.,00 | H94: R$ 300-R$ 500,0 | I94: FILIAL SAO LUIZ | J94: 45814 | K94: PARAMETRIZAR CAMPANHA - GC EDVAN - REF: JUNHO 2025 | L94: TODOS OS BANCOS - INSS - 96X - TODOS OS PRODUTOS
A95: 1583 | B95: 06 - JUNHO | C95: 5023 | D95: 45809 | E95: 45838 | F95: MENSAL | G95: R$ 200.000,00 - R$ 400.000.,00 | H95: R$ 300-R$ 500,0 | I95: FILIAL SAO LUIZ | J95: 45814 | K95: PARAMETRIZAR CAMPANHA - GC EDVAN - REF: JUNHO 2025 | L95: TODOS OS BANCOS - INSS - 96X - TODOS OS PRODUTOS
A96: 1584 | B96: 06 - JUNHO | C96: 12147 | D96: 45809 | E96: 45838 | F96: MENSAL | G96: R$ 200.000,00 - R$ 400.000.,00 | H96: R$ 300-R$ 500,0 | I96: FILIAL SAO LUIZ | J96: 45814 | K96: PARAMETRIZAR CAMPANHA - GC EDVAN - REF: JUNHO 2025 | L96: TODOS OS BANCOS - INSS - 96X - TODOS OS PRODUTOS
A97: 1585 | B97: 06 - JUNHO | C97: 3741 | D97: 45809 | E97: 45838 | F97: MENSAL | G97: R$ 200.000,00 - R$ 400.000.,00 | H97: R$ 250- R$ 500,0 | I97: FILIAL SAO LUIZ | J97: 45814 | K97: PARAMETRIZAR CAMPANHA - GC EDVAN - REF: JUNHO 2025 | L97: TODOS OS BANCOS - INSS - 96X - TODOS OS PRODUTOS
A98: 1586 | B98: 06 - JUNHO | C98: 5844 | D98: 45809 | E98: 45838 | F98: MENSAL | G98: R$ 200.000,00 - R$ 400.000.,00 | H98: R$ 250- R$ 500,0 | I98: FILIAL SAO LUIZ | J98: 45814 | K98: PARAMETRIZAR CAMPANHA - GC EDVAN - REF: JUNHO 2025 | L98: TODOS OS BANCOS - INSS - 96X - TODOS OS PRODUTOS
A99: 1587 | B99: 06 - JUNHO | C99: 4723 | D99: 45809 | E99: 45838 | F99: MENSAL | G99: 80000 | H99: 0.002 | I99: FILIAL LONDRINA | J99: 45817 | K99: PARAMETRIZAR CAMPANHA - ID: 4723 - REF: JUNHO 2025 | L99: BANCO FACTA - CONFORME REGULAMENTO
A100: 1588 | B100: 06 - JUNHO | C100: 11730 | D100: 45809 | E100: 45838 | F100: MENSAL | G100: 50000 | H100: 0.005 | I100: FILIAL FORTALEZA | J100: 45817 | K100: PARAMETRIZAR CAMPANHA - ID 11730 - SAQUE COMPLEMENTAR OLE/PAN/BMG | L100: OPERAÇÕES DE CARTÕES DOS BANCOS OLÉ, PAN E BMG.
A101: 1589 | B101: 06 - JUNHO | C101: 17514 | D101: 45809 | E101: 45838 | F101: MENSAL | G101: 0.01 | H101: 0.005 | I101: FILIAL RECIFE | J101: 45817 | K101: PARAMETRIZAR CAMPANHA - ID: 17514 / 14722 - BMG - JUNHO 2025 | L101: BMG – OPERAÇÕES DE CARTÕES RMC E RCC – TODAS AS TABELAS QUE ESTEJAM VIGENTE PARA PAGAMENTO.
A102: 1590 | B102: 06 - JUNHO | C102: 14722 | D102: 45809 | E102: 45838 | F102: MENSAL | G102: 0.01 | H102: 0.005 | I102: FILIAL RECIFE | J102: 45817 | K102: PARAMETRIZAR CAMPANHA - ID: 17514 / 14722 - BMG - JUNHO 2025 | L102: BMG – OPERAÇÕES DE CARTÕES RMC E RCC – TODAS AS TABELAS QUE ESTEJAM VIGENTE PARA PAGAMENTO.
A103: 1591 | B103: 06 - JUNHO | C103: 6887 | D103: 45809 | E103: 45838 | F103: MENSAL | G103: 100000 | H103: 0.005 | I103: FILIAL SALVADOR | J103: 45817 | K103: PARAMETRIZACAO CAMPANHA I BANCO DIGIO I COD 6887 - JUNHO | L103: DIGIO PRODUCAO TOTAL
...

Sheet MAI - 25
A1: Nº | B1: FECHAMENTO | C1: COD | D1: INICIO | E1: FIM | F1: PERÍODO FECHAMENTO | G1: META | H1: PRÊMIO GANHO | I1: FILIAL | J1: SOLICITAÇÃO (E-MAIL) | K1: ASSUNTO (E-MAIL) | L1: PARÂMETRO
A2: 1120 | B2: 05 - MAIO | C2: 5713 | D2: 45778 | E2: 45808 | F2: MENSAL | G2: 100000 | H2: 0.002 | I2: FILIAL RJ | J2: 45769 | K2: PARAMETRIZAR CAMPANHA - ID 5713 REF ABRIL E MAIO | L2: PRODUCAO TOTAL - EXCETO TABELAS QUE CONSTAM NA VIP
A3: 1122 | B3: 05 - MAIO | C3: 12279 | D3: 45778 | E3: 45808 | F3: MENSAL | G3: 100000 | H3: 0.002 | I3: FILIAL RJ | J3: 45769 | K3: PARAMETRIZAR CAMPANHA - REF ABRIL E MAIO - ID 12279 | L3: PRODUCAO TOTAL - EXCETO TABELAS QUE CONSTAM NA VIP
A4: 1124 | B4: 05 - MAIO | C4: 11937 | D4: 45778 | E4: 45808 | F4: MENSAL | G4: 0.01 | H4: 0.002 | I4: FILIAL SAO LUIZ | J4: 45769 | K4: Fwd: CAMPANHA SUB - ABRIL 2025 | L4: C6 - INSS - TODO CONTRATO NOVO - 96X
A5: 1126 | B5: 05 - MAIO | C5: 12021 | D5: 45778 | E5: 45808 | F5: MENSAL | G5: 0.01 | H5: 0.002 | I5: FILIAL SAO LUIZ | J5: 45769 | K5: Fwd: CAMPANHA SUB - ABRIL 2025 | L5: C6 - INSS - TODO CONTRATO NOVO - 96X
A6: 1128 | B6: 05 - MAIO | C6: 11937 | D6: 45778 | E6: 45808 | F6: MENSAL | G6: 0.01 | H6: 0.005 | I6: FILIAL SAO LUIZ | J6: 45769 | K6: Fwd: CAMPANHA SUB - ABRIL 2025 | L6: BANCO FACTA - INSS - NOVO - CONFORME REGULAMENTO
A7: 1130 | B7: 05 - MAIO | C7: 12021 | D7: 45778 | E7: 45808 | F7: MENSAL | G7: 0.01 | H7: 0.005 | I7: FILIAL SAO LUIZ | J7: 45769 | K7: Fwd: CAMPANHA SUB - ABRIL 2025 | L7: BANCO FACTA - INSS - NOVO - CONFORME REGULAMENTO
A8: 1153 | B8: 05 - MAIO | C8: 726/13552 | D8: 45778 | E8: 45808 | F8: MENSAL | G8: 0.01 | H8: 0.001 | I8: FILIAL BH1 | J8: 45580 | K8: PARAMETRIZAR CAMPANHA - 726 E 13552 SUB | L8: TODOS OS BANCOS E TODOS OS PRODUTOS.-CREDITO 13552
A9: 1154 | B9: 05 - MAIO | C9: 8835 | D9: 45778 | E9: 45808 | F9: MENSAL | G9: 0.01 | H9: r$ 32,00 | I9: FILIAL SP | J9: 45716 | K9: PARAMETRIZAR CAMPANHA - ID 8835 - REEMBOLSO DE TED | L9: REMBOLSO DE TED
A10: 1155 | B10: 05-MAIO | C10: 16988 | D10: 45726 | E10: 45808 | F10: TRIMESTRAL | G10: 0.01 | H10: 0.0025 | I10: FILIAL SP CAPITAL | J10: 45728 | K10: Re: CAMPANHA MES MARÇO 25 - FACTA - GM PROMOTORA 16988 (ERICK VIEIRA) | L10: CONFORME REGRAS FACTA
A11: 1156 | B11: 05 - MAIO | C11: 7460 / 12006 | D11: 45778 | E11: 45808 | F11: MENSAL | G11: 800000 | H11: 0.001 | I11: FILIAL UBERLANDIA | J11: 45730 | K11: PARAMETRIZAR CAMPANHA - 7460 / 12006 | L11: PRODUÇÃO TOTAL - PAGAMENTO DA BONIFICAÇÃO EM AMBOS OS CODIGOS 7460 / 12006
A12: 1157 | B12: 05 - MAIO | C12: 3184-12430 | D12: 45778 | E12: 45808 | F12: MENSAL | G12: 300000 | H12: 0.002 | I12: FILIAL BH2 | J12: 45721 | K12: PARAMETRIZAR CAMPANHA - ID 3184/12430 | L12: PRODUCAO TOTAL PARA ATINGIR A META E CONTABILIZAR-META DESCONSIDERAR BMG E C6 ( INSS /NOVO ) -CREDITO 3184
A13: 1158 | B13: 05 - MAIO | C13: 4310/13955 | D13: 45778 | E13: 45808 | F13: MENSAL | G13: 300000 | H13: 0.004 | I13: FILIAL BH2 | J13: 45728 | K13: PARAMETRIZAR CAMPNAHA - BANCO FACTA - ID 4310 /13955 | L13: FACTA-IREMOS CONSIDERAR TODA A PRODUÇÃO / EXCETO AS TABELAS QUE POSSUEM VIP-credito 14603
A14: 1159 | B14: 05 - MAIO | C14: 7934 | D14: 45778 | E14: 45808 | F14: MENSAL | G14: 1000 | H14: 0.002 | I14: FILIAL JOAO PESSOA | J14: 45734 | K14: PARAMETRIZAR CAMPANHA - ID 7934 - TODA A PRODUÇÃO | L14: TODO A PRODUÇÃO
A15: 1160 | B15: 05 - MAIO | C15: 1729/8125 | D15: 45778 | E15: 45808 | F15: MENSAL | G15: 600000 | H15: 0.005 | I15: FILIAL BH2 | J15: 45737 | K15: PARAMETRIZAR CAMPANHA - ID: 1729 / 8125 - REF: MARÇO 2025 | L15: PRODUCAO TOTAL -CREDITO 1729
A16: 1161 | B16: 05 - MAIO | C16: 12765 | D16: 45778 | E16: 45808 | F16: MENSAL | G16: 1000000 | H16: 0 | I16: FILIAL VITORIA | J16: 45740 | K16: Re: Antecipação de valores RL Rangel Serviços LTDA - 12765 (Projeto de ampliação Call Center) | L16: TODA PRODUÇÃO - CASO ATINJA OU NÃO, APENAS RETORNAR NO E-MAIL COMUNICANDO A PRODUÇÃO
A17: 1162 | B17: 05 - MAIO | C17: 13961 | D17: 45717 | E17: 45808 | F17: FINAL DE CAMPANHA | G17: 700000 | H17: 0.0005 | I17: FILIAL BH2 | J17: 45713 | K17: PARAMETRIZAR CAMPANHA - 13961 | L17: BANCO DIGIO - TODA A PRODUÇÃO
A18: 1163 | B18: 05 - MAIO | C18: 13961 | D18: 45717 | E18: 45808 | F18: FINAL DE CAMPANHA | G18: 1200000 | H18: 0.001 | I18: FILIAL BH2 | J18: 45713 | K18: PARAMETRIZAR CAMPANHA - 13961 | L18: BANCO DIGIO - TODA A PRODUÇÃO
A19: 1164 | B19: 05 - MAIO | C19: 13961 | D19: 45717 | E19: 45808 | F19: FINAL DE CAMPANHA | G19: 2000000 | H19: 0.0015 | I19: FILIAL BH2 | J19: 45713 | K19: PARAMETRIZAR CAMPANHA - 13961 | L19: BANCO DIGIO - TODA A PRODUÇÃO
A20: 1165 | B20: 05 - MAIO | C20: 8465/1363/3728/3729 | D20: 45748 | E20: 45808 | F20: FINAL DE CAMPANHA | G20: 500000 | H20: 0.01 | I20: FILIAL BH1 | J20: 45749 | K20: PARAMETRIZAR CAMPANHA - ID 8465/1363/3728/3729 - BANCO AMIGOZ | L20: TODA A PRODUÇÃO AMIGOZ-CREDITO o 8465.
A21: 1167 | B21: 05 - MAIO | C21: 2911-11402 | D21: 45778 | E21: 45808 | F21: MENSAL | G21: 1 | H21: 0.002 | I21: FILIAL VITORIA | J21: 45754 | K21: PARAMETRIZAR CAMPANHA - 2911 E 11402 - ABRIL 2025 | L21: TODOS BANCOS / INSS-SIAPE/novo / port/refin de port /cartao rmc /cartao benefcio / 84X TODAS AS TABELAS CREDITO 2911
A22: 1168 | B22: 05 - MAIO | C22: 2911-11402 | D22: 45778 | E22: 45808 | F22: MENSAL | G22: 1 | H22: 0.002 | I22: FILIAL VITORIA | J22: 45754 | K22: PARAMETRIZAR CAMPANHA - 2911 E 11402 - ABRIL 2025 | L22: fACTA/INSS/NOVO/CARTAO RMC/CARTAO BENEFICIO /PORT E REFIN DA PORT /84X TODAS AS TABELAS-CREDITO 2911
A23: 1169 | B23: 05 - MAIO | C23: 3209-13857 | D23: 45778 | E23: 45808 | F23: MENSAL | G23: 300.000,00 | H23: 0.002 | I23: FILIAL BH2 | J23: 45763 | K23: PARAMETRIZAR CAMPANHA - ID 3209/13857 | L23: PRODUCAO TOTAL Exceto (INSS-NOVO-BMG)-CREDITO 3209
A24: 1170 | B24: 05 - MAIO | C24: 1212 | D24: 45778 | E24: 45808 | F24: MENSAL | G24: 0 A499.999,00 | H24: 0.002 | I24: FILIAL UBERLANDIA | J24: 45764 | K24: PARAMETRIZAR CAMPANHA - ID: 1212 - REF: ABRIL E MAIO | L24: BANCO DIGIO CONVENIO SIAPE
A25: 1172 | B25: 05 - MAIO | C25: 5599 | D25: 45778 | E25: 45808 | F25: MENSAL | G25: 400000 | H25: 0.005 | I25: FILIAL UBERLANDIA | J25: 45764 | K25: PARAMETRIZAR CAMPANHA - 5599 | L25: DIGIO PRODUCAO TOTAL
A26: 1173 | B26: 05 - MAIO | C26: 3444 | D26: 45778 | E26: 45808 | F26: MENSAL | G26: 10000 | H26: 0.005 | I26: FILIAL UBERLANDIA | J26: 45769 | K26: PARAMETRIZAR CAMPANHA- ID 3444/10487 | L26: CONSIDERAR A PRODUÇAO DO MEU CREDBANK PARA APURAÇAO.
A27: 1174 | B27: 05 - MAIO | C27: 3444 | D27: 45778 | E27: 45808 | F27: MENSAL | G27: 10000 | H27: 0.005 | I27: FILIAL UBERLANDIA | J27: 45769 | K27: PARAMETRIZAR CAMPANHA- ID 3444/10487 | L27: CONSIDERAR A PRODUÇAO DO BANCO MERCANTIL PARA APURAÇAO.
A28: 1175 | B28: 05 - MAIO | C28: 3444 | D28: 45778 | E28: 45808 | F28: MENSAL | G28: 10000 | H28: 0.003 | I28: FILIAL UBERLANDIA | K28: PARAMETRIZAR CAMPANHA- ID 3444/10487 | L28: CONSIDERAR A PRODUÇAO DO BANCO FACTA PARA APURAÇAO.
A29: 1176 | B29: 05 - MAIO | C29: 10487 | D29: 45778 | E29: 45808 | F29: MENSAL | G29: 10000 | H29: 0.005 | I29: FILIAL UBERLANDIA | K29: PARAMETRIZAR CAMPANHA- ID 3444/10487 | L29: CONSIDERAR A PRODUÇAO DO VCTEX PARA APURAÇAO.
A30: 1177 | B30: 05 - MAIO | C30: 15001 / 6935 | D30: 45778 | E30: 45807 | F30: MENSAL | G30: 200000 | H30: 0.005 | I30: FILIAL UBERLANDIA | J30: 45762 | K30: PARAMETRIZAR CAMPANHA - 15001 | 6935 | L30: CONSIDERAR TODA A PRODUÇAO NO FACTA PARA APURAÇAO E ATINGIMENTO DA META EM AMBOS OS CODIGOS.-CREDITO 6935
A31: 1178 | B31: 05 - MAIO | C31: 15001 / 6935 | D31: 45778 | E31: 45807 | F31: MENSAL | G31: 200000 | H31: 0.005 | I31: FILIAL UBERLANDIA | J31: 45762 | K31: PARAMETRIZAR CAMPANHA - 15001 | 6935 | L31: CONSIDERAR TODA A PRODUÇAO NO DIGIO PARA APURAÇAO E ATINGIMENTO DA META EM AMBOS OS CODIGOS.-CREDITO 6935
A32: 1179 | B32: 05 - MAIO | C32: 15001 / 6935 | D32: 45778 | E32: 45807 | F32: MENSAL | G32: 150000 | H32: 0.0025 | I32: FILIAL UBERLANDIA | J32: 45762 | K32: PARAMETRIZAR CAMPANHA - 15001 | 6935 | L32: CONSIDERAR TODA A PRODUÇAO NO MEU CREDBANK PARA APURAÇAO E ATINGIMENTO DA META EM AMBOS OS CODIGOS.-CREDITO 6935
A33: 1180 | B33: 05 - MAIO | C33: 16403 | D33: 45778 | E33: 45807 | F33: MENSAL | G33: 150000 | H33: 0.0025 | I33: FILIAL UBERLANDIA | J33: 45763 | K33: PARAMETRIZAR CAMPANHA - ID 16403/17375 | L33: CONSIDERAR SOMENTE A PRODUÇÃO INSS DO BANCO DIGIO PARA APURAÇAO E ATINGIMENTO DA META.
A34: 1181 | B34: 05 - MAIO | C34: 16403 | D34: 45778 | E34: 45807 | F34: MENSAL | G34: 100000 | H34: 0.003 | I34: FILIAL UBERLANDIA | J34: 45763 | K34: PARAMETRIZAR CAMPANHA - ID 16403/17375 | L34: CONSIDERAR A PRODUÇÃO TOTAL DO BANCO FACTA PARA APURAÇAO E ATINGIMENTO DA META.
A35: 1182 | B35: 05 - MAIO | C35: 17375 | D35: 45778 | E35: 45807 | F35: MENSAL | G35: 40000 | H35: 0.005 | I35: FILIAL UBERLANDIA | J35: 45763 | K35: PARAMETRIZAR CAMPANHA - ID 16403/17375 | L35: CONSIDERAR A PRODUÇÃO TOTAL DO BANCO VCTEX PARA APURAÇAO E ATINGIMENTO DA META.
A36: 1183 | B36: 05 - MAIO | C36: 12340 | D36: 45778 | E36: 45807 | F36: MENSAL | G36: 300.000,00 / 500.000,00 | H36: 0.10% / 0,20% | I36: FILIAL UBERLANDIA | J36: 45763 | K36: PARAMETRIZAR CAMPANHA - ID 12340 | L36: PRODUCAO TOTAL PARA CONTABILIZAR-META PRODUCAO TOTAL DESCONSIDERANDO BANCO BMG-CREDITO 3190
A37: 1184 | B37: 05 - MAIO | C37: 3190 / 6950 / 7036 | D37: 45778 | E37: 45807 | F37: MENSAL | G37: 300.000,00 / 500.000,00 | H37: 0.10% / 0,20% | I37: FILIAL UBERLANDIA | J37: 45762 | K37: PARAMETRIZAR CAMPANHA - ID´s 3190 / 6950 / 7036 | L37: PRODUCAO TOTAL -CREDITO 3190
A38: 1185 | B38: 05 - MAIO | C38: 1427 | D38: 45778 | E38: 45807 | F38: MENSAL | G38: 0.01 | H38: 0.0045 | I38: FILIAL BH2 | J38: 45721 | K38: PARAMETRIZAR CAMPANHA - ID 1427 - BANCO FACTA | L38: Facta / INSS / Novo / 96, 84, 72 Facta / INSS / Refin de Port / 40 a 96
A39: 1186 | B39: 05 - MAIO | C39: 16710 | D39: 45778 | E39: 45808 | F39: MENSAL | G39: 1000 | H39: 0.005 | I39: FILIAL SERTAO DE PERNAMBUCO | J39: 45775 | K39: PARAMETRIZAR CAMPANHA - 16710 | L39: FACTA - TODOS OS PRAZOS EM NOVO (exceto CLT)
A40: 1187 | B40: 05 - MAIO | C40: 13483 | D40: 45778 | E40: 45808 | F40: MENSAL | G40: 100000 | H40: 0.002 | I40: FILIAL RJ | J40: 45777 | K40: PARAMETRIZAR CAMPANHA - 13483 | L40: PRODUCAO TOTAL CONTABILIZAR E ATINGIR A META BONIFICACAO DESCONSIDERAR TABELAS VIP
A41: 1188 | B41: 05 - MAIO | C41: 17467 | D41: 45778 | E41: 45808 | F41: MENSAL | G41: 0.01 | H41: 0.005 | I41: FILIAL LONDRINA | J41: 45779 | K41: PARAMETRIZA CAMPANHA - BANCO FACTA - COD 17467 - MAIO | L41: FACTA CONFORME REGULAMENTO
A42: 1189 | B42: 05 - MAIO | C42: 2598 | D42: 45778 | E42: 45808 | F42: MENSAL | G42: 0.01 | H42: 0.0025 | I42: FILIAL BH1 | J42: 45779 | K42: PARAMETRIZAR CAMPANHA - ID: 2598 - REF: MAIO 2025 | L42: TODOS OS BANCOS E TODOS OS PRODUTOS. Exceto banco BMG E ITAU E TABELAS QUE POSSUEM REGRAS VIP APROVADAS)
A43: 1190 | B43: 05 - MAIO | C43: 15087 | D43: 45778 | E43: 45808 | F43: MENSAL | G43: 30000 | H43: 0.0025 | I43: FILIAL BELEM | J43: 45779 | K43: PARAMETRIZAR CAMPANHA - 15087 | L43: REFIN DA PORT \ MEUCREDBANK\INSS\96 E 84 X
A44: 1191 | B44: 05 - MAIO | C44: 17142 | D44: 45778 | E44: 45808 | F44: MENSAL | G44: 30000 | H44: 0.005 | I44: FILIAL BELEM | J44: 45782 | K44: PARAMETRIZAÇÃO CAMPANHA - COD 17142 - BANCO MASTER - MAIO | L44: MASTER-TODOS OS PRODUTOS E PRAZOS
A45: 1192 | B45: 05 - MAIO | C45: 15086 | D45: 45778 | E45: 45808 | F45: MENSAL | G45: 1000 | H45: 0.005 | I45: FILIAL JOAO PESSOA | K45: CADASTRAR CAMPANHAS | 15086 SUB D VALOR e 5804 JOSEVAL PF | L45: FACTA TODOS OS CONVENIOS E PRAZOS
A46: 1193 | B46: 05 - MAIO | C46: 5804 | D46: 45778 | E46: 45808 | F46: MENSAL | G46: 1000 | H46: 0.005 | I46: FILIAL JOAO PESSOA | J46: 45782 | K46: CADASTRAR CAMPANHAS | 15086 SUB D VALOR e 5804 JOSEVAL PF | L46: BANCO MEU CREDBANK - INSS – APENAS TABELAS COM SEGURO.
A47: 1194 | B47: 05 - MAIO | C47: 15086 | D47: 45778 | E47: 45808 | F47: MENSAL | G47: 0.01 | H47: 0.02 | I47: FILIAL JOAO PESSOA | J47: 45782 | K47: CADASTRAR CAMPANHAS | 15086 SUB D VALOR e 5804 JOSEVAL PF | L47: MEU CASH CARD - TODAS OS PRODUTOS E TABELAS
A48: 1195 | B48: 05 - MAIO | C48: 15086 | D48: 45778 | E48: 45808 | F48: MENSAL | G48: 0.01 | H48: 0.005 | I48: FILIAL JOAO PESSOA | J48: 45782 | K48: CADASTRAR CAMPANHAS | 15086 SUB D VALOR e 5804 JOSEVAL PF | L48: C6 – TODOS OS CONVENIOS, NAS TABELAS ELEGIVEIS.
A49: 1196 | B49: 05 - MAIO | C49: 15086 | D49: 45778 | E49: 45808 | F49: MENSAL | G49: 0.01 | H49: 0.005 | I49: FILIAL JOAO PESSOA | J49: 45782 | K49: CADASTRAR CAMPANHAS | 15086 SUB D VALOR e 5804 JOSEVAL PF | L49: DAYCOVAL - 50% DO BÔNUS QUE A CREDFRANCO RECEBER DO BANCO , NAS TABELAS ELEGIVIES.
A50: 1197 | B50: 05 - MAIO | C50: 14363 | D50: 45778 | E50: 45808 | F50: MENSAL | G50: 1000 | H50: 0.015 | I50: FILIAL FLORIANOPOLIS | J50: 45782 | K50: PARAMETRIZAR CAMPANHA - 14363 | L50: QUERO MAIS -SIAPE CARTÃO CONSIGNADO E CARTÃO BENEFICIO
A51: 1198 | B51: 05 - MAIO | C51: 16236 | D51: 45778 | E51: 45808 | F51: MENSAL | G51: 10000 | H51: 0.005 | I51: FILIAL RECIFE | J51: 45782 | K51: CADASTRAR CAMPANHA l JARVIS 16236 l BANCO FACTA | L51: FACTA CONFORME REGULAMENTO
A52: 1199 | B52: 05 - MAIO | C52: 8336 | D52: 45778 | E52: 45808 | F52: MENSAL | G52: 0.01 | H52: 0.02 | I52: FILIAL SP CAPITAL | J52: 45782 | K52: PARAMETRIZAR CAMPANHA - ID: 8336 - REF; MAIO 2025 | L52: AMIGOZ-CONFORME CAMPANHA-INSS-CARTOES-EXCETO PLASTICO (CONFORME CAMPANHA DO BANCO)
A53: 1200 | B53: 05 - MAIO | C53: 16055 | D53: 45778 | E53: 45808 | F53: MENSAL | G53: 0.01 | H53: 0.0075 | I53: FILIAL SP CAPITAL | J53: 45783 | K53: CAMPANHA FACTA I MAIO I 16055 SUB - INSTITUTO VAP | L53: FACTA CONFORME REGULAMENTO
A54: 1201 | B54: 05 - MAIO | C54: 15087 | D54: 45778 | E54: 45808 | F54: MENSAL | G54: 30000 | H54: 0.005 | I54: FILIAL BELEM | J54: 45783 | K54: PARAMETRIZAR CAMPANHA - 15087 | L54: NOVO COM E SEM SEGURO \ PRESENÇA BANK \INSS\96 E 84 X
A55: 1202 | B55: 05 - MAIO | C55: 9212 | D55: 45778 | E55: 45808 | F55: MENSAL | G55: 0.01 | H55: 0.0075 | I55: FILIAL FORTALEZA | J55: 45783 | K55: PARAMETRIZAR CAMPANHAS - GC CHRISTIANE - REF: MAIO 2025 | L55: FACTA – PRODUÇAÕ TOTAL CONFORME PARÂMETRO DO BANCO
A56: 1203 | B56: 05 - MAIO | C56: 15366 | D56: 45778 | E56: 45808 | F56: MENSAL | G56: 0.01 | H56: 0.0022 | I56: FILIAL FORTALEZA | J56: 45783 | K56: PARAMETRIZAR CAMPANHAS - GC CHRISTIANE - REF: MAIO 2025 | L56: BANCO C6 – NOVO INSS-PRAZO MAXIMO
A57: 1204 | B57: 05 - MAIO | C57: 15932 | D57: 45778 | E57: 45808 | F57: MENSAL | G57: 0.01 | H57: 0.015 | I57: FILIAL JOAO PESSOA | J57: 45783 | K57: PARAMETRIZAR CAMPANHAS - GC CHRISTIANE - REF: MAIO 2025 | L57: PRESENÇA BANK- PRODUÇÃO TOTAL
A58: 1205 | B58: 05 - MAIO | C58: 15932 | D58: 45778 | E58: 45808 | F58: MENSAL | G58: 0.01 | H58: 0.035 | I58: FILIAL JOAO PESSOA | J58: 45783 | K58: PARAMETRIZAR CAMPANHAS - GC CHRISTIANE - REF: MAIO 2025 | L58: AMIGOZ – PRODUÇÃO TOTAL
A59: 1206 | B59: 05 - MAIO | C59: 15932 | D59: 45778 | E59: 45808 | F59: MENSAL | G59: 0.01 | H59: 0.0075 | I59: FILIAL JOAO PESSOA | J59: 45783 | K59: PARAMETRIZAR CAMPANHAS - GC CHRISTIANE - REF: MAIO 2025 | L59: MEU CREDBANK - REFIN DA PORT -INSS-PRAZO MÁXIMO
A60: 1207 | B60: 05 - MAIO | C60: 15932 | D60: 45778 | E60: 45808 | F60: MENSAL | G60: 0.01 | H60: 0.005 | I60: FILIAL JOAO PESSOA | J60: 45783 | K60: PARAMETRIZAR CAMPANHAS - GC CHRISTIANE - REF: MAIO 2025 | L60: MEU CREDBANK – NOVO COM SEGURO-INSS-PRAZO MAXIMO
A61: 1208 | B61: 05 - MAIO | C61: 15932 | D61: 45778 | E61: 45808 | F61: MENSAL | G61: 0.01 | H61: 0.0025 | I61: FILIAL JOAO PESSOA | J61: 45783 | K61: PARAMETRIZAR CAMPANHAS - GC CHRISTIANE - REF: MAIO 2025 | L61: MEU CREDBANK – NOVO SEM SEGURO-INSS-PRAZO MAXIMO
A62: 1209 | B62: 05 - MAIO | C62: 12466 | D62: 45778 | E62: 45808 | F62: MENSAL | G62: 0.01 | H62: 0.02 | I62: FILIAL FORTALEZA | J62: 45783 | K62: PARAMETRIZAR CAMPANHA - MAIO - GC MICHAELE | L62: B2S (MEU CASHCARD) - TODOS OS CONVÊNIOS - TODOS OS PRAZOS E TABELAS
A63: 1210 | B63: 05 - MAIO | C63: 12466 | D63: 45778 | E63: 45808 | F63: MENSAL | G63: 0.01 | H63: 0.015 | I63: FILIAL FORTALEZA | J63: 45783 | K63: PARAMETRIZAR CAMPANHA - MAIO - GC MICHAELE | L63: QUERO MAIS PRODUCAO TOTAL
A64: 1211 | B64: 05 - MAIO | C64: 13249 | D64: 45778 | E64: 45808 | F64: MENSAL | G64: 0.01 | H64: 0.018 | I64: FILIAL FORTALEZA | J64: 45783 | K64: PARAMETRIZAR CAMPANHA - MAIO - GC MICHAELE | L64: PAN - CONVÊNIOS PÚBLICOS - TODOS OS PRODUTOS (EXCETO INSS, FGTS E SIAPE)
A65: 1212 | B65: 05 - MAIO | C65: 13249 | D65: 45778 | E65: 45808 | F65: MENSAL | G65: 0.01 | H65: 0.005 | I65: FILIAL FORTALEZA | J65: 45783 | K65: PARAMETRIZAR CAMPANHA - MAIO - GC MICHAELE | L65: PAN - CASCATA - FGTS-TABELAS FLEX
A66: 1213 | B66: 05 - MAIO | C66: 13249 | D66: 45778 | E66: 45808 | F66: MENSAL | G66: 0.01 | H66: 0.005 | I66: FILIAL FORTALEZA | J66: 45783 | K66: PARAMETRIZAR CAMPANHA - MAIO - GC MICHAELE | L66: PAN - ORÇAMENTO SECRETO - FGTS -EXCETO TABELAS FLEX
A67: 1214 | B67: 05 - MAIO | C67: 13249 | D67: 45778 | E67: 45808 | F67: MENSAL | G67: 0.01 | H67: 0.0275 | I67: FILIAL FORTALEZA | J67: 45783 | K67: PARAMETRIZAR CAMPANHA - MAIO - GC MICHAELE | L67: PAN - SAQUE COMPLEMENTAR - TODOS OS PRODUTOS DE CARTÃO
A68: 1215 | B68: 05 - MAIO | C68: 13470 | D68: 45778 | E68: 45808 | F68: MENSAL | G68: 0.01 | H68: 0.0015 | I68: FILIAL FORTALEZA | J68: 45783 | K68: PARAMETRIZAR CAMPANHA - MAIO - GC MICHAELE | L68: FACTA - NOVO - 84x -INSS
A69: 1216 | B69: 05 - MAIO | C69: 13611 | D69: 45778 | E69: 45808 | F69: MENSAL | G69: 0.01 | H69: 0.0075 | I69: FILIAL FORTALEZA | J69: 45783 | K69: PARAMETRIZAR CAMPANHA - MAIO - GC MICHAELE | L69: FACTA CONFORME REGULAMENTO
A70: 1217 | B70: 05 - MAIO | C70: 12986 | D70: 45778 | E70: 45808 | F70: MENSAL | G70: 0.01 | H70: 0.005 | I70: FILIAL FORTALEZA | J70: 45783 | K70: PARAMETRIZAR CAMPANHA - MAIO - GC MICHAELE | L70: VCTEX - SOBRE TODA A OPERAÇÃO
A71: 1218 | B71: 05 - MAIO | C71: 17031 | D71: 45778 | E71: 45808 | F71: MENSAL | G71: 0.01 | H71: 0.004 | I71: FILIAL FORTALEZA | J71: 45783 | K71: PARAMETRIZAR CAMPANHA - MAIO - GC MICHAELE | L71: QUERO MAIS PRODUCAO TOTAL
A72: 1219 | B72: 05 - MAIO | C72: 12466 | D72: 45778 | E72: 45808 | F72: MENSAL | G72: 0.01 | H72: 1 | I72: FILIAL FORTALEZA | J72: 45783 | K72: PARAMETRIZAR CAMPANHA - MAIO - GC MICHAELE | L72: ITAU -SOBRE OQUE RECEBEMOS 100%
A73: 1220 | B73: 05 - MAIO | C73: 12288 | D73: 45778 | E73: 45808 | F73: MENSAL | G73: 0.01 | H73: 0.018 | I73: FILIAL FORTALEZA | J73: 45783 | K73: PARAMETRIZAR CAMPANHA - GC MICHAELE | L73: MASTER - TODOS OS PRODUTOS E PRAZOS
... A82: 1229 | B82: 05 - MAIO | C82: 12932 | D82: 45778 | E82: 45808 | F82: MENSAL | G82: 0.01 | H82: 0.01 | I82: FILIAL FORTALEZA | J82: 45792 | K82: PARAMETRIZAR CAMPANHA - GC MICHAELE | L82: PRESENÇA BANK - TODOS OS PRODUTOS E PRAZOS (exceto clt)
A83: 1230 | B83: 05 - MAIO | C83: 13166 | D83: 45778 | E83: 45808 | F83: MENSAL | G83: 300000 | H83: 0.005 | I83: FILIAL PORTO ALEGRE | J83: 45783 | K83: PARAMTRIZAR CAMPANHA I BANCO FACTA I COD 13166 - MAIO | L83: FACTA CONFORME REGULAMENTO
A84: 1231 | B84: 05 - MAIO | C84: 17229 | D84: 45778 | E84: 45808 | F84: MENSAL | G84: 0.01 | H84: 0.005 | I84: FILIAL PORTO ALEGRE | J84: 45783 | K84: PARAMETRIZAR CAMPANHA I BANCO FACTA I COD 17229 -MAIO | L84: FACTA CONFORME REGULAMENTO
A85: 1232 | B85: 05 - MAIO | C85: 16995 | D85: 45778 | E85: 45808 | F85: MENSAL | G85: 300000 | H85: 0.005 | I85: FILIAL PORTO ALEGRE | J85: 45783 | K85: PARAMETRIZAÇÃO CAMPANHA I BANCO FACTA I COD 16995 -MAIO | L85: FACTA CONFORME REGULAMENTO
A86: 1235 | B86: 05 - MAIO | C86: 16360 | D86: 45778 | E86: 45808 | F86: MENSAL | G86: 100000 | H86: 0.005 | I86: FILIAL PORTO ALEGRE | J86: 45783 | K86: PARAMETRIZAR CAMPANHA I BANCO FACTA I COD 16360 - MAIO | L86: FACTA - TODOS OS PRODUTOS E PRAZOS
A87: 1236 | B87: 05 - MAIO | C87: 17421 | D87: 45778 | E87: 45808 | F87: MENSAL | G87: 300000 | H87: 0.005 | I87: FILIAL PORTO ALEGRE | J87: 45783 | K87: PARAMETRIZAR CAMPANHA I BANCO FACTA I COD 17421 - MAIO | L87: FACTA CONFORME REGULAMENTO
A88: 1239 | B88: 05 - MAIO | C88: 1818 | D88: 45778 | E88: 45808 | F88: MENSAL | G88: 500000 | H88: 0.002 | I88: FILIAL BH2 | J88: 45783 | K88: PARAMETRIZAR CAMPANHA - ID: 1818 - REF: MAIO 2025 | L88: TODA A PRODUÇÃO ( EXCETO TABELAS VIP)
A89: 1240 | B89: 05 - MAIO | C89: 16898 | D89: 45779 | E89: 45808 | F89: MENSAL | G89: 200000 | H89: 0.0025 | I89: FILIAL SP CAPITAL | J89: 45784 | K89: CAMPANHA MAIO FACTA | JARVIS 16898 | L89: FACTA CONFORME REGULAMENTO
A90: 1241 | B90: 05 - MAIO | C90: 17102 | D90: 45779 | E90: 45808 | F90: MENSAL | G90: 200000 | H90: 0.0025 | I90: FILIAL SP CAPITAL | J90: 45784 | K90: PARAMETRIZAR CAMPANHA I BANCO FACTA I COD17102 - MAIO | L90: FACTA CONFORME REGULAMENTO
A91: 1242 | B91: 05 - MAIO | C91: 15874 | D91: 45778 | E91: 45808 | F91: MENSAL | G91: 0.01 | H91: 0.005 | I91: FILIAL BH2 | J91: 45783 | K91: PARAMETRIZAR CAMPANHA I BANCO QUERO MAIS I COD 15874 -MAIO | L91: QUERO MAIS/ INSS/SIAPE/CARTÃO RMC/CARTÃO BENEFÍCIO/ TODAS AS TABELAS
A92: 1243 | B92: 05 - MAIO | C92: 8687 | D92: 45778 | E92: 45808 | F92: MENSAL | G92: 0.01 | H92: 0.001 | I92: FILIAL SAO LUIZ | J92: 45784 | K92: PARAMETRIZAR CAMPANHA - GC EDVAN | L92: FACTA - INSS - TODOS OS PRODUTOS
A93: 1244 | B93: 05 - MAIO | C93: 10461 | D93: 45778 | E93: 45808 | F93: MENSAL | G93: 0.01 | H93: 0.01 | I93: FILIAL SAO LUIZ | J93: 45784 | K93: PARAMETRIZAR CAMPANHA - GC EDVAN | L93: BANCO QUERO MAIS CRÉDITO - INSS - CARTÃO RMC e CB
A94: 1245 | B94: 05 - MAIO | C94: 12385 | D94: 45778 | E94: 45808 | F94: MENSAL | G94: 0.01 | H94: 0.01 | I94: FILIAL SAO LUIZ | J94: 45784 | K94: PARAMETRIZAR CAMPANHA - GC EDVAN | L94: BANCO QUERO MAIS CRÉDITO - INSS - CARTÃO RMC e CB
A95: 1246 | B95: 05 - MAIO | C95: 12385 | D95: 45778 | E95: 45808 | F95: MENSAL | G95: 0.01 | H95: 0.005 | I95: FILIAL SAO LUIZ | J95: 45784 | K95: PARAMETRIZAR CAMPANHA - GC EDVAN | L95: FACTA - INSS - TODOS OS PRODUTOS
A96: 1247 | B96: 05 - MAIO | C96: 10649 | D96: 45778 | E96: 45808 | F96: MENSAL | G96: 180000 | H96: 0.002 | I96: FILIAL RJ | J96: 45784 | K96: PARAMETRIZAR CAMPANHA - GC IGOR | L96: PRODUCAO TOTAL ATINGIR A META-BONIFICACAO NOVOS INSS C 6 ,FACTA , CREDBANK, PRESENÇA E VCTEX
A97: 1249 | B97: 05 - MAIO | C97: 15244 | D97: 45778 | E97: 45808 | F97: MENSAL | G97: 1000 | H97: 0.0025 | I97: FILIAL RJ | J97: 45784 | K97: PARAMETRIZAR CAMPANHA - GC IGOR | L97: BANCO MASTER (TODOS OS CONVÊNIOS)
A98: 1250 | B98: 05 - MAIO | C98: 14129 | D98: 45778 | E98: 45808 | F98: MENSAL | G98: 1000 | H98: 0.0075 | I98: FILIAL RJ | J98: 45784 | K98: PARAMETRIZAR CAMPANHA - GC IGOR | L98: FACTA CONFORME REGULAMENTO
A99: 1251 | B99: 05 - MAIO | C99: 865 / 13671 | D99: 45778 | E99: 45808 | F99: MENSAL | G99: 0.01 | H99: 0.002 | I99: FILIAL UBERLANDIA | J99: 45784 | K99: PARAMETRIZAR CAMPANHA - 865 e 13671 | L99: PRODUCAO TOTAL - CREDITO 865
A100: 1252 | B100: 05 - MAIO | C100: 14544 | D100: 45778 | E100: 45808 | F100: MENSAL | G100: 100000 | H100: 0.0025 | I100: FILIAL SALVADOR | J100: 45789 | K100: PARAMETRIZAR CAMPANHA - ID: 14544 - REF: MAIO 2025 | L100: CONTABILIZAR TODA PRODUÇÃO PARA META E REMUNERAR BANCO MASTER APENAS, MFÁCIL E CREDCESTA, TODOS OS CONVÊNIOS EXCETO INSS.
A101: 1253 | B101: 05 - MAIO | C101: 13900 | D101: 45778 | E101: 45808 | F101: MENSAL | G101: 0.01 | H101: 0.001 | I101: FILIAL SAO LUIZ | J101: 45789 | K101: CADASTRAR CAMPANHA MAIO | BANCO FACTA | JARVIS 13900 | L101: CONFORME REGULAMENTO FACTA (E EXCETO CLT).
A102: 1254 | B102: 05 - MAIO | C102: 17288 | D102: 45778 | E102: 45808 | F102: MENSAL | G102: 10000 | H102: 0.007 | I102: FILIAL SALVADOR | J102: 45789 | K102: CAMPANHA BANCO FACTA I 17288 I MAIO | L102: CONFORME REGRAS FACTA
A103: 1255 | B103: 05 - MAIO | C103: 14105 | D103: 45778 | E103: 45808 | F103: MENSAL | G103: 1000 | H103: 0.002 | I103: FILIAL GOIANIA | J103: 45762 | K103: PARAMETRIZAR CAMPANHA I BANCO QUERO + I COD 14105 - MAIO | L103: QUERO MAIS-SOMENTE SOBRE CONVÊNIO SIAPE-TODOS OS PRODUTOS
A104: 1256 | B104: 05 - MAIO | C104: 17303 | D104: 45778 | E104: 45790 | F104: MENSAL | G104: 1000 | H104: 0.03 | I104: FILIAL JOAO PESSOA | J104: 45790 | K104: PARAMETRIZAR CAMPANHA - ID: 17303 - REF: MAIO 2025 | L104: PRODUCAO TOTAL AMIGOZ
A105: 1257 | B105: 05 - MAIO | C105: 13694 | D105: 45778 | E105: 45808 | F105: MENSAL | G105: 200000 | H105: 0.005 | I105: FILIAL VITORIA | J105: 45790 | K105: PARAMETRIZAR CAMPANHA - 13694 | L105: PRODUCAO TOTAL ATINGIR A META-BONIFICACAO NOVO /INSS/PRAZO 84 E 96 / BANCO FACTA
A106: 1258 | B106: 05 - MAIO | C106: 13694 | D106: 45778 | E106: 45808 | F106: MENSAL | G106: 200000 | H106: 0.005 | I106: FILIAL VITORIA | J106: 45790 | K106: PARAMETRIZAR CAMPANHA - 13694 | L106: PRODUCAO TOTAL ATINGIR A META-BONIFICACAO NOVO /INSS/PRAZO 84 E 96 / PRESENÇA BANK
A107: 1259 | B107: 05 - MAIO | C107: 13694 | D107: 45778 | E107: 45808 | F107: MENSAL | G107: 200000 | H107: 0.005 | I107: FILIAL VITORIA | J107: 45790 | K107: PARAMETRIZAR CAMPANHA - 13694 | L107: PRODUCAO TOTAL ATINGIR A META-BONIFICACAO NOVO /INSS/PRAZO 84 E 96 / MEU CREDBANK
A108: 1260 | B108: 05 - MAIO | C108: 13694 | D108: 45778 | E108: 45808 | F108: MENSAL | G108: 200000 | H108: 0.005 | I108: FILIAL VITORIA | J108: 45790 | K108: PARAMETRIZAR CAMPANHA - 13694 | L108: PRODUCAO TOTAL ATINGIR A META -BONIFICACAO NOVO /INSS/PRAZO 84 E 96 / BMG
...

Sheet ABR - 25
A1: Nº | B1: FECHAMENTO | C1: COD | D1: INICIO | E1: FIM | F1: PERÍODO FECHAMENTO | G1: META | H1: PRÊMIO GANHO | I1: FILIAL | J1: SOLICITAÇÃO (E-MAIL) | K1: ASSUNTO (E-MAIL) | L1: PARÂMETRO
A2: 793 | B2: 04 - ABRIL | C2: 726 / 13552 | D2: 45748 | E2: 45777 | F2: MENSAL | G2: 0.01 | H2: 0.001 | I2: Não achou | J2: 45580 | K2: PARAMETRIZAR CAMPANHA - 726 E 13552 SUB | L2: TODOS OS BANCOS E TODOS OS PRODUTOS.-CREDITO 13522
A3: 794 | B3: 04 - ABRIL | C3: 15001 / 6935 | D3: 45748 | E3: 45777 | F3: MENSAL | G3: 900000 | H3: 0.0015 | I3: FILIAL BH1 | J3: 45705 | K3: PARAMETRIZAR CAMPANHA - ID 15001/6935 | L3: PRODUCAO TOTAL ATINGIR A META- BONIFICACAO PRODUCAO TOTAL EXCETO ITAU NOVO E PORTABILIDADE -CREDITO 15001
A4: 795 | B4: 04 - ABRIL | C4: 12340 | D4: 45748 | E4: 45777 | F4: MENSAL | G4: 300.000/ 500.000,00 | H4: 0,1% / 0,20 % | I4: FILIAL UBERLANDIA | J4: 45705 | K4: PARAMETRIZAR CAMPANHA - ID 12340 | L4: TODA A PRODUÇÃO
A5: 796 | B5: 04 - ABRIL | C5: 8835 | D5: 45748 | E5: 45777 | F5: MENSAL | G5: 0.01 | H5: 32 | I5: FILIAL UBERLANDIA | J5: 45716 | K5: PARAMETRIZAR CAMPANHA - ID 8835 - REEMBOLSO DE TED | L5: REMBOLSO DE TED
A6: 797 | B6: 04 - ABRIL | C6: 1427 | D6: 45748 | E6: 45777 | F6: MENSAL | G6: 0.01 | H6: 0.0045 | I6: FILIAL SP | J6: 45721 | K6: PARAMETRIZAR CAMPANHA - ID 1427 - BANCO FACTA | L6: Facta / INSS / Novo / 96, 84, 72 Facta / INSS / Refin de Port / 40 a 96
A7: 798 | B7: 04 - ABRIL | C7: 7460 / 12006 | D7: 45748 | E7: 45777 | F7: MENSAL | G7: 800000 | H7: 0.001 | I7: FILIAL BH2 | J7: 45730 | K7: PARAMETRIZAR CAMPANHA - 7460 / 12006 | L7: PRODUÇÃO TOTAL - PAGAMENTO DA BONIFICAÇÃO EM AMBOS OS CODIGOS 7460 / 12006-CODIGO 7460 EXCTO REFIN PORTABILIDADE MEU CREDBANK
A8: 799 | B8: 04 - ABRIL | C8: 3184 / 12430 | D8: 45748 | E8: 45777 | F8: MENSAL | G8: 300000 | H8: 0.002 | I8: FILIAL UBERLANDIA | J8: 45721 | K8: PARAMETRIZAR CAMPANHA - ID 3184/12430 | L8: PRODUCAO TOTAL PARA ATINGIR A META E CONTABILIZAR-META DESCONSIDERAR BMG E C6 ( INSS /NOVO )
A9: 800 | B9: 04 - ABRIL | C9: 4310 / 13955 | D9: 45748 | E9: 45777 | F9: MENSAL | G9: 300000 | H9: 0.004 | I9: FILIAL BH2 | J9: 45728 | K9: PARAMETRIZAR CAMPNAHA - BANCO FACTA - ID 4310 /13955 | L9: IREMOS CONSIDERAR TODA A PRODUÇÃO / EXCETO AS TABELAS QUE POSSUEM VIP-credito 14603
A10: 801 | B10: 04 - ABRIL | C10: 7934 | D10: 45748 | E10: 45777 | F10: MENSAL | G10: 1000 | H10: 0.002 | I10: FILIAL BH2 | J10: 45734 | K10: PARAMETRIZAR CAMPANHA - ID 7934 - TODA A PRODUÇÃO | L10: TODO A PRODUÇÃO
A11: 802 | B11: 04 - ABRIL | C11: 10649 | D11: 45736 | E11: 45768 | F11: MENSAL | G11: 170000 | H11: 0.002 | I11: FILIAL JOAO PESSOA | J11: 45736 | K11: PARAMETRIZAR CAMPANHA - ID: 10649 | L11: NOVOS INSS TABELAS PRINCIPAIS COM E SEM SEGURO: C6 ,FACTA , CREDBANK, PRESENÇA E VCTEX
A12: 803 | B12: 04 - ABRIL | C12: 10649 | D12: 45736 | E12: 45768 | F12: MENSAL | G12: 200000 | H12: 0.003 | I12: FILIAL VITORIA | J12: 45736 | K12: PARAMETRIZAR CAMPANHA - ID: 10649 | L12: NOVOS INSS TABELAS PRINCIPAIS COM E SEM SEGURO: C6 ,FACTA , CREDBANK, PRESENÇA E VCTEX
A13: 804 | B13: 04 - ABRIL | C13: 1729 / 8125 | D13: 45748 | E13: 45777 | F13: MENSAL | G13: 600000 | H13: 0.005 | I13: FILIAL VITORIA | J13: 45737 | K13: PARAMETRIZAR CAMPANHA - ID: 1729 / 8125 - REF: MARÇO 2025 | L13: PRODUCAO TOTAL -CREDITO 1729
A14: 805 | B14: 04 - ABRIL | C14: 12765 | D14: 45748 | E14: 45777 | F14: MENSAL | G14: 1000000 | H14: 0 | I14: FILIAL BH2 | J14: 45740 | K14: Re: Antecipação de valores RL Rangel Serviços LTDA - 12765 (Projeto de ampliação Call Center) | L14: CALCULAR TODA PRODUCAO- CASO ATINJA OU NÃO, APENAS RETORNAR NO E-MAIL COMUNICANDO A PRODUÇÃO
A15: 806 | B15: 04 - ABRIL | C15: 17270 | D15: 45748 | E15: 45777 | F15: MENSAL | G15: 100000 | H15: 0.004 | I15: FILIAL VITORIA | J15: 45748 | K15: PARAMETRIZAR CAMPANHA - ID 17270 - BANCO C6 | L15: C6 – INSS – NOVO – 84X A 96X
A16: 807 | B16: 04 - ABRIL | C16: 8336 | D16: 45748 | E16: 45777 | F16: MENSAL | G16: 0.01 | H16: 0.02 | I16: FILIAL MANAUS | J16: 45748 | K16: PARAMETRIZAR CAMPANHA - ID 8336 - BANCO AMIGOZ | L16: AMIGOZ-Conforme Campanha do Banco para RMC e RCC INSS.
A17: 808 | B17: 04 - ABRIL | C17: 13016 | D17: 45748 | E17: 45777 | F17: MENSAL | G17: 100000 | H17: 0.002 | I17: FILIAL SP CAPITAL | J17: 45748 | K17: PARAMETRIZAR CAMPANHA - ID: 13016 - REF: MARÇO 2025 | L17: NOVO INSS FACTA- TODAS AS TABELAS POSSÍVEIS- 84X e 96x
A18: 809 | B18: 04 - ABRIL | C18: 13016 | D18: 45748 | E18: 45777 | F18: MENSAL | G18: 87500 | H18: 0.0015 | I18: FILIAL BH1 | J18: 45748 | K18: PARAMETRIZAR CAMPANHA - ID: 13016 - REF: MARÇO 2025 | L18: NOVO INSS FACTA- TODAS AS TABELAS POSSÍVEIS- 84X e 96x
A19: 810 | B19: 04 - ABRIL | C19: 13016 | D19: 45748 | E19: 45777 | F19: MENSAL | G19: 75000 | H19: 0.001 | I19: FILIAL BH1 | J19: 45748 | K19: PARAMETRIZAR CAMPANHA - ID: 13016 - REF: MARÇO 2025 | L19: NOVO INSS FACTA- TODAS AS TABELAS POSSÍVEIS- 84X e 96x
A20: 811 | B20: 04 - ABRIL | C20: 11652 | D20: 45748 | E20: 45754 | F20: MENSAL | G20: 0.01 | H20: 0.01 | I20: FILIAL BH1 | J20: 45748 | K20: PARAMETRIZAR CAMPNHA - ID 11652/ 10090/14533/16839/4629/16775 - REF ABRIL DAYCOVAL /MEU CREDBANK | L20: TODA PRODUÇÃO DO MEU CRED BANk
A21: 812 | B21: 04 - ABRIL | C21: 11652 | D21: 45748 | E21: 45777 | F21: MENSAL | G21: 0.01 | H21: 0.0025 | I21: FILIAL SAO LUIZ | J21: 45748 | K21: PARAMETRIZAR CAMPNHA - ID 11652/ 10090/14533/16839/4629/16775 - REF ABRIL DAYCOVAL /MEU CREDBANK | L21: DAYCOVAL - NOVO - INSS PRAZO 84 E 96X
A22: 813 | B22: 04 - ABRIL | C22: 10090 | D22: 45748 | E22: 45777 | F22: MENSAL | G22: 0.01 | H22: 0.01 | I22: FILIAL SAO LUIZ | J22: 45748 | K22: PARAMETRIZAR CAMPNHA - ID 11652/ 10090/14533/16839/4629/16775 - REF ABRIL DAYCOVAL /MEU CREDBANK | L22: TODA PRODUÇÃO DO MEU CRED BANk-PRODUTO INSS-NOVO(ATE A DATA 07/04 CONFORME EMAIL: Campanhas MEUCRED BANK-DEMAIS PRODUTOS 30/04
A23: 814 | B23: 04 - ABRIL | C23: 14533 | D23: 45748 | E23: 45777 | F23: MENSAL | G23: 0.01 | H23: 0.01 | I23: FILIAL SAO LUIZ | J23: 45748 | K23: PARAMETRIZAR CAMPNHA - ID 11652/ 10090/14533/16839/4629/16775 - REF ABRIL DAYCOVAL /MEU CREDBANK | L23: TODA PRODUÇÃO DO MEU CRED BANk-PRODUTO INSS-NOVO(ATE A DATA 07/04 CONFORME EMAIL: Campanhas MEUCRED BANK-DEMAIS PRODUTOS 30/04
A24: 815 | B24: 04 - ABRIL | C24: 14533 | D24: 45748 | E24: 45777 | F24: MENSAL | G24: 0.01 | H24: 0.0025 | I24: FILIAL SAO LUIZ | J24: 45748 | K24: PARAMETRIZAR CAMPNHA - ID 11652/ 10090/14533/16839/4629/16775 - REF ABRIL DAYCOVAL /MEU CREDBANK | L24: DAYCOVAL - NOVO - INSS PRAZO 84 E 96X
A25: 816 | B25: 04 - ABRIL | C25: 16839 | D25: 45748 | E25: 45777 | F25: MENSAL | G25: 0.01 | H25: 0.01 | I25: FILIAL SAO LUIZ | J25: 45748 | K25: PARAMETRIZAR CAMPNHA - ID 11652/ 10090/14533/16839/4629/16775 - REF ABRIL DAYCOVAL /MEU CREDBANK | L25: TODA PRODUÇÃO DO MEU CRED BANk-PRODUTO INSS-NOVO(ATE A DATA 07/04 CONFORME EMAIL: Campanhas MEUCRED BANK-DEMAIS PRODUTOS 30/04
... A48: 839 | B48: 04 - ABRIL | C48: 16572 | D48: 45748 | E48: 45777 | F48: MENSAL | G48: 0.01 | H48: 0.003 | I48: FILIAL FORTALEZA | J48: 45749 | K48: PARAMETRIZAR CAMPANHA I JARVIS 16572 I BANCO MASTER | L48: BANCO MASTER SOMENTE EMPRÉSTIMOS GOV RIO - TODOS OS PRAZOS
A49: 840 | B49: 04 - ABRIL | C49: 3024 / 6839 | D49: 45748 | E49: 45777 | F49: MENSAL | G49: 0.01 | H49: 0.003 | I49: FILIAL RJ | J49: 45749 | K49: PARAMETRIZAR CAMPANHA - 3024 |6839 | L49: PRODUCAO TOTAL -EXCETO PAN -E TABELAS : AMIGOZ - PREFEITURA DE BELO HORIZONTE - CARTAO BENEFICIO COM SAQUE - AMIGOZ - PREFEITURA DE BELO HORIZONTE - CARTAO BENEFICIO COM SAQUE - COM SEGURO DIAMANTE -
A50: 841 | B50: 04 - ABRIL | C50: 14905 | D50: 45748 | E50: 45777 | F50: MENSAL | G50: 200000 | H50: 0.003 | I50: FILIAL BH2 | J50: 45749 | K50: PARAMETRIZAR CAMPANHA - ID: 14905 - REF: ABRIL | L50: PRODUCAO TOTAL ATINGIR A META - BONIFICACAO EXCETO PORTABILIDADE-PRODUCAO TOTAL BANCOS DAYCOVAL, PAN, VEMCARD, CASHCARD, FACTA, CREFAZ
A51: 842 | B51: 04 - ABRIL | C51: 14964 | D51: 45748 | E51: 45777 | F51: MENSAL | G51: 200000 | H51: 0.003 | I51: FILIAL SP | J51: 45743 | K51: PARAMETRIZAR CAMPANHA - ID 14964 | L51: DAYCOVAL, PAN, VEMCARD, MEU CASHCARD, FACTA, CREFAZ, MASTER-CARTÃO RMC, REFIN, REFIN/PORT, CARTÃO BENEFICIO-TODOS OS CONVENIOS
A52: 843 | B52: 04 - ABRIL | C52: 14129 | D52: 45748 | E52: 45777 | F52: MENSAL | G52: 1000 | H52: 0.0075 | I52: FILIAL SP | J52: 45750 | K52: PARAMETRIZAR CAMPANHA - ID: 14129 - REF: ABRIL 2025 | L52: BANCO FACTA - CONFORME REGULAMENTO
A53: 844 | B53: 04 - ABRIL | C53: 15087 | D53: 45748 | E53: 45777 | F53: MENSAL | G53: 30000 | H53: 0.005 | I53: FILIAL RJ | J53: 45750 | K53: PARAMETRIZAR CAMPANHA - ID: 15087 | L53: NOVO COM E SEM SEGURO \ PRESENÇA BANK \INSS\96 E 84 X
A54: 845 | B54: 04 - ABRIL | C54: 15802 | D54: 45748 | E54: 45777 | F54: MENSAL | G54: 1000 | H54: 0.015 | I54: FILIAL BELEM | J54: 45750 | K54: PARAMETRIZAR CAMPANHA I JARVIS 15802 l QUERO MAIS | L54: QUERO MAIS CRÉDITO- SIAPE-CARTÃO CONSIGNADO E CARTÃO BENEFICIO
A55: 846 | B55: 04 - ABRIL | C55: 16140 / 15156 | D55: 45748 | E55: 45777 | F55: MENSAL | G55: 200000 | H55: 0.002 | I55: FILIAL ESTRATEGICA | J55: 45750 | K55: PARAMETRIZAR CAMPANHA - ID: 16140 / 15156 | L55: todas propostas INSS digitadas no c6, contrato novo com pact e sem nos prazos 84 e 96-credito 16140
A56: 847 | B56: 04 - ABRIL | C56: 16140 / 15156 | D56: 45748 | E56: 45777 | F56: MENSAL | G56: 200000 | H56: 0.002 | I56: FILIAL RONDONIA | J56: 45750 | K56: PARAMETRIZAR CAMPANHA - ID: 16140 / 15156 | L56: todas propostas INSS digitadas no bmg, contrato novo e cartao benefício -credito 16140
A57: 848 | B57: 04 - ABRIL | C57: 16140 / 15156 | D57: 45748 | E57: 45777 | F57: MENSAL | G57: 200000 | H57: 0.002 | I57: FILIAL RONDONIA | J57: 45750 | K57: PARAMETRIZAR CAMPANHA - ID: 16140 / 15156 | L57: todas propostas INSS digitadas no pan, contrato novo e cartao benefício -credito 16140
A58: 849 | B58: 04 - ABRIL | C58: 16763 | D58: 45748 | E58: 45777 | F58: MENSAL | G58: 0.01 | H58: 0.01 | I58: FILIAL RONDONIA | J58: 45750 | K58: PARAMETRIZAR CAMPANHA I JARVIS 16763 I BANCO AMIGOZ | L58: AMIGOZ PRODUCAO TOTAL - exceto Prefeitura de Juiz de Fora / Prefeitura de Recife e TJ.
A59: 850 | B59: 04 - ABRIL | C59: 16457 | D59: 45748 | E59: 45777 | F59: MENSAL | G59: 300000 | H59: 0.005 | I59: FILIAL SP CAPITAL | J59: 45750 | K59: PARAMETRIZAR CAMPANHAS - ID- 16457 - REF: ABRIL 2025 | L59: PRODUCAO TOTAL ATINGIR A META-BONIFICACAO INSS-NOVO-84X-96-PRESENCA BANK E FACTA
A60: 851 | B60: 04 - ABRIL | C60: 14129 | D60: 45748 | E60: 45777 | F60: MENSAL | G60: 1000 | H60: 0.001 | I60: FILIAL VITORIA | J60: 45751 | K60: PARAMETRIZAR CAMPANHA - ID 14129 - CREDBANK | L60: CONSIDERAR PRODUÇÃO DO MEU CREDBANK REFIN DA PORTABILIDADE
A61: 852 | B61: 04 - ABRIL | C61: 15990 | D61: 45748 | E61: 45777 | F61: MENSAL | G61: 400000 | H61: 0.0025 | I61: FILIAL RJ | J61: 45754 | K61: PARAMETRIZAR CAMPANHA - ID: 15990 | L61: BANCO FACTA - INSS / FGTS - CONFORME REGULAMENTO
A62: 853 | B62: 04 - ABRIL | C62: 16537 | D62: 45748 | E62: 45777 | F62: MENSAL | G62: 800000 | H62: 0.0025 | I62: FILIAL SP CAPITAL | J62: 45754 | K62: PARAMETRIZAR CAMPANHA - 16537 | L62: BANCO FACTA - INSS / FGTS - CONFORME REGULAMENTO
A63: 854 | B63: 04 - ABRIL | C63: 16898 | D63: 45748 | E63: 45777 | F63: MENSAL | G63: 0.01 | H63: 0.0025 | I63: FILIAL SP CAPITAL | J63: 45754 | K63: PARAMETRIZAR CAMPANHA I JARVIS 16898 I BANCO FACTA | L63: BANCO FACTA - INSS / FGTS - CONFORME REGULAMENTO
A64: 855 | B64: 04 - ABRIL | C64: 17102 | D64: 45748 | E64: 45777 | F64: MENSAL | G64: 200000 | H64: 0.0025 | I64: FILIAL SP CAPITAL | J64: 45754 | K64: PARAMETRIZAR CAMPANHA l CÓDIGO 17102 l BANCO FACTA | L64: BANCO FACTA - CONFORME REGULAMENTO
A65: 856 | B65: 04 - ABRIL | C65: 15874 | D65: 45748 | E65: 45777 | F65: MENSAL | G65: 0.01 | H65: 0.005 | I65: FILIAL SP CAPITAL | J65: 45754 | K65: CAMPANHA QUERO MAIS CRÉDITO I 15874 IMETA SOLUÇÕES DE CRÉDITO E SERVIÇO I ABRIL | L65: QUERO MAIS/ INSS/CARTÃO RMC/CARTAO BENEFICIO/ TODAS AS TABELAS
A66: 857 | B66: 04 - ABRIL | C66: 16358 | D66: 45748 | E66: 45777 | F66: MENSAL | G66: 100000 | H66: 0.006 | I66: FILIAL BH2 | J66: 45754 | K66: PARAMETRIZAÇÃO CAMPANHA I BANCO FACTA I COD 16358 I ABRIL | L66: BANCO FACTA - CONFORME REGULAMENTO
A67: 858 | B67: 04 - ABRIL | C67: 17142 | D67: 45748 | E67: 45777 | F67: MENSAL | G67: 30000 | H67: 0.005 | I67: FILIAL SP CAPITAL | J67: 45754 | K67: PARAMETRIZAR CAMPANHA MASTER l CÓDIGO 17142 l BANCO MASTER | L67: MASTER-PRODUCAO TOTAL
A68: 859 | B68: 04 - ABRIL | C68: 16481 | D68: 45748 | E68: 45777 | F68: MENSAL | G68: 300000 | H68: 0.005 | I68: FILIAL BELEM | J68: 45754 | K68: PARAMETRIZAR CAMPANHA - ID 16481 - REF MARÇO | L68: PRODUCAO TOTAL ATINGIR A META,BONIFICACAO INSS-NOVO-84 E 96 - FACTA
A69: 860 | B69: 04 - ABRIL | C69: 16481 | D69: 45748 | E69: 45777 | F69: MENSAL | G69: 300000 | H69: 0.005 | I69: FILIAL VITORIA | J69: 45754 | K69: PARAMETRIZAR CAMPANHA - ID 16481 - REF MARÇO | L69: PRODUCAO TOTAL ATINGIR A META,BONIFICACAO INSS-NOVO-84 E 96 - PRESENCA BANK
... A74: 865 | B74: 04 - ABRIL | C74: 14722 | D74: 45748 | E74: 45777 | F74: MENSAL | G74: 10000 | H74: 0.0075 | I74: FILIAL RECIFE | J74: 45754 | K74: PARAMETRIZAR CAMPANHA - ID 14722 | L74: FACTA - INSS NOVO - PRAZO MAXIMO 96X
A75: 866 | B75: 04 - ABRIL | C75: 2911 / 11402 | D75: 45748 | E75: 45777 | F75: MENSAL | G75: 0.01 | H75: 0.002 | I75: FILIAL RECIFE | J75: 45754 | K75: PARAMETRIZAR CAMPANHA - 2911 E 11402 - ABRIL 2025 | L75: TODOS BANCOS / INSS-SIAPE/novo / port/refin de port /cartao rmc /cartao benefcio / 84X TODAS AS TABELASCREDITO 2911
A76: 867 | B76: 04 - ABRIL | C76: 12679 | D76: 45748 | E76: 45777 | F76: MENSAL | G76: 150000 | H76: 100 | I76: FILIAL BH1 | J76: 45754 | K76: PARAMETRIZAR CAMPANHA - ISENÇÃO COBRANÇA TARIFA - ID: 12679 - ABRIL 2025 | L76: PRODUCAO TOTAL
A77: 868 | B77: 04 - ABRIL | C77: 15086 | D77: 45748 | E77: 45777 | F77: MENSAL | G77: 1000 | H77: 0.005 | I77: FILIAL FORTALEZA | J77: 45755 | K77: PARAMETRIZAR CAMPANHA I JARVIS 15086 E 5804 | L77: BANCO FACTA - CONFORME REGULAMENTO
A78: 869 | B78: 04 - ABRIL | C78: 5804 | D78: 45748 | E78: 45777 | F78: MENSAL | G78: 1000 | H78: 0.005 | I78: FILIAL JOAO PESSOA | J78: 45755 | K78: PARAMETRIZAR CAMPANHA I JARVIS 15086 E 5804 | L78: BANCO MEU CREDBANK - INSS – APENAS TABELAS COM SEGURO.
A79: 870 | B79: 04 - ABRIL | C79: 15086 | D79: 45748 | E79: 45777 | F79: MENSAL | G79: 0.01 | H79: 0.02 | I79: FILIAL JOAO PESSOA | J79: 45755 | K79: PARAMETRIZAR CAMPANHA I JARVIS 15086 E 5804 | L79: MEU CASH CARD - TODAS OS PRODUTOS E TABELAS
A80: 871 | B80: 04 - ABRIL | C80: 16988 | D80: 45748 | E80: 45777 | F80: MENSAL | G80: 0.01 | H80: 0.0075 | I80: FILIAL JOAO PESSOA | J80: 45754 | K80: Re: CAMPANHA MES ABRIL 2025 - FACTA - GM PROMOTORA 16988 (ERICK VIEIRA) | L80: BANCO FACTA - CONFORME REGULAMENTO
A81: 872 | B81: 04 - ABRIL | C81: 17184 | D81: 45748 | E81: 45777 | F81: MENSAL | G81: 1000 | H81: 0.035 | I81: FILIAL SP CAPITAL | J81: 45756 | K81: PARAMETRIZAR CAMPANHA - ID 17184 - BANCO AMIGOZ | L81: AMIGOS-PRODUCAO TOTAL
A82: 873 | B82: 04 - ABRIL | C82: 11449 / 14895 | D82: 45748 | E82: 45777 | F82: MENSAL | G82: 500000 | H82: 0.0015 | I82: FILIAL BH2 | J82: 45756 | K82: PARAMETRIZAR CAMPANHA - 11449 / 14895 sub | L82: PRODUCAO TOTAL ATINGIR A META- BONIFICACAO , POREM PAGAREMOS SOMENTE SOBRE MARGEM LIVRE TODOS CONVENIOS -CREDITO 11449
A83: 874 | B83: 04 - ABRIL | C83: 15463 / 5407 | D83: 45748 | E83: 45777 | F83: MENSAL | G83: 400000 | H83: 0.0015 | I83: FILIAL GOIANIA | J83: 45756 | K83: PARAMETRIZAR CAMPANHA - ID 15463/5407 | L83: PAGAR BÔNUS SOBRE TODA PRODUÇÃO-EXCETO ITAU-INSS-CREDITO 5407
A84: 875 | B84: 04 - ABRIL | C84: 14341 | D84: 45748 | E84: 45777 | F84: MENSAL | G84: 50000 | H84: 160 | I84: FILIAL GOIANIA | J84: 45756 | K84: PARAMETRIZAR CAMPANHA - ID 14341 | L84: PRODUCAO TOTAL
A85: 876 | B85: 04 - ABRIL | C85: 13215 | D85: 45748 | E85: 45754 | F85: MENSAL | G85: 1000 | H85: 0.01 | I85: FILIAL ARACAJU | J85: 45756 | K85: PARAMETRIZAR CAMPANHA - ID 13215 - MEU CREDBANK | L85: MEU CREDBANK - INSS - MEU CREDBANK - INSS - FP - SEGURO PLUS - TAXA 1,80 MEU CREDBANK - INSS - MEU CREDBANK - INSS - FP - SEGURO - TX 1,80
A86: 877 | B86: 04 - ABRIL | C86: 7274 | D86: 45748 | E86: 45777 | F86: MENSAL | G86: 0.01 | H86: 0.01 | I86: FILIAL ARACAJU | J86: 45749 | K86: PARAMETRIZAR CAMPANHA - BANCO PRESENÇA - ID 7274 / 14876 | L86: PRESENÇA BANCO / INSS / TODAS TABELAS E PRAZOS-NOVO
A87: 878 | B87: 04 - ABRIL | C87: 14876 | D87: 45748 | E87: 45777 | F87: MENSAL | G87: 0.01 | H87: 0.005 | I87: FILIAL NATAL | J87: 45749 | K87: PARAMETRIZAR CAMPANHA - BANCO PRESENÇA - ID 7274 / 14876 | L87: PRESENÇA BANCO / INSS / TODAS TABELAS E PRAZOS-NOVO
A88: 879 | B88: 04 - ABRIL | C88: 7274 | D88: 45748 | E88: 45754 | F88: MENSAL | G88: 0.01 | H88: 0.01 | I88: FILIAL NATAL | J88: 45756 | K88: PARAMETRIZAR CAMPANHA - MEU CREDBANK / FACTA - ID 7274 | L88: MEUCREDBANK / INSS novo / tabelas com seguro top
A89: 880 | B89: 04 - ABRIL | C89: 7274 | D89: 45755 | E89: 45777 | F89: MENSAL | G89: 300000 | H89: 0.005 | I89: FILIAL NATAL | J89: 45756 | K89: PARAMETRIZAR CAMPANHA - MEU CREDBANK / FACTA - ID 7274 | L89: producao total
A90: 881 | B90: 04 - ABRIL | C90: 7274 | D90: 45748 | E90: 45777 | F90: MENSAL | G90: 0.01 | H90: 0.0075 | I90: FILIAL NATAL | J90: 45756 | K90: PARAMETRIZAR CAMPANHA - MEU CREDBANK / FACTA - ID 7274 | L90: BANCO FACTA - INSS - CONFORME REGULAMENTO
A91: 882 | B91: 04 - ABRIL | C91: 13063 | D91: 45748 | E91: 45777 | F91: MENSAL | G91: 50000 | H91: 0.005 | I91: FILIAL NATAL | J91: 45756 | K91: PARAMETRIZAR CAMPANHA - 13063 | L91: PRODUCAO TOTAL ATINGIR A META- PRODUCAO TOTAL BMG NOVO.CARTOES, RMC -RCC
A92: 883 | B92: 04 - ABRIL | C92: 8687 | D92: 45748 | E92: 45777 | F92: MENSAL | G92: 0.01 | H92: 0.001 | I92: FILIAL VITORIA | J92: 45756 | K92: PARAMETRIZAR CAMPANHA - GC EDVAN | L92: BANCO FACTA - INSS - CONFORME REGULAMENTO
A93: 884 | B93: 04 - ABRIL | C93: 10461 | D93: 45748 | E93: 45777 | F93: MENSAL | G93: 0.01 | H93: 0.01 | I93: FILIAL FORTALEZA | J93: 45756 | K93: PARAMETRIZAR CAMPANHA - GC EDVAN | L93: BANCO QUERO MAIS CRÉDITO - INSS - CARTÃO RMC e CB
A94: 885 | B94: 04 - ABRIL | C94: 12385 | D94: 45748 | E94: 45777 | F94: MENSAL | G94: 0.01 | H94: 0.01 | I94: FILIAL FORTALEZA | J94: 45756 | K94: PARAMETRIZAR CAMPANHA - GC EDVAN | L94: BANCO QUERO MAIS CRÉDITO - INSS - CARTÃO RMC e CB
A95: 886 | B95: 04 - ABRIL | C95: 12385 | D95: 45748 | E95: 45777 | F95: MENSAL | G95: 0.01 | H95: 0.005 | I95: FILIAL SAO LUIZ | J95: 45756 | K95: PARAMETRIZAR CAMPANHA - GC EDVAN | L95: BANCO FACTA - INSS - CONFORME REGULAMENTO
... A108: 903 | B108: 04 - ABRIL | C108: 16458 | D108: 45748 | E108: 45777 | F108: MENSAL | G108: 100000 | H108: 0.0025 | I108: FILIAL PORTO ALEGRE | J108: 45757 | K108: PARAMETRIZAR CAMPANHA - 16458 | L108: BANCO FACTA - CONFORME REGULAMENTO
A109: 904 | B109: 04 - ABRIL | C109: 12291 / 16101 | D109: 45748 | E109: 45777 | F109: MENSAL | G109: 500000 | H109: 0.005 | I109: FILIAL SP CAPITAL | J109: 45751 | K109: PARAMETRIZAR CAMPANHA I JARVIS 12291 / 16101 I BANCO FACTA | L109: ENGLOBAR TODA A PRODUÇÃO PARA A META E PAGAMENTO /FACTA/INSS/NOVO/ TODOS OS PRAZOS-credito 16101
A110: 905 | B110: 04 - ABRIL | C110: 10293 | D110: 45748 | E110: 45777 | F110: MENSAL | G110: 1000 | H110: 0.005 | I110: FILIAL BOA VISTA | J110: 45757 | K110: PARAMETRIZAR CAMPANHA - 10293 | L110: Presença Bank – NOVO – INSS – Todas as Tabelas/ Presença Bank – NOVO – SIAPE– Todas as Tabelas
A111: 906 | B111: 04 - ABRIL | C111: 13977 | D111: 45748 | E111: 45777 | F111: MENSAL | G111: 100 | H111: 0.0015 | I111: FILIAL JOAO PESSOA | J111: 45756 | K111: PARAMETRIZAR CAMPANHA - CODIGO 13977 - ABRIL | L111: BANCO FACTA - CONFORME REGULAMENTO
A112: 907 | B112: 04 - ABRIL | C112: 16186 | D112: 45756 | E112: 45777 | F112: MENSAL | G112: 100000 | H112: 0.005 | I112: FILIAL PIAUI | J112: 45756 | K112: PARAMETRIZAR CAMPANHA I JARVIS 16186 I BANCO C6 | L112: CONSIDERAR TODA A PRODUÇAO PARA APURAÇAO, MAS PAGAREMOS SOBRE O REFIN INSS DO BANCO C6
A113: 908 | B113: 04 - ABRIL | C113: 12805 | D113: 45748 | E113: 45777 | F113: MENSAL | G113: 250000 | H113: 0.003 | I113: FILIAL GOIANIA | J113: 45757 | K113: PARAMETRIZAR CAMPANHA I JARVIS 12805 I BANCO FACTA | L113: BANCO FACTA - CONFORME REGULAMENTO
A114: 909 | B114: 04 - ABRIL | C114: 15574 | D114: 45748 | E114: 45777 | F114: MENSAL | G114: 150000 | H114: 0.0025 | I114: FILIAL BH2 | J114: 45757 | K114: PARAMETRIZAR CAMPANHA - 15574 | L114: INSS NOVO – PRESENÇA BANK / C6 BANK / FACTA-EXCETO TABELAS QUE CONSTAM NA VIP
A115: 910 | B115: 04 - ABRIL | C115: 13900 | D115: 45748 | E115: 45777 | F115: MENSAL | G115: 0.01 | H115: 0.001 | I115: FILIAL SP | J115: 45757 | K115: CAMPANHA BANCO FACTA I 13900 I FEVEREIRO I G&S SERVIÇOS LTDA-ME | L115: BANCO FACTA - CONFORME REGULAMENTO
A116: 911 | B116: 04 - ABRIL | C116: 16537 | D116: 45748 | E116: 45777 | F116: MENSAL | G116: 800000 | H116: 0.0025 | I116: FILIAL FORTALEZA | J116: 45758 | K116: PARAMETRIZAR CAMPANHA - ID: 16537 - REF: ABRIL 2025 | L116: NOVO INSS TODOS OS BANCOS NO PRAZO 84 E 96 MESES (com exceção dos que estão na tabela VIP.
A117: 912 | B117: 04 - ABRIL | C117: 6706 | D117: 45748 | E117: 45777 | F117: MENSAL | G117: 100000 | H117: 0.0025 | I117: FILIAL SP CAPITAL | J117: 45758 | K117: PARAMETRIZAR CAMPANHA - 6706 | L117: TODOS OS BANCOS INSS- NOVO- PRAZOS 84 E 96-exceto tabelas que constam na vip
A118: 913 | B118: 04 - ABRIL | C118: 1818 | D118: 45748 | E118: 45777 | F118: MENSAL | G118: 500000 | H118: 0.002 | I118: FILIAL SP CAPITAL | J118: 45758 | K118: PARAMETRIZAR CAMPANHA - 1818 | L118: PRODUCAO TOTAL - EXCETO TABELAS QUE CONSTAM NA VIP
A119: 914 | B119: 04 - ABRIL | C119: 15990 | D119: 45748 | E119: 45777 | F119: MENSAL | G119: 400000 | H119: 0.0025 | I119: FILIAL BH2 | J119: 45758 | K119: PARAMETRIZAR CAMPANHA - ID: 15990 | L119: TODAS AS OPERAÇÕES INSS - BANCO MASTER - EXCETO TABELAS QUE POSSUEM REGRAS VIP
A120: 915 | B120: 04 - ABRIL | C120: 16010 | D120: 45748 | E120: 45777 | F120: MENSAL | G120: 150000 | H120: 0.0025 | I120: FILIAL SP CAPITAL | J120: 45758 | K120: PARAMETRIZAR CAMPANHA - ID: 16010 - REF: ABRIL 2025 | L120: TODAS AS OPERAÇÕES INSS – GOVERNO – PREFEITURA - TODOS OS BANCOS - SOMENTE CONTRATO NOVO
